Workbook

Sheet Calc
L1: Row | M1: 46 | N1: 67 | P1: 81 | Q1: 104 | S1: 115 | T1: 142 | W1: 169
B2: Lansdowne | M2: Based on SQM | P2: Based on Asset Value (Fixed Based on Weighted Age/Asset/risk) | S2: Based on % minutes worked | V2: Based on % Staff | Z2: Total | AD2: Total Per Minute | BB2: Ave Increase
A3: Date:2017/10/17 10:28 | C3: Asset Value | D3: SQM | M3: Fixed | N3: Variable | P3: Fixed | Q3: Variable | S3: Fixed | T3: Variable | V3: Fixed | W3: Variable | Y3: Wages | Z3: Fixed | AA3: Variable | AC3: Wages | AD3: Fixed | AE3: Variable | AF3: Current | AH3: % Change | AJ3: Syspro | AK3: 46054 | AL3: 45870 | AM3: 45689 | AN3: 45323 | AO3: 45199 | AP3: 44958 | AQ3: 44927 | AR3: 44804 | AS3: 44620 | AT3: 44440 | AU3: 44248 | AV3: 43862 | AW3: 43497 | AX3: 43132 | AY3: 42767 | AZ3: 42401 | BB3: =AVERAGE(BB5:BB116) -> #DIV/0!
A4: Work center | B4: Description | F4: Qty | G4: Sum | I4: Old Cost per Min | J4: Labour Price per Man Minute | L4: Minutes worked per year | M4: =HLOOKUP($B$14,Overhead!$E:$E,M$1,FALSE) -> 301413.49 | N4: =HLOOKUP($B$14,Overhead!$E:$E,N$1,FALSE) -> 19679.793 | P4: =HLOOKUP($B$14,Overhead!$E:$E,P$1,FALSE) -> 151950.61 | Q4: =HLOOKUP($B$14,Overhead!$E:$E,Q$1,FALSE) -> 177767.45 | S4: =HLOOKUP($B$14,Overhead!$E:$E,S$1,FALSE) -> 691435.62 | T4: =HLOOKUP($B$14,Overhead!$E:$E,T$1,FALSE) -> 256024.4 | W4: =HLOOKUP($B$14,Overhead!$E:$E,W$1,FALSE) -> 75138.443 | Y4: =SUM(Y5:Y13) -> 3601081.3 | Z4: =+M4+P4+S4+V4 -> 1144799.7 | AA4: =+N4+Q4+T4+W4 -> 528610.09
A5: M00001 | B5: Bending Brakes and PS00005 | C5: =SUMIF('Asset Allocation'!$F$1:$I$270,Calc!A5,'Asset Allocation'!I:I) -> 2342981.9 | D5: 77 | E5: M00001 | F5: =SUMIF(Wages!$O$2:$P$220,Calc!E5,Wages!$P$2:$P$220) -> 2.55 | G5: =SUMIF(Wages!$O$2:$AD$192,Calc!E5,Wages!$AD$2:$AD$192) -> 1197334.5 | I5: 2.02 | J5: =+G5/L5 -> 4.0758935 | L5: =+F5*40*48*60 -> 293760 | M5: =+D5/$D$14*M$4 -> 69696.211 | N5: =+D5/$D$14*N$4 -> 4550.5827 | P5: =+C5/$C$14*$P$4 -> 113851.01 | Q5: =+$Q$4*C5/$C$14 -> 133194.62 | S5: =+L5/$L$14*$S$4 -> 192695.17 | T5: =+L5/$L$14*$T$4 -> 71351.064 | W5: =+F5/$F$14*$W$4 -> 20940.222 | Y5: =+G5 -> 1197334.5 | Z5: =+M5+P5+S5+V5 -> 376242.39 | AA5: =+N5+Q5+T5+W5 -> 230036.49 | AC5: =+Y5/L5 -> 4.0758935 | AD5: =+Z5/$L5 -> 1.2807816 | AE5: =+AA5/$L5 -> 0.78307628 | AF5: =SUM(AC5:AE5) -> 6.1397513 | AG5: x | AH5: =+(AF5-AJ5)/AJ5 -> -4.0497278e-05 | AJ5: =VLOOKUP(E5,Syspro!$A$2:$F$91,6,FALSE) -> 6.14 | AK5: 7.52 | AL5: 7.0896489 | AM5: 6.56 | AN5: 4.53 | AO5: 4.02 | AP5: 4.0202097 | AQ5: 3.93 | AR5: 3.75 | AS5: 3.75 | AT5: 3.96 | AU5: 3.88 | AV5: 4.45 | AW5: 4.0724898 | AX5: 3.7362698 | AY5: 3.49 | AZ5: 3.03 | BB5: =(+AF5-AJ5)/AJ5 -> -4.0497278e-05
A6: M00002 | B6: Spot Welding and PS00006 | C6: =SUMIF('Asset Allocation'!$F$1:$I$270,Calc!A6,'Asset Allocation'!I:I) -> 207705.78 | D6: 22 | E6: M00002 | F6: =SUMIF(Wages!$O$2:$P$220,Calc!E6,Wages!$P$2:$P$220) -> 1.3 | G6: =SUMIF(Wages!$O$2:$AD$192,Calc!E6,Wages!$AD$2:$AD$192) -> 469995.19 | I6: 2.02 | J6: =+G6/L6 -> 3.1383226 | L6: =+F6*40*48*60 -> 149760 | M6: =+D6/$D$14*M$4 -> 19913.203 | N6: =+D6/$D$14*N$4 -> 1300.1665 | P6: =+C6/$C$14*$P$4 -> 10092.913 | Q6: =+$Q$4*C6/$C$14 -> 11807.728 | S6: =+L6/$L$14*$S$4 -> 98236.754 | T6: =+L6/$L$14*$T$4 -> 36375.052 | W6: =+F6/$F$14*$W$4 -> 10675.407 | Y6: =+G6 -> 469995.19 | Z6: =+M6+P6+S6+V6 -> 128242.87 | AA6: =+N6+Q6+T6+W6 -> 60158.354 | AC6: =+Y6/L6 -> 3.1383226 | AD6: =+Z6/$L6 -> 0.85632259 | AE6: =+AA6/$L6 -> 0.40169841 | AF6: =SUM(AC6:AE6) -> 4.3963435 | AG6: x | AH6: =+(AF6-AJ6)/AJ6 -> -0.00083101205 | AJ6: =VLOOKUP(E6,Syspro!$A$2:$F$91,6,FALSE) -> 4.4 | AK6: 4.42 | AL6: 3.9685487 | AM6: 4.15 | AN6: 4.37 | AO6: 4.07 | AP6: 4.0710459 | AQ6: 3.9 | AR6: 3.73 | AS6: 3.73 | AT6: 3.47 | AU6: 3.44 | AV6: 4.59 | AW6: 4.0315629 | AX6: 3.4428349 | AY6: 3.49 | AZ6: 3.03 | BB6: =(+AF6-AJ6)/AJ6 -> -0.00083101205
A7: M00003 | B7: Grinding Stations and PS00007 | C7: =SUMIF('Asset Allocation'!$F$1:$I$270,Calc!A7,'Asset Allocation'!I:I) -> 53256 | D7: 53 | E7: M00003 | F7: =SUMIF(Wages!$O$2:$P$220,Calc!E7,Wages!$P$2:$P$220) -> 0.25 | G7: =SUMIF(Wages!$O$2:$AD$192,Calc!E7,Wages!$AD$2:$AD$192) -> 80042.533 | I7: 2.02 | J7: =+G7/L7 -> 2.7792546 | L7: =+F7*40*48*60 -> 28800 | M7: =+D7/$D$14*M$4 -> 47972.717 | N7: =+D7/$D$14*N$4 -> 3132.2193 | P7: =+C7/$C$14*$P$4 -> 2587.8345 | Q7: =+$Q$4*C7/$C$14 -> 3027.5149 | S7: =+L7/$L$14*$S$4 -> 18891.684 | T7: =+L7/$L$14*$T$4 -> 6995.2023 | W7: =+F7/$F$14*$W$4 -> 2052.9629 | Y7: =+G7 -> 80042.533 | Z7: =+M7+P7+S7+V7 -> 69452.235 | AA7: =+N7+Q7+T7+W7 -> 15207.899 | AC7: =+Y7/L7 -> 2.7792546 | AD7: =+Z7/$L7 -> 2.4115359 | AE7: =+AA7/$L7 -> 0.52805206 | AF7: =SUM(AC7:AE7) -> 5.7188426 | AG7: x | AH7: =+(AF7-AJ7)/AJ7 -> -0.00020234211 | AJ7: =VLOOKUP(E7,Syspro!$A$2:$F$91,6,FALSE) -> 5.72 | AK7: 5.71 | AL7: 5.3915324 | AM7: 5.34 | AN7: 4.06 | AO7: 2.96 | AP7: 2.9592541 | AQ7: 3.82 | AR7: 3.63 | AS7: 3.63 | AT7: 4.76 | AU7: 4.03 | AV7: 4.14 | AW7: 4.1095591 | AX7: 3.7789618 | AY7: 3.49 | AZ7: 3.03 | BB7: =(+AF7-AJ7)/AJ7 -> -0.00020234211
A8: M00004 | B8: Notching an PS00008 | C8: =SUMIF('Asset Allocation'!$F$1:$I$270,Calc!A8,'Asset Allocation'!I:I) -> 12700 | D8: 4 | E8: M00004 | F8: =SUMIF(Wages!$O$2:$P$220,Calc!E8,Wages!$P$2:$P$220) -> 0.25 | G8: =SUMIF(Wages!$O$2:$AD$192,Calc!E8,Wages!$AD$2:$AD$192) -> 80042.533 | I8: 2.02 | J8: =+G8/L8 -> 2.7792546 | L8: =+F8*40*48*60 -> 28800 | M8: =+D8/$D$14*M$4 -> 3620.5824 | N8: =+D8/$D$14*N$4 -> 236.39391 | P8: =+C8/$C$14*$P$4 -> 617.12292 | Q8: =+$Q$4*C8/$C$14 -> 721.97386 | S8: =+L8/$L$14*$S$4 -> 18891.684 | T8: =+L8/$L$14*$T$4 -> 6995.2023 | W8: =+F8/$F$14*$W$4 -> 2052.9629 | Y8: =+G8 -> 80042.533 | Z8: =+M8+P8+S8+V8 -> 23129.389 | AA8: =+N8+Q8+T8+W8 -> 10006.533 | AC8: =+Y8/L8 -> 2.7792546 | AD8: =+Z8/$L8 -> 0.80310378 | AE8: =+AA8/$L8 -> 0.34744906 | AF8: =SUM(AC8:AE8) -> 3.9298074 | AG8: x | AH8: =+(AF8-AJ8)/AJ8 -> -4.899607e-05 | AJ8: =VLOOKUP(E8,Syspro!$A$2:$F$91,6,FALSE) -> 3.93 | AK8: 3.94 | AL8: 3.690239 | AM8: 3.63 | AN8: 4.09 | AO8: 3.89 | AP8: 3.8938812 | AQ8: 3.8 | AR8: 3.58 | AS8: 3.58 | AT8: 3.63 | AU8: 3.55 | AV8: 5.12 | AW8: 4.7102179 | AX8: 4.1179881 | AY8: 3.49 | AZ8: 3.03 | BB8: =(+AF8-AJ8)/AJ8 -> -4.899607e-05
A9: M00014 | B9: Guilotene | C9: =SUMIF('Asset Allocation'!$F$1:$I$270,Calc!A9,'Asset Allocation'!I:I) -> 262767.15 | D9: 89 | E9: M00014 | F9: =SUMIF(Wages!$O$2:$P$220,Calc!E9,Wages!$P$2:$P$220) -> 1 | G9: =SUMIF(Wages!$O$2:$AD$192,Calc!E9,Wages!$AD$2:$AD$192) -> 458354.62 | I9: 2.02 | J9: =+G9/L9 -> 3.9787727 | L9: =+F9*40*48*60 -> 115200 | M9: =+D9/$D$14*M$4 -> 80557.959 | N9: =+D9/$D$14*N$4 -> 5259.7644 | P9: =+C9/$C$14*$P$4 -> 12768.475 | Q9: =+$Q$4*C9/$C$14 -> 14937.875 | S9: =+L9/$L$14*$S$4 -> 75566.734 | T9: =+L9/$L$14*$T$4 -> 27980.809 | W9: =+F9/$F$14*$W$4 -> 8211.8517 | Y9: =+G9 -> 458354.62 | Z9: =+M9+P9+S9+V9 -> 168893.17 | AA9: =+N9+Q9+T9+W9 -> 56390.3 | AC9: =+Y9/L9 -> 3.9787727 | AD9: =+Z9/$L9 -> 1.4660865 | AE9: =+AA9/$L9 -> 0.48949914 | AF9: =SUM(AC9:AE9) -> 5.9343584 | AG9: x | AH9: =+(AF9-AJ9)/AJ9 -> -0.00094976421 | AJ9: =VLOOKUP(E9,Syspro!$A$2:$F$91,6,FALSE) -> 5.94 | AK9: 5.96 | AL9: 5.6500617 | AM9: 5.5 | AN9: 4.44 | AO9: 4.24 | AP9: 4.244345 | AQ9: 3.97 | AR9: 3.53 | AS9: 3.53 | AT9: 4 | AU9: 3.92 | AV9: 4.79 | AW9: 4.7974945 | AX9: 4.5467463 | AY9: 3.49 | AZ9: 3.03 | BB9: =(+AF9-AJ9)/AJ9 -> -0.00094976421
A10: M00006 | B10: Rolling and PS00009 | C10: =SUMIF('Asset Allocation'!$F$1:$I$270,Calc!A10,'Asset Allocation'!I:I) -> 59200 | D10: 14 | E10: M00006 | F10: =SUMIF(Wages!$O$2:$P$220,Calc!E10,Wages!$P$2:$P$220) -> 1.35 | G10: =SUMIF(Wages!$O$2:$AD$192,Calc!E10,Wages!$AD$2:$AD$192) -> 355699.45 | I10: 2.02 | J10: =+G10/L10 -> 2.2871621 | L10: =+F10*40*48*60 -> 155520 | M10: =+D10/$D$14*M$4 -> 12672.038 | N10: =+D10/$D$14*N$4 -> 827.37868 | P10: =+C10/$C$14*$P$4 -> 2876.6675 | Q10: =+$Q$4*C10/$C$14 -> 3365.4215 | S10: =+L10/$L$14*$S$4 -> 102015.09 | T10: =+L10/$L$14*$T$4 -> 37774.092 | W10: =+F10/$F$14*$W$4 -> 11086 | Y10: =+G10 -> 355699.45 | Z10: =+M10+P10+S10+V10 -> 117563.8 | AA10: =+N10+Q10+T10+W10 -> 53052.892 | AC10: =+Y10/L10 -> 2.2871621 | AD10: =+Z10/$L10 -> 0.75594005 | AE10: =+AA10/$L10 -> 0.34113228 | AF10: =SUM(AC10:AE10) -> 3.3842344 | AG10: x | AH10: =+(AF10-AJ10)/AJ10 -> -0.0017007537 | AJ10: =VLOOKUP(E10,Syspro!$A$2:$F$91,6,FALSE) -> 3.39 | AK10: 3.5 | AL10: 3.1886977 | AM10: 3.25 | AN10: 4.1 | AO10: 3.76 | AP10: 3.7548395 | AQ10: 3.67 | AR10: 3.5 | AS10: 3.5 | AT10: 3.43 | AU10: 3.38 | AV10: 4.84 | AW10: 4.2076158 | AX10: 3.5750546 | AY10: 3.49 | AZ10: 3.03 | BB10: =(+AF10-AJ10)/AJ10 -> -0.0017007537
A11: M00007 | B11: Beading | C11: =SUMIF('Asset Allocation'!$F$1:$I$270,Calc!A11,'Asset Allocation'!I:I) -> 44000 | D11: 14 | E11: M00007 | F11: =SUMIF(Wages!$O$2:$P$220,Calc!E11,Wages!$P$2:$P$220) -> 0.1 | G11: =SUMIF(Wages!$O$2:$AD$192,Calc!E11,Wages!$AD$2:$AD$192) -> 46939.849 | I11: 2.02 | J11: =+G11/L11 -> 4.0746397 | L11: =+F11*40*48*60 -> 11520 | M11: =+D11/$D$14*M$4 -> 12672.038 | N11: =+D11/$D$14*N$4 -> 827.37868 | P11: =+C11/$C$14*$P$4 -> 2138.0637 | Q11: =+$Q$4*C11/$C$14 -> 2501.3268 | S11: =+L11/$L$14*$S$4 -> 7556.6734 | T11: =+L11/$L$14*$T$4 -> 2798.0809 | W11: =+F11/$F$14*$W$4 -> 821.18517 | Y11: =+G11 -> 46939.849 | Z11: =+M11+P11+S11+V11 -> 22366.776 | AA11: =+N11+Q11+T11+W11 -> 6947.9715 | AC11: =+Y11/L11 -> 4.0746397 | AD11: =+Z11/$L11 -> 1.9415604 | AE11: =+AA11/$L11 -> 0.60312253 | AF11: =SUM(AC11:AE11) -> 6.6193226 | AG11: x | AH11: =+(AF11-AJ11)/AJ11 -> 0.0014103721 | AJ11: =VLOOKUP(E11,Syspro!$A$2:$F$91,6,FALSE) -> 6.61 | AK11: 6.64 | AL11: 6.3095377 | AM11: 6.18 | AN11: 4.2 | AO11: 3.78 | AP11: 3.7810959 | AQ11: 3.71 | AR11: 3.51 | AS11: 3.51 | AT11: 3.44 | AU11: 3.4 | AV11: 4.41 | AW11: 3.9064988 | AX11: 3.3334163 | AY11: 3.49 | AZ11: 3.03 | BB11: =(+AF11-AJ11)/AJ11 -> 0.0014103721
A12: M00099 | B12: Miscellaneous and PS00011 | C12: =SUMIF('Asset Allocation'!$F$1:$I$270,Calc!A12,'Asset Allocation'!I:I) -> 129490.78 | D12: 20 | E12: M00099 | F12: =SUMIF(Wages!$O$2:$P$220,Calc!E12,Wages!$P$2:$P$220) -> 1.25 | G12: =SUMIF(Wages!$O$2:$AD$192,Calc!E12,Wages!$AD$2:$AD$192) -> 416130.56 | I12: 2.02 | J12: =+G12/L12 -> 2.8897955 | L12: =+F12*40*48*60 -> 144000 | M12: =+D12/$D$14*M$4 -> 18102.912 | N12: =+D12/$D$14*N$4 -> 1181.9695 | P12: =+C12/$C$14*$P$4 -> 6292.2621 | Q12: =+$Q$4*C12/$C$14 -> 7361.3353 | S12: =+L12/$L$14*$S$4 -> 94458.418 | T12: =+L12/$L$14*$T$4 -> 34976.012 | W12: =+F12/$F$14*$W$4 -> 10264.815 | Y12: =+G12 -> 416130.56 | Z12: =+M12+P12+S12+V12 -> 118853.59 | AA12: =+N12+Q12+T12+W12 -> 53784.131 | AC12: =+Y12/L12 -> 2.8897955 | AD12: =+Z12/$L12 -> 0.82537217 | AE12: =+AA12/$L12 -> 0.37350091 | AF12: =SUM(AC12:AE12) -> 4.0886686 | AG12: x | AH12: =+(AF12-AJ12)/AJ12 -> -0.00032552493 | AJ12: =VLOOKUP(E12,Syspro!$A$2:$F$91,6,FALSE) -> 4.09 | AK12: 4.2 | AL12: 3.7800581 | AM12: 4.05 | AN12: 4.43 | AO12: 4.07 | AP12: 4.0691209 | AQ12: 3.97 | AR12: 3.56 | AS12: 3.56 | AT12: 3.51 | AU12: 3.46 | AV12: 3.41 | AW12: 4.0426559 | AX12: 3.5426329 | AY12: 3.49 | AZ12: 3.03 | BB12: =(+AF12-AJ12)/AJ12 -> -0.00032552493
A13: M00008 | B13: Mig Welding and PS00010 | C13: =SUMIF('Asset Allocation'!$F$1:$I$270,Calc!A13,'Asset Allocation'!I:I) -> 14946 | D13: 40 | E13: M00008 | F13: =SUMIF(Wages!$O$2:$P$220,Calc!E13,Wages!$P$2:$P$220) -> 1.1 | G13: =SUMIF(Wages!$O$2:$AD$192,Calc!E13,Wages!$AD$2:$AD$192) -> 496542.06 | I13: 2.02 | J13: =+G13/L13 -> 3.918419 | L13: =+F13*40*48*60 -> 126720 | M13: =+D13/$D$14*M$4 -> 36205.824 | N13: =+D13/$D$14*N$4 -> 2363.9391 | P13: =+C13/$C$14*$P$4 -> 726.26135 | Q13: =+$Q$4*C13/$C$14 -> 849.65522 | S13: =+L13/$L$14*$S$4 -> 83123.408 | T13: =+L13/$L$14*$T$4 -> 30778.89 | W13: =+F13/$F$14*$W$4 -> 9033.0369 | Y13: =+G13 -> 496542.06 | Z13: =+M13+P13+S13+V13 -> 120055.49 | AA13: =+N13+Q13+T13+W13 -> 43025.521 | AC13: =+Y13/L13 -> 3.918419 | AD13: =+Z13/$L13 -> 0.94740762 | AE13: =+AA13/$L13 -> 0.33953221 | AF13: =SUM(AC13:AE13) -> 5.2053589 | AG13: x | AH13: =+(AF13-AJ13)/AJ13 -> -0.00089081561 | AJ13: =VLOOKUP(E13,Syspro!$A$2:$F$91,6,FALSE) -> 5.21 | AK13: 5.21 | AL13: 4.9506932 | AM13: 4.84 | AN13: 4.34 | AO13: 4.15 | AP13: 4.1522814 | AQ13: 4.04 | AR13: 3.52 | AS13: 3.52 | AT13: 3.83 | AU13: 3.57 | AV13: 4.42 | AW13: 4.0331648 | AX13: 3.6805127 | AY13: 3.49 | AZ13: 3.03 | BB13: =(+AF13-AJ13)/AJ13 -> -0.00089081561
B14: Manufacturing | C14: =SUM(C5:C13) -> 3127047.6 | D14: =SUM(D5:D13) -> 333 | F14: =SUM(F5:F13) -> 9.15 | L14: =+SUM(L5:L13) -> 1054080 | AB14: x
B16: Ottery
A17: M00009 | B17: Bending Breaks Ottery | C17: =SUMIF('Asset Allocation'!$F$1:$I$270,Calc!A17,'Asset Allocation'!I:I) -> 0 | D17: 0 | E17: M00009 | F17: =SUMIF(Wages!$O$2:$P$190,Calc!E17,Wages!$P$2:$P$190) -> 0 | G17: =SUMIF(Wages!$O$2:$AD$192,Calc!E17,Wages!$AD$2:$AD$192) -> 0 | AJ17: 0 | AK17: 0 | AM17: 0 | AN17: 0 | AO17: 0 | AQ17: 0 | AR17: 0 | AS17: 0 | AT17: 0 | AU17: 0 | AV17: 4.38 | AW17: 3.9662936 | AX17: 3.6341206 | AY17: 3.49 | AZ17: 3.03 | BB17: =(+AF17-AW17)/AW17 -> -1
A18: M00010 | B18: Spot Welding Ottery | C18: =SUMIF('Asset Allocation'!$F$1:$I$270,Calc!A18,'Asset Allocation'!I:I) -> 0 | D18: 0 | E18: M00010 | F18: =SUMIF(Wages!$O$2:$P$190,Calc!E18,Wages!$P$2:$P$190) -> 0 | G18: =SUMIF(Wages!$O$2:$AD$192,Calc!E18,Wages!$AD$2:$AD$192) -> 0 | AJ18: 0 | AK18: 0 | AM18: 0 | AN18: 0 | AO18: 0 | AQ18: 0 | AR18: 0 | AS18: 0 | AT18: 0 | AU18: 0 | AV18: 3.88 | AW18: 4.2850296 | AX18: 3.8044197 | AY18: 3.49 | AZ18: 3.03 | BB18: =(+AF18-AW18)/AW18 -> -1
A19: M00011 | B19: Rolling Ottery | C19: =SUMIF('Asset Allocation'!$F$1:$I$270,Calc!A19,'Asset Allocation'!I:I) -> 0 | D19: 0 | E19: M00011 | F19: =SUMIF(Wages!$O$2:$P$190,Calc!E19,Wages!$P$2:$P$190) -> 0 | G19: =SUMIF(Wages!$O$2:$AD$192,Calc!E19,Wages!$AD$2:$AD$192) -> 0 | AJ19: 0 | AK19: 0 | AM19: 0 | AN19: 0 | AO19: 0 | AQ19: 0 | AR19: 0 | AS19: 0 | AT19: 0 | AU19: 0 | AV19: 3.47 | AW19: 3.5357021 | AX19: 3.1478332 | AY19: 3.49 | AZ19: 3.03 | BB19: =(+AF19-AW19)/AW19 -> -1
A20: M00012 | B20: Beading Ottery | C20: =SUMIF('Asset Allocation'!$F$1:$I$270,Calc!A20,'Asset Allocation'!I:I) -> 0 | D20: 0 | E20: M00012 | F20: =SUMIF(Wages!$O$2:$P$190,Calc!E20,Wages!$P$2:$P$190) -> 0 | G20: =SUMIF(Wages!$O$2:$AD$192,Calc!E20,Wages!$AD$2:$AD$192) -> 0 | AJ20: 0 | AK20: 0 | AM20: 0 | AN20: 0 | AO20: 0 | AQ20: 0 | AR20: 0 | AS20: 0 | AT20: 0 | AU20: 0 | AV20: 3.76 | AW20: 4.2782884 | AX20: 3.7822454 | AY20: 3.49 | AZ20: 3.03 | BB20: =(+AF20-AW20)/AW20 -> -1
A21: M00013 | B21: Mig Welding Ottery | C21: =SUMIF('Asset Allocation'!$F$1:$I$270,Calc!A21,'Asset Allocation'!I:I) -> 0 | D21: 0 | E21: M00013 | F21: =SUMIF(Wages!$O$2:$P$190,Calc!E21,Wages!$P$2:$P$190) -> 0 | G21: =SUMIF(Wages!$O$2:$AD$192,Calc!E21,Wages!$AD$2:$AD$192) -> 0 | AJ21: 0 | AK21: 0 | AM21: 0 | AN21: 0 | AO21: 0 | AQ21: 0 | AR21: 0 | AS21: 0 | AT21: 0 | AU21: 0 | AV21: 4.13 | AW21: 4.0239837 | AX21: 3.7565265 | AY21: 3.49 | AZ21: 3.03 | BB21: =(+AF21-AW21)/AW21 -> -1
A22: M00005 | B22: Guilotene | C22: =SUMIF('Asset Allocation'!$F$1:$I$270,Calc!A22,'Asset Allocation'!I:I) -> 0 | D22: 0 | E22: M00005 | F22: =SUMIF(Wages!$O$2:$P$190,Calc!E22,Wages!$P$2:$P$190) -> 0 | G22: =SUMIF(Wages!$O$2:$AD$192,Calc!E22,Wages!$AD$2:$AD$192) -> 0 | AJ22: 0 | AK22: 0 | AM22: 0 | AN22: 0 | AO22: 0 | AQ22: 0 | AR22: 0 | AS22: 0 | AT22: 0 | AU22: 0 | AV22: 5.73 | AW22: 5.4924862 | AX22: 5.1733211 | AY22: 3.49 | AZ22: 3.03 | BB22: =(+AF22-AW22)/AW22 -> -1
B23: Total SQM | C23: =SUM(C16:C22) -> 0 | D23: 0 | F23: =SUM(F17:F22) -> 0
A24: Trumpf | E24: Trumpf | M24: =HLOOKUP($B$26,Overhead!$G:$G,M$1,FALSE) -> 108125.48 | N24: =HLOOKUP($B$26,Overhead!$G:$G,N$1,FALSE) -> 7059.7352 | P24: =HLOOKUP($B$26,Overhead!$G:$G,P$1,FALSE) -> 314754.83 | Q24: =HLOOKUP($B$26,Overhead!$G:$G,Q$1,FALSE) -> 245430.24 | S24: =HLOOKUP($B$26,Overhead!$G:$G,S$1,FALSE) -> 518364.25 | T24: =HLOOKUP($B$26,Overhead!$G:$G,T$1,FALSE) -> 188524.1 | W24: =HLOOKUP($B$26,Overhead!$G:$G,W$1,FALSE) -> 8211.8517 | Y24: =+Y25 -> 412182.08 | Z24: =+Z25 -> 941244.56 | AA24: =+AA25 -> 449225.92
A25: 05 | B25: Trumpf | C25: =SUMIF('Asset Allocation'!$F$1:$I$270,Calc!A25,'Asset Allocation'!I:I) -> 4317281 | D25: 111 | E25: 05 | F25: 1 | G25: =SUMIF(Wages!$O$2:$AD$192,Calc!E25,Wages!$AD$2:$AD$192) -> 412182.08 | I25: 4.07 | J25: =+G25/L25 -> 3.5779695 | L25: =40*48*60 -> 115200 | M25: =+$D$25/$D$26*M$24 -> 108125.48 | N25: =+$D$25/$D$26*N$24 -> 7059.7352 | P25: =+$D$25/$D$26*P$24 -> 314754.83 | Q25: =+$D$25/$D$26*Q$24 -> 245430.24 | S25: =+$L$25/$L$26*$S$24 -> 518364.25 | T25: =+$L$25/$L$26*$T$24 -> 188524.1 | W25: =+$F$25/$F$26*W$24 -> 8211.8517 | Y25: =+G25 -> 412182.08 | Z25: =+M25+P25+S25+V25 -> 941244.56 | AA25: =+N25+Q25+T25+W25 -> 449225.92 | AB25: x | AC25: =+Y25/L25 -> 3.5779695 | AD25: =+Z25/$L25 -> 8.1705257 | AE25: =+AA25/$L25 -> 3.8995306 | AF25: =SUM(AC25:AE25) -> 15.648026 | AH25: =+(AF25-AJ25)/AJ25 -> -0.00012614959 | AJ25: =VLOOKUP(E25,Syspro!$A$2:$F$91,6,FALSE) -> 15.65 | AK25: 15.85 | AL25: 14.459058 | AM25: 14.39 | AN25: 12.77 | AO25: 12.61 | AP25: 12.608115 | AQ25: 11.8 | AR25: 13.33 | AS25: 13.33 | AT25: 14.61 | AU25: 14.22 | AV25: 16.83 | AW25: 15.850981 | AX25: 16.596263 | AY25: 19.5 | AZ25: 14.56 | BB25: =(+AF25-AJ25)/AJ25 -> -0.00012614959
B26: Trumpf | C26: =+C25 -> 4317281 | D26: =SUM(D25) -> 111 | F26: =SUM(F25) -> 1 | L26: =SUM(L25) -> 115200
A27: Assembly | B27: Lansdowne | E27: Assembly | M27: =HLOOKUP($B$34,Overhead!$H:$H,M$1,FALSE) -> 551155.83 | N27: =HLOOKUP($B$34,Overhead!$H:$H,N$1,FALSE) -> 35985.907 | P27: =HLOOKUP($B$34,Overhead!$H:$H,P$1,FALSE) -> 10853.615 | Q27: =HLOOKUP($B$34,Overhead!$H:$H,Q$1,FALSE) -> 13184.231 | S27: =HLOOKUP($B$34,Overhead!$H:$H,S$1,FALSE) -> 836877.31 | T27: =HLOOKUP($B$34,Overhead!$H:$H,T$1,FALSE) -> 51127.211 | W27: =HLOOKUP($B$34,Overhead!$H:$H,W$1,FALSE) -> 102237.55 | Y27: =SUM(Y28:Y33) -> 4871983.4 | Z27: =+M27+P27+S27+V27 -> 1398886.8 | AA27: =+N27+Q27+T27+W27 -> 202534.9
A28: A00001 | B28: Induction Channel Assembly | C28: =SUMIF('Asset Allocation'!$F$1:$I$270,Calc!A28,'Asset Allocation'!I:I) -> 0 | D28: 20 | E28: A00001 | F28: =SUMIF(Wages!$O$2:$P$220,Calc!E28,Wages!$P$2:$P$220) -> 2 | G28: =SUMIF(Wages!$O$2:$AD$192,Calc!E28,Wages!$AD$2:$AD$192) -> 809046.09 | I28: 1.86 | J28: =+G28/L28 -> 3.5114848 | L28: =+F28*40*48*60 -> 230400 | M28: =+D28/$D$34*M$27 -> 29394.978 | N28: =+D28/$D$34*N$27 -> 1919.2484 | P28: =+P$27*$C28/$C$34 -> 0 | Q28: =+Q$27*$C28/$C$34 -> 0 | S28: =+L28/$L$34*$S$27 -> 134438.12 | T28: =+L28/$L$34*$T$27 -> 8213.2066 | W28: =+F28/$F$34*$W$27 -> 16423.703 | Y28: =+G28 -> 809046.09 | Z28: =+M28+P28+S28+V28 -> 163833.1 | AA28: =+N28+Q28+T28+W28 -> 26556.158 | AC28: =+Y28/L28 -> 3.5114848 | AD28: =+Z28/$L28 -> 0.71108116 | AE28: =+AA28/$L28 -> 0.1152611 | AF28: =SUM(AC28:AE28) -> 4.337827 | AG28: x | AH28: =+(ROUND(AF28,2)-AJ28)/AJ28 -> 0 | AJ28: =VLOOKUP(E28,Syspro!$A$2:$F$91,6,FALSE) -> 4.34 | AK28: 4.32 | AL28: 4.2523529 | AM28: 3.95 | AN28: 3.59 | AO28: 3.53 | AP28: 3.5422252 | AQ28: 3.27 | AR28: 3.08 | AS28: 3.08 | AT28: 3.09 | AU28: 3.02 | AV28: 3.18 | AW28: 2.9909304 | AX28: 2.8682207 | AY28: 3.39 | AZ28: 2.631129 | BB28: =(+AF28-AJ28)/AJ28 -> -0.00050068415
A29: A00002 | B29: Constant Volume Diffuser Ass | C29: =SUMIF('Asset Allocation'!$F$1:$I$270,Calc!A29,'Asset Allocation'!I:I) -> 0 | D29: 64 | E29: A00002 | F29: =SUMIF(Wages!$O$2:$P$220,Calc!E29,Wages!$P$2:$P$220) -> 2 | G29: =SUMIF(Wages!$O$2:$AD$192,Calc!E29,Wages!$AD$2:$AD$192) -> 807351.38 | I29: 1.86 | J29: =+G29/L29 -> 3.5041293 | L29: =+F29*40*48*60 -> 230400 | M29: =+D29/$D$34*M$27 -> 94063.928 | N29: =+D29/$D$34*N$27 -> 6141.5948 | P29: =+P$27*$C29/$C$34 -> 0 | Q29: =+Q$27*$C29/$C$34 -> 0 | S29: =+L29/$L$34*$S$27 -> 134438.12 | T29: =+L29/$L$34*$T$27 -> 8213.2066 | W29: =+F29/$F$34*$W$27 -> 16423.703 | Y29: =+G29 -> 807351.38 | Z29: =+M29+P29+S29+V29 -> 228502.05 | AA29: =+N29+Q29+T29+W29 -> 30778.505 | AC29: =+Y29/L29 -> 3.5041293 | AD29: =+Z29/$L29 -> 0.99176237 | AE29: =+AA29/$L29 -> 0.13358726 | AF29: =SUM(AC29:AE29) -> 4.6294789 | AG29: x | AH29: =+(ROUND(AF29,2)-AJ29)/AJ29 -> 0.0021645022 | AJ29: =VLOOKUP(E29,Syspro!$A$2:$F$91,6,FALSE) -> 4.62 | AK29: 4.61 | AL29: 4.5322075 | AM29: 4.3 | AN29: 3.75 | AO29: 3.69 | AP29: 3.6950899 | AQ29: 3.91 | AR29: 3.38 | AS29: 3.38 | AT29: 3.39 | AU29: 3.32 | AV29: 3.65 | AW29: 3.4427417 | AX29: 3.3196433 | AY29: 3.39 | AZ29: 2.631129 | BB29: =(+AF29-AJ29)/AJ29 -> 0.002051711
A30: A00003 | B30: Diffuser Sub-Assembly | C30: =SUMIF('Asset Allocation'!$F$1:$I$270,Calc!A30,'Asset Allocation'!I:I) -> 94000 | D30: 138 | E30: A00003 | F30: =SUMIF(Wages!$O$2:$P$220,Calc!E30,Wages!$P$2:$P$220) -> 3.95 | G30: =SUMIF(Wages!$O$2:$AD$192,Calc!E30,Wages!$AD$2:$AD$192) -> 1557753.8 | I30: 2.28 | J30: =+G30/L30 -> 3.4233338 | L30: =+F30*40*48*60 -> 455040 | M30: =+D30/$D$34*M$27 -> 202825.35 | N30: =+D30/$D$34*N$27 -> 13242.814 | P30: =+P$27*$C30/$C$34 -> 4399.114 | Q30: =+Q$27*$C30/$C$34 -> 5343.7435 | S30: =+L30/$L$34*$S$27 -> 265515.29 | T30: =+L30/$L$34*$T$27 -> 16221.083 | W30: =+F30/$F$34*$W$27 -> 32436.814 | Y30: =+G30 -> 1557753.8 | Z30: =+M30+P30+S30+V30 -> 472739.75 | AA30: =+N30+Q30+T30+W30 -> 67244.455 | AC30: =+Y30/L30 -> 3.4233338 | AD30: =+Z30/$L30 -> 1.0388971 | AE30: =+AA30/$L30 -> 0.14777702 | AF30: =SUM(AC30:AE30) -> 4.6100079 | AG30: x | AH30: =+(ROUND(AF30,2)-AJ30)/AJ30 -> 0 | AJ30: =VLOOKUP(E30,Syspro!$A$2:$F$91,6,FALSE) -> 4.61 | AK30: 4.59 | AL30: 4.51 | AM30: 4.4 | AN30: 3.95 | AO30: 3.89 | AP30: 3.8919537 | AQ30: 3.8 | AR30: 3.49 | AS30: 3.49 | AT30: 3.5 | AU30: 3.42 | AV30: 3.53 | AW30: 3.3276832 | AX30: 3.1238648 | AY30: 4.51 | AZ30: 3.8039549 | BB30: =(+AF30-AJ30)/AJ30 -> 1.713799e-06
A31: A00004 | B31: Diffuser Final Assembly & Sales Assembly | C31: =SUMIF('Asset Allocation'!$F$1:$I$270,Calc!A31,'Asset Allocation'!I:I) -> 0 | D31: 90 | E31: A00004 | F31: =SUMIF(Wages!$O$2:$P$220,Calc!E31,Wages!$P$2:$P$220) -> 2.7 | G31: =SUMIF(Wages!$O$2:$AD$192,Calc!E31,Wages!$AD$2:$AD$192) -> 1080353.9 | I31: 2.28 | J31: =+G31/L31 -> 3.47336 | L31: =+F31*40*48*60 -> 311040 | M31: =+D31/$D$34*M$27 -> 132277.4 | N31: =+D31/$D$34*N$27 -> 8636.6176 | P31: =+P$27*$C31/$C$34 -> 0 | Q31: =+Q$27*$C31/$C$34 -> 0 | S31: =+L31/$L$34*$S$27 -> 181491.46 | T31: =+L31/$L$34*$T$27 -> 11087.829 | W31: =+F31/$F$34*$W$27 -> 22172 | Y31: =+G31 -> 1080353.9 | Z31: =+M31+P31+S31+V31 -> 313768.86 | AA31: =+N31+Q31+T31+W31 -> 41896.446 | AC31: =+Y31/L31 -> 3.47336 | AD31: =+Z31/$L31 -> 1.0087734 | AE31: =+AA31/$L31 -> 0.13469794 | AF31: =SUM(AC31:AE31) -> 4.6168313 | AG31: x | AH31: =+(ROUNDUP(AF31,2)-AJ31)/AJ31 -> 0.0021691974 | AJ31: =VLOOKUP(E31,Syspro!$A$2:$F$91,6,FALSE) -> 4.61 | AK31: 4.6 | AL31: 4.5222124 | AM31: 4.59 | AN31: 3.84 | AO31: 3.78 | AP31: 3.7854809 | AQ31: 3.7 | AR31: 3.51 | AS31: 3.51 | AT31: 3.52 | AU31: 3.45 | AV31: 3.52 | AW31: 3.3135837 | AX31: 3.1122554 | AY31: 4.51 | AZ31: 3.8039549 | BB31: =(+AF31-AJ31)/AJ31 -> 0.0014818466
A32: A00005 | B32: Testing | C32: =SUMIF('Asset Allocation'!$F$1:$I$270,Calc!A32,'Asset Allocation'!I:I) -> 132500 | D32: 39 | E32: A00005 | F32: =SUMIF(Wages!$O$2:$P$220,Calc!E32,Wages!$P$2:$P$220) -> 0.8 | G32: =SUMIF(Wages!$O$2:$AD$192,Calc!E32,Wages!$AD$2:$AD$192) -> 335227.17 | I32: 2.28 | J32: =+G32/L32 -> 3.6374476 | L32: =+F32*40*48*60 -> 92160 | M32: =+D32/$D$34*M$27 -> 57320.206 | N32: =+D32/$D$34*N$27 -> 3742.5343 | P32: =+P$27*$C32/$C$34 -> 6200.8788 | Q32: =+Q$27*$C32/$C$34 -> 7532.4044 | S32: =+L32/$L$34*$S$27 -> 53775.249 | T32: =+L32/$L$34*$T$27 -> 3285.2827 | W32: =+F32/$F$34*$W$27 -> 6569.4814 | Y32: =+G32 -> 335227.17 | Z32: =+M32+P32+S32+V32 -> 117296.33 | AA32: =+N32+Q32+T32+W32 -> 21129.703 | AC32: 3.42 | AD32: 1.16 | AE32: =+AA32/$L32 -> 0.22927195 | AF32: =SUM(AC32:AE32) -> 4.8092719 | AG32: x | AH32: =+(ROUND(AF32,2)-AJ32)/AJ32 -> -1.8465248e-16 | AJ32: =VLOOKUP(E32,Syspro!$A$2:$F$91,6,FALSE) -> 4.81 | AK32: 4.82 | AL32: 4.78 | AM32: 4.78 | AN32: 4.09 | AO32: 4.03 | AP32: 4.0342803 | AQ32: 3.94 | AR32: 3.75 | AS32: 3.75 | AT32: 3.77 | AU32: 3.68 | AV32: 4.08 | AW32: 3.8571434 | AX32: 3.7718559 | AY32: 4.51 | AZ32: 3.8039549 | BB32: =(+AF32-AJ32)/AJ32 -> -0.00015136209
A33: A00006 | B33: QC | C33: =SUMIF('Asset Allocation'!$F$1:$I$270,Calc!A33,'Asset Allocation'!I:I) -> 5419.38 | D33: 24 | E33: A00006 | F33: =SUMIF(Wages!$O$2:$P$220,Calc!E33,Wages!$P$2:$P$220) -> 1 | G33: =SUMIF(Wages!$O$2:$AD$192,Calc!E33,Wages!$AD$2:$AD$192) -> 282251.1 | I33: 1.65 | J33: =+G33/L33 -> 2.4500963 | L33: =+F33*40*48*60 -> 115200 | M33: =+D33/$D$34*M$27 -> 35273.973 | N33: =+D33/$D$34*N$27 -> 2303.098 | P33: =+P$27*$C33/$C$34 -> 253.62203 | Q33: =+Q$27*$C33/$C$34 -> 308.08273 | S33: =+L33/$L$34*$S$27 -> 67219.061 | T33: =+L33/$L$34*$T$27 -> 4106.6033 | W33: =+F33/$F$34*$W$27 -> 8211.8517 | Y33: =+G33 -> 282251.1 | Z33: =+M33+P33+S33+V33 -> 102746.66 | AA33: =+N33+Q33+T33+W33 -> 14929.636 | AC33: =+Y33/L33 -> 2.4500963 | AD33: =+Z33/$L33 -> 0.89189805 | AE33: =+AA33/$L33 -> 0.12959753 | AF33: =SUM(AC33:AE33) -> 3.4715919 | AG33: x | AH33: =+(ROUND(AF33,2)-AJ33)/AJ33 -> 0 | AJ33: =VLOOKUP(E33,Syspro!$A$2:$F$91,6,FALSE) -> 3.47 | AK33: 3.45 | AL33: 3.3829586 | AM33: 3.21 | AN33: 2.79 | AO33: 2.84 | AP33: 2.8506451 | AQ33: 2.81 | AR33: 0 | AS33: 3.1 | AT33: 2.24 | AU33: 1.58 | AV33: 3.64 | AW33: 3.4903804 | AX33: 3.2799387 | AZ33: 1.65 | BB33: =(+AF33-AJ33)/AJ33 -> 0.00045876193
B34: Assembly | C34: =SUM(C28:C33) -> 231919.38 | D34: =SUM(D28:D33) -> 375 | F34: =SUM(F28:F33) -> 12.45 | L34: =SUM(L28:L33) -> 1434240 | AB34: x
B35: Pretoria | M35: =HLOOKUP($B$37,Overhead!$I:$I,M$1,FALSE) -> 529697.11 | N35: =HLOOKUP($B$37,Overhead!$I:$I,N$1,FALSE) -> 518.85434 | P35: =HLOOKUP($B$37,Overhead!$I:$I,P$1,FALSE) -> 5426.8075 | Q35: =HLOOKUP($B$37,Overhead!$I:$I,Q$1,FALSE) -> 0 | S35: =HLOOKUP($B$37,Overhead!$I:$I,S$1,FALSE) -> 271159.78 | T35: =HLOOKUP($B$37,Overhead!$I:$I,T$1,FALSE) -> 133793.4 | W35: =HLOOKUP($B$37,Overhead!$I:$I,W$1,FALSE) -> 17932.979
A36: 01PTA | B36: Assembly | C36: =SUMIF('Asset Allocation'!$F$1:$I$270,Calc!A36,'Asset Allocation'!I:I) -> 45877.23 | D36: 150 | E36: 01PTA | F36: =SUMIF(Wages!$O$2:$P$190,Calc!E36,Wages!$P$2:$P$190) -> 2 | G36: =SUMIF(Wages!$O$2:$AD$192,Calc!E36,Wages!$AD$2:$AD$192) -> 374336.1 | I36: 2.33 | J36: =+G36/L36 -> 1.6247227 | L36: =+F36*40*48*60 -> 230400 | M36: =+$D36/$D$37*M$35 -> 529697.11 | N36: =+D36/$D$37*N$35 -> 518.85434 | P36: =+P$35*$C36/$C$34 -> 1073.5062 | Q36: =+Q$35*$C36/$C$34 -> 0 | S36: =+L36/$L$37*$S$35 -> 271159.78 | T36: =+L36/$L$37*$T$35 -> 133793.4 | W36: =+F36/$F$37*$W$35 -> 17932.979 | Y36: =+G36 -> 374336.1 | Z36: =+M36+P36+S36+V36 -> 801930.39 | AA36: =+N36+Q36+T36+W36 -> 152245.23 | AC36: =+Y36/L36 -> 1.6247227 | AD36: =+Z36/$L36 -> 3.4806007 | AE36: =+AA36/$L36 -> 0.6607866 | AF36: =SUM(AC36:AE36) -> 5.76611 | AH36: =+(AF36-AJ36)/AJ36 -> 0.0010607553 | AJ36: =VLOOKUP(E36,Syspro!$A$2:$F$91,6,FALSE) -> 5.76 | AK36: 5.5 | AL36: 5.1113402 | AM36: 5.07 | AN36: 4.91 | AO36: 4.83 | AP36: 4.8307509 | AQ36: 4.96 | AR36: 5.94 | AS36: 5.94 | AT36: 5.75 | AU36: 5.66 | AV36: 5.84 | AW36: 5.2677184 | AX36: 5.6428628 | AZ36: 2.22 | BB36: =(+AF36-AJ36)/AJ36 -> 0.0010607553
B37: AssemblyPTA | C37: =SUM(C36) -> 45877.23 | D37: =SUM(D36) -> 150 | F37: =SUM(F36) -> 2 | L37: =SUM(L36) -> 230400
A39: Damper | E39: Damper | M39: =HLOOKUP($B$48,Overhead!$J:$J,M$1,FALSE) -> 500440.73 | N39: =HLOOKUP($B$48,Overhead!$J:$J,N$1,FALSE) -> 32674.704 | P39: =HLOOKUP($B$48,Overhead!$J:$J,P$1,FALSE) -> 21707.23 | Q39: =HLOOKUP($B$48,Overhead!$J:$J,Q$1,FALSE) -> 37217.095 | S39: =HLOOKUP($B$48,Overhead!$J:$J,S$1,FALSE) -> 565717.53 | T39: =HLOOKUP($B$48,Overhead!$J:$J,T$1,FALSE) -> 128528.01 | W39: =HLOOKUP($B$48,Overhead!$J:$J,W$1,FALSE) -> 82118.517 | Y39: =SUM(Y40:Y47) -> 4089933.9 | Z39: =+M39+P39+S39+V39 -> 1087865.5 | AA39: =+N39+Q39+T39+W39 -> 280538.33
A40: D00001 | B40: Cutting | C40: =SUMIF('Asset Allocation'!$F$2:$I$269,Calc!$A40,'Asset Allocation'!$I$2:$I$269) -> 61401.58 | D40: 83 | E40: D00001 | F40: =SUMIF(Wages!$O$2:$P$220,Calc!E40,Wages!$P$2:$P$220) -> 3 | G40: =SUMIF(Wages!$O$2:$AD$192,Calc!E40,Wages!$AD$2:$AD$192) -> 1276708.4 | I40: 2.31 | J40: =+G40/L40 -> 3.6941793 | L40: =+F40*40*48*60 -> 345600 | M40: =+$D40/$D$48*M$39 -> 91289.188 | N40: =+$D40/$D$48*N$39 -> 5960.4404 | P40: =+P$39*$C40/$C$48 -> 2035.9131 | Q40: =+Q$39*$C40/$C$48 -> 3490.5776 | S40: =+$S$39*L40/$L$48 -> 169715.26 | T40: =+$T$39*L40/$L$48 -> 38558.404 | W40: =+$W$39*F40/$F$48 -> 24635.555 | Y40: =+G40 -> 1276708.4 | Z40: =+M40+P40+S40+V40 -> 263040.36 | AA40: =+N40+Q40+T40+W40 -> 72644.977 | AC40: =+Y40/L40 -> 3.6941793 | AD40: =+Z40/$L40 -> 0.76111215 | AE40: =+AA40/$L40 -> 0.21019959 | AF40: =SUM(AC40:AE40) -> 4.665491 | AG40: x | AH40: =+(ROUND(AF40,2)-AJ40)/AJ40 -> 0.0021459227 | AJ40: =VLOOKUP(E40,Syspro!$A$2:$F$91,6,FALSE) -> 4.66 | AK40: 4.64 | AL40: 4.73 | AM40: 4.15 | AN40: 5.21 | AO40: 5.1 | AP40: 5.0929133 | AQ40: 4.95 | AR40: 4.96 | AS40: 4.96 | AT40: 5.08 | AU40: 4.65 | AV40: 4.61 | AW40: 4.3082856 | AX40: 4.2295808 | AY40: 3.11 | AZ40: 2.68 | BB40: =(+AF40-AJ40)/AJ40 -> 0.0011783247
A41: D00002 | B41: Brushing | C41: =SUMIF('Asset Allocation'!$F$1:$I$270,Calc!A41,'Asset Allocation'!I:I) -> 0 | D41: 7 | E41: D00002 | F41: =SUMIF(Wages!$O$2:$P$220,Calc!E41,Wages!$P$2:$P$220) -> 0.2 | G41: =SUMIF(Wages!$O$2:$AD$192,Calc!E41,Wages!$AD$2:$AD$192) -> 85941.062 | I41: 2.31 | J41: =+G41/L41 -> 3.7300808 | L41: =+F41*40*48*60 -> 23040 | M41: =+$D41/$D$48*M$39 -> 7699.0882 | N41: =+$D41/$D$48*N$39 -> 502.68775 | P41: =+P$39*$C41/$C$48 -> 0 | Q41: =+Q$39*$C41/$C$48 -> 0 | S41: =+$S$39*L41/$L$48 -> 11314.351 | T41: =+$T$39*L41/$L$48 -> 2570.5602 | W41: =+$W$39*F41/$F$48 -> 1642.3703 | Y41: =+G41 -> 85941.062 | Z41: =+M41+P41+S41+V41 -> 19013.439 | AA41: =+N41+Q41+T41+W41 -> 4715.6183 | AC41: =+Y41/L41 -> 3.7300808 | AD41: =+Z41/$L41 -> 0.82523606 | AE41: =+AA41/$L41 -> 0.20467093 | AF41: =SUM(AC41:AE41) -> 4.7599878 | AG41: x | AH41: =+(ROUND(AF41,2)-AJ41)/AJ41 -> 0 | AJ41: =VLOOKUP(E41,Syspro!$A$2:$F$91,6,FALSE) -> 4.76 | AK41: 4.73 | AL41: 4.66 | AM41: 4.25 | AN41: 4.87 | AO41: 4.76 | AP41: 4.7542743 | AQ41: 4.62 | AR41: 4.6 | AS41: 4.6 | AT41: 4.73 | AU41: 4.3 | AV41: 5.23 | AW41: 4.8896709 | AX41: 4.7829864 | AY41: 3.11 | AZ41: 2.68 | BB41: =(+AF41-AJ41)/AJ41 -> -2.5630787e-06
A42: D00003 | B42: Notching | C42: =SUMIF('Asset Allocation'!$F$1:$I$270,Calc!A42,'Asset Allocation'!I:I) -> 5647.83 | D42: 7 | E42: D00003 | F42: =SUMIF(Wages!$O$2:$P$220,Calc!E42,Wages!$P$2:$P$220) -> 0.65 | G42: =SUMIF(Wages!$O$2:$AD$192,Calc!E42,Wages!$AD$2:$AD$192) -> 274244.19 | I42: 2.31 | J42: =+G42/L42 -> 3.6624492 | L42: =+F42*40*48*60 -> 74880 | M42: =+$D42/$D$48*M$39 -> 7699.0882 | N42: =+$D42/$D$48*N$39 -> 502.68775 | P42: =+P$39*$C42/$C$48 -> 187.26702 | Q42: =+Q$39*$C42/$C$48 -> 321.06973 | S42: =+$S$39*L42/$L$48 -> 36771.639 | T42: =+$T$39*L42/$L$48 -> 8354.3208 | W42: =+$W$39*F42/$F$48 -> 5337.7036 | Y42: =+G42 -> 274244.19 | Z42: =+M42+P42+S42+V42 -> 44657.995 | AA42: =+N42+Q42+T42+W42 -> 14515.782 | AC42: =+Y42/L42 -> 3.6624492 | AD42: =+Z42/$L42 -> 0.59639416 | AE42: =+AA42/$L42 -> 0.19385392 | AF42: =SUM(AC42:AE42) -> 4.4526973 | AG42: x | AH42: =+(ROUND(AF42,2)-AJ42)/AJ42 -> 0 | AJ42: =VLOOKUP(E42,Syspro!$A$2:$F$91,6,FALSE) -> 4.45 | AK42: 4.43 | AL42: 4.36 | AM42: 3.77 | AN42: 4.9 | AO42: 4.78 | AP42: 4.7818603 | AQ42: 4.64 | AR42: 4.64 | AS42: 4.64 | AT42: 4.77 | AU42: 4.34 | AV42: 5.31 | AW42: 4.9671274 | AX42: 4.7829864 | AY42: 3.11 | AZ42: 2.68 | BB42: =(+AF42-AJ42)/AJ42 -> 0.00060612599
A43: D00004 | B43: Welding | C43: =SUMIF('Asset Allocation'!$F$1:$I$270,Calc!A43,'Asset Allocation'!I:I) -> 32995.24 | D43: 67 | E43: D00004 | F43: =SUMIF(Wages!$O$2:$P$220,Calc!E43,Wages!$P$2:$P$220) -> 1.4 | G43: =SUMIF(Wages!$O$2:$AD$192,Calc!E43,Wages!$AD$2:$AD$192) -> 624164.09 | I43: 2.31 | J43: =+G43/L43 -> 3.870065 | L43: =+F43*40*48*60 -> 161280 | M43: =+$D43/$D$48*M$39 -> 73691.272 | N43: =+$D43/$D$48*N$39 -> 4811.4399 | P43: =+P$39*$C43/$C$48 -> 1094.0344 | Q43: =+Q$39*$C43/$C$48 -> 1875.7245 | S43: =+$S$39*L43/$L$48 -> 79200.454 | T43: =+$T$39*L43/$L$48 -> 17993.922 | W43: =+$W$39*F43/$F$48 -> 11496.592 | Y43: =+G43 -> 624164.09 | Z43: =+M43+P43+S43+V43 -> 153985.76 | AA43: =+N43+Q43+T43+W43 -> 36177.678 | AC43: =+Y43/L43 -> 3.870065 | AD43: =+Z43/$L43 -> 0.95477282 | AE43: =+AA43/$L43 -> 0.22431596 | AF43: =SUM(AC43:AE43) -> 5.0491538 | AG43: x | AH43: =+(ROUND(AF43,2)-AJ43)/AJ43 -> 0.001984127 | AJ43: =VLOOKUP(E43,Syspro!$A$2:$F$91,6,FALSE) -> 5.04 | AK43: 5.02 | AL43: 4.94 | AM43: 4.66 | AN43: 4.51 | AO43: 4.27 | AP43: 4.2707248 | AQ43: 4.15 | AR43: 4.14 | AS43: 4.14 | AT43: 4.29 | AU43: 4.12 | AV43: 4.69 | AW43: 4.380371 | AX43: 4.300741 | AY43: 3.11 | AZ43: 2.68 | BB43: =(+AF43-AJ43)/AJ43 -> 0.001816232
A44: D00005 | B44: Grille Assembly | C44: =SUMIF('Asset Allocation'!$F$1:$I$270,Calc!A44,'Asset Allocation'!I:I) -> 180936 | D44: 60 | E44: D00005 | F44: =SUMIF(Wages!$O$2:$P$220,Calc!E44,Wages!$P$2:$P$220) -> 0.7 | G44: =SUMIF(Wages!$O$2:$AD$192,Calc!E44,Wages!$AD$2:$AD$192) -> 299493.56 | I44: 2.31 | J44: =+G44/L44 -> 3.7139578 | L44: =+F44*40*48*60 -> 80640 | M44: =+$D44/$D$48*M$39 -> 65992.184 | N44: =+$D44/$D$48*N$39 -> 4308.7521 | P44: =+P$39*$C44/$C$48 -> 5999.3565 | Q44: =+Q$39*$C44/$C$48 -> 10285.91 | S44: =+$S$39*L44/$L$48 -> 39600.227 | T44: =+$T$39*L44/$L$48 -> 8996.9608 | W44: =+$W$39*F44/$F$48 -> 5748.2962 | Y44: =+G44 -> 299493.56 | Z44: =+M44+P44+S44+V44 -> 111591.77 | AA44: =+N44+Q44+T44+W44 -> 29339.92 | AC44: =+Y44/L44 -> 3.7139578 | AD44: =+Z44/$L44 -> 1.3838265 | AE44: =+AA44/$L44 -> 0.36383829 | AF44: =SUM(AC44:AE44) -> 5.4616226 | AG44: x | AH44: =+(ROUND(AF44,2)-AJ44)/AJ44 -> 0.0018348624 | AJ44: =VLOOKUP(E44,Syspro!$A$2:$F$91,6,FALSE) -> 5.45 | AK44: 5.45 | AL44: 5.31 | AM44: 4.9 | AN44: 3.84 | AO44: 4.31 | AP44: 4.3062002 | AQ44: 4.04 | AR44: 4.11 | AS44: 4.11 | AT44: 4.16 | AU44: 4.16 | AV44: 3.91 | AW44: 3.6268439 | AX44: 3.6559691 | AY44: 3.11 | AZ44: 2.68 | BB44: =(+AF44-AJ44)/AJ44 -> 0.002132588
A45: D00006 | B45: Damper Assembly | C45: =SUMIF('Asset Allocation'!$F$1:$I$270,Calc!A45,'Asset Allocation'!I:I) -> 373692.79 | D45: =133+38 -> 171 | E45: D00006 | F45: =SUMIF(Wages!$O$2:$P$220,Calc!E45,Wages!$P$2:$P$220) -> 2.75 | G45: =SUMIF(Wages!$O$2:$AD$192,Calc!E45,Wages!$AD$2:$AD$192) -> 1097852.6 | I45: 2.31 | J45: =+G45/L45 -> 3.4654439 | L45: =+F45*40*48*60 -> 316800 | M45: =+$D45/$D$48*M$39 -> 188077.72 | N45: =+$D45/$D$48*N$39 -> 12279.944 | P45: =+P$39*$C45/$C$48 -> 12390.659 | Q45: =+Q$39*$C45/$C$48 -> 21243.813 | S45: =+$S$39*L45/$L$48 -> 155572.32 | T45: =+$T$39*L45/$L$48 -> 35345.203 | W45: =+$W$39*F45/$F$48 -> 22582.592 | Y45: =+G45 -> 1097852.6 | Z45: =+M45+P45+S45+V45 -> 356040.7 | AA45: =+N45+Q45+T45+W45 -> 91451.552 | AC45: =+Y45/L45 -> 3.4654439 | AD45: =+Z45/$L45 -> 1.1238659 | AE45: =+AA45/$L45 -> 0.28867283 | AF45: =SUM(AC45:AE45) -> 4.8779826 | AG45: x | AH45: =+(ROUND(AF45,2)-AJ45)/AJ45 -> 0 | AJ45: =VLOOKUP(E45,Syspro!$A$2:$F$91,6,FALSE) -> 4.88 | AK45: 4.87 | AL45: 5.18 | AM45: 4.73 | AN45: 4.68 | AO45: 4.33 | AP45: 4.336537 | AQ45: 4.04 | AR45: 3.92 | AS45: 3.92 | AT45: 4.04 | AU45: 3.87 | AV45: 3.73 | AW45: 3.4860328 | AX45: 3.558088 | AY45: 3.11 | AZ45: 2.68 | BB45: =(+AF45-AJ45)/AJ45 -> -0.00041339739
A46: D00007 | B46: Testing | C46: =SUMIF('Asset Allocation'!$F$1:$I$270,Calc!A46,'Asset Allocation'!I:I) -> 0 | D46: 40 | E46: D00007 | F46: =SUMIF(Wages!$O$2:$P$220,Calc!E46,Wages!$P$2:$P$220) -> 0.3 | G46: =SUMIF(Wages!$O$2:$AD$192,Calc!E46,Wages!$AD$2:$AD$192) -> 143488.71 | I46: 2.31 | J46: =+G46/L46 -> 4.1518723 | L46: =+F46*40*48*60 -> 34560 | M46: =+$D46/$D$48*M$39 -> 43994.789 | N46: =+$D46/$D$48*N$39 -> 2872.5014 | P46: =+P$39*$C46/$C$48 -> 0 | Q46: =+Q$39*$C46/$C$48 -> 0 | S46: =+$S$39*L46/$L$48 -> 16971.526 | T46: =+$T$39*L46/$L$48 -> 3855.8404 | W46: =+$W$39*F46/$F$48 -> 2463.5555 | Y46: =+G46 -> 143488.71 | Z46: =+M46+P46+S46+V46 -> 60966.315 | AA46: =+N46+Q46+T46+W46 -> 9191.8973 | AC46: =+Y46/L46 -> 4.1518723 | AD46: =+Z46/$L46 -> 1.7640716 | AE46: =+AA46/$L46 -> 0.26596925 | AF46: =SUM(AC46:AE46) -> 6.1819132 | AG46: x | AH46: =+(ROUND(AF46,2)-AJ46)/AJ46 -> 0 | AJ46: =VLOOKUP(E46,Syspro!$A$2:$F$91,6,FALSE) -> 6.18 | AK46: 6.14 | AL46: 6.0383444 | AM46: 5.75 | AN46: 4.45 | AO46: 4.34 | AP46: 4.3397079 | AQ46: 4.22 | AR46: 4.21 | AS46: 4.21 | AT46: 4.35 | AU46: 4.26 | AV46: 4.25 | AW46: 4.0201748 | AX46: 3.9397243 | AY46: 3.11 | AZ46: 2.68 | BB46: =(+AF46-AJ46)/AJ46 -> 0.00030957973
A47: D00008 | B47: Damper QC | C47: =SUMIF('Asset Allocation'!$F$1:$I$270,Calc!A47,'Asset Allocation'!I:I) -> 0 | D47: 20 | E47: D00008 | F47: =SUMIF(Wages!$O$2:$P$220,Calc!E47,Wages!$P$2:$P$220) -> 1 | G47: =SUMIF(Wages!$O$2:$AD$192,Calc!E47,Wages!$AD$2:$AD$192) -> 288041.34 | I47: 2.31 | J47: =+G47/L47 -> 2.5003588 | L47: =+F47*40*48*60 -> 115200 | M47: =+$D47/$D$48*M$39 -> 21997.395 | N47: =+$D47/$D$48*N$39 -> 1436.2507 | P47: =+P$39*$C47/$C$48 -> 0 | Q47: =+Q$39*$C47/$C$48 -> 0 | S47: =+$S$39*L47/$L$48 -> 56571.753 | T47: =+$T$39*L47/$L$48 -> 12852.801 | W47: =+$W$39*F47/$F$48 -> 8211.8517 | Y47: =+G47 -> 288041.34 | Z47: =+M47+P47+S47+V47 -> 78569.148 | AA47: =+N47+Q47+T47+W47 -> 22500.904 | AC47: =+Y47/L47 -> 2.5003588 | AD47: =+Z47/$L47 -> 0.68202385 | AE47: =+AA47/$L47 -> 0.19532034 | AF47: =SUM(AC47:AE47) -> 3.377703 | AG47: x | AH47: =+(ROUND(AF47,2)-AJ47)/AJ47 -> -1.3138734e-16 | AJ47: =VLOOKUP(E47,Syspro!$A$2:$F$91,6,FALSE) -> 3.38 | AK47: 3.35 | AL47: 3.29 | AM47: 3.07 | AN47: 2.96 | AO47: 2.89 | AP47: 2.8882452 | AQ47: 2.82 | AR47: 0 | AS47: 3.61 | AT47: 2.55 | AU47: 2.51 | AV47: 4.25 | AW47: 4.0201748 | AX47: 3.9397243 | AY47: 3.11 | AZ47: 2.68 | BB47: =(+AF47-AJ47)/AJ47 -> -0.00067957294
B48: Dampers | C48: =SUM(C40:C47) -> 654673.44 | D48: =SUM(D40:D47) -> 455 | F48: =SUM(F40:F47) -> 10 | L48: =SUM(L40:L47) -> 1152000 | AB48: x
A49: Despatch | B49: Lansdowne | E49: Despatch | M49: =HLOOKUP($B$51,Overhead!$M:$M,M$1,FALSE) -> 211467.76 | N49: =HLOOKUP($B$51,Overhead!$M:$M,N$1,FALSE) -> 13807.093 | P49: =HLOOKUP($B$51,Overhead!$M:$M,P$1,FALSE) -> 130243.38 | Q49: =HLOOKUP($B$51,Overhead!$M:$M,Q$1,FALSE) -> 54101.022 | S49: =HLOOKUP($B$51,Overhead!$M:$M,S$1,FALSE) -> 486795.4 | T49: =HLOOKUP($B$51,Overhead!$M:$M,T$1,FALSE) -> 111177.47 | W49: =HLOOKUP($B$51,Overhead!$M:$M,W$1,FALSE) -> 65694.814 | Y49: =SUM(Y50) -> 3310056.9 | Z49: =SUM(Z50) -> 828506.54 | AA49: =SUM(AA50) -> 245301.64
A50: F00001 | B50: Despatch | C50: =SUMIF('Asset Allocation'!$F$2:$I$269,Calc!$A50,'Asset Allocation'!$I$2:$I$269) -> 951672.94 | D50: 348 | E50: F00001 | F50: =SUMIF(Wages!$O$2:$P$220,Calc!E50,Wages!$P$2:$P$220) -> 8 | G50: =SUMIF(Wages!$O$2:$AD$192,Calc!E50,Wages!$AD$2:$AD$192) -> 3310056.9 | I50: 2.17 | J50: =+G50/L50 -> 3.5916416 | L50: =+F50*40*48*60 -> 921600 | M50: =+$D51/$D$50*M$49 -> 211467.76 | N50: =+$D51/$D$50*N$49 -> 13807.093 | P50: =+$C51/$C$50*P$49 -> 130243.38 | Q50: =+$C51/$C$50*Q$49 -> 54101.022 | S50: =+$S$49*L50/$L$51 -> 486795.4 | T50: =+$S$49*M50/$L$51 -> 111698.71 | W50: =+$F51/$F$50*W$49 -> 65694.814 | Y50: =+G50 -> 3310056.9 | Z50: =+M50+P50+S50+V50 -> 828506.54 | AA50: =+N50+Q50+T50+W50 -> 245301.64 | AC50: =+Y50/L50 -> 3.5916416 | AD50: =+Z50/$L50 -> 0.89898713 | AE50: =+AA50/$L50 -> 0.26616931 | AF50: =SUM(AC50:AE50) -> 4.7567981 | AG50: x | AH50: =+(AF50-AJ50)/AJ50 -> -0.00067267607 | AJ50: =VLOOKUP(E50,Syspro!$A$2:$F$91,6,FALSE) -> 4.76 | AK50: 4.63 | AL50: 4.5609836 | AM50: 4.29 | AN50: 4.19 | AO50: 3.83 | AP50: 3.829613 | AQ50: 3.95 | AR50: 3.66 | AS50: 3.66 | AT50: 3.7 | AU50: 3.62 | AV50: 5.95 | AW50: 5.6135438 | AX50: 5.2458174 | AY50: 3.75 | AZ50: 2.76 | BB50: =(+AF50-AJ50)/AJ50 -> -0.00067267607
B51: Despatch | C51: =SUM(C50) -> 951672.94 | D51: =SUM(D50) -> 348 | F51: =SUM(F50) -> 8 | L51: =SUM(L50) -> 921600
A53: F00002 | B53: Dispatch Ottery | C53: =SUMIF('Asset Allocation'!$F$1:$I$270,Calc!A53,'Asset Allocation'!I:I) -> 0 | D53: 0 | E53: F00002 | F53: =SUMIF(Wages!$O$2:$P$190,Calc!E53,Wages!$P$2:$P$190) -> 0 | G53: =SUMIF(Wages!$O$2:$AD$192,Calc!E53,Wages!$AD$2:$AD$192) -> 0 | AJ53: 0 | AK53: 0 | AM53: 0 | AN53: 0 | AO53: 0 | AQ53: 0 | AR53: 0 | AS53: 0 | AT53: 0 | AU53: 0 | AV53: 4.42 | AW53: 4.1720919 | AX53: 3.9828268 | AY53: 3.75 | AZ53: 2.76 | BB53: =(+AF53-AJ53)/AJ53 -> #DIV/0!
B54: Total | C54: =SUM(C53) -> 0 | D54: =+D53 -> 0
A56: Powder | E56: Powder
B57: Lansdowne | M57: =HLOOKUP($B$61,Overhead!$K:$K,M$1,FALSE) -> 362653.02 | N57: =HLOOKUP($B$61,Overhead!$K:$K,N$1,FALSE) -> 23678.227 | P57: =HLOOKUP($B$61,Overhead!$K:$K,P$1,FALSE) -> 119389.76 | Q57: =HLOOKUP($B$61,Overhead!$K:$K,Q$1,FALSE) -> 137660.94 | S57: =HLOOKUP($B$61,Overhead!$K:$K,S$1,FALSE) -> 443673.82 | T57: =HLOOKUP($B$61,Overhead!$K:$K,T$1,FALSE) -> 641712.14 | W57: =HLOOKUP($B$61,Overhead!$K:$K,W$1,FALSE) -> 90330.369 | Y57: =SUM(Y58:Y60) -> 2795899 | Z57: =+M57+P57+S57+V57 -> 925716.61 | AA57: =+N57+Q57+T57+W57 -> 893381.67
A58: P00001 | B58: Chemical Treatment | C58: =SUMIF('Asset Allocation'!$F$1:$I$270,Calc!A58,'Asset Allocation'!I:I) -> 90418.53 | D58: 60 | E58: P00001 | F58: =SUMIF(Wages!$O$2:$P$220,Calc!E58,Wages!$P$2:$P$220) -> 2 | G58: =SUMIF(Wages!$O$2:$AD$192,Calc!E58,Wages!$AD$2:$AD$192) -> 508753.44 | J58: =+G58/L58 -> 4.4162625 | L58: =40*48*60 -> 115200 | M58: =+$D58/$D$61*M$57 -> 40294.78 | N58: =+$D58/$D$61*N$57 -> 2630.9141 | P58: =+P$57*$C58/$C$61 -> 4457.9128 | Q58: =+Q$57*$C58/$C$61 -> 5140.1429 | W58: =+$W$57*F58/$F$61 -> 16423.703 | Y58: =+G58 -> 508753.44 | Z58: =+M58+P58+S58+V58 -> 44752.693 | AA58: =+N58+Q58+T58+W58 -> 24194.76 | AC58: =+Y58/L58 -> 4.4162625 | AD58: =+Z58/$L58 -> 0.38847824 | AE58: =+AA58/$L58 -> 0.21002396 | AF58: =SUM(AC58:AE58) -> 5.0147647 | AG58: x | AH58: =+(AF58-AJ58)/AJ58 -> -0.0010428834 | AJ58: =VLOOKUP(E58,Syspro!$A$2:$F$91,6,FALSE) -> 5.02 | AK58: 5.02 | AL58: 4.9001013 | AM58: 4.59 | AN58: 4.38 | AO58: 4.27 | AP58: 4.2690819 | AQ58: 4.06 | AR58: 3.05 | AS58: 3.05 | AT58: 3.01 | AU58: 2.94 | AV58: 4.08 | AW58: 3.8907143 | AX58: 4.0201843 | AY58: 34.09 | AZ58: 26.76 | BB58: =(+AF58-AJ58)/AJ58 -> -0.0010428834
A59: P00002 | B59: Powder Coating | C59: =SUMIF('Asset Allocation'!$F$1:$I$270,Calc!A59,'Asset Allocation'!I:I) -> 2268466.9 | D59: 451 | E59: P00002 | F59: =SUMIF(Wages!$O$2:$P$220,Calc!E59,Wages!$P$2:$P$220) -> 8 | G59: =SUMIF(Wages!$O$2:$AD$192,Calc!E59,Wages!$AD$2:$AD$192) -> 2107815.5 | I59: 10.25 | J59: =+G59/L59 -> 18.297009 | L59: =40*48*60 -> 115200 | M59: =+$D59/$D$61*M$57 -> 302882.43 | N59: =+$D59/$D$61*N$57 -> 19775.704 | P59: =+P$57*$C59/$C$61 -> 111842.42 | Q59: =+Q$57*$C59/$C$61 -> 128958.56 | S59: =+S57 -> 443673.82 | T59: =+T57 -> 641712.14 | W59: =+$W$57*F59/$F$61 -> 65694.814 | Y59: =+G59 -> 2107815.5 | Z59: =+M59+P59+S59+V59 -> 858398.67 | AA59: =+N59+Q59+T59+W59 -> 856141.22 | AC59: =+Y59/L59 -> 18.297009 | AD59: =+Z59/$L59 -> 7.4513774 | AE59: =+AA59/$L59 -> 7.4317814 | AF59: =SUM(AC59:AE59) -> 33.180168 | AG59: x | AH59: =+(AF59-AJ59)/AJ59 -> 5.0723334e-06 | AJ59: =VLOOKUP(E59,Syspro!$A$2:$F$91,6,FALSE) -> 33.18 | AK59: 32.67 | AL59: 29.479999 | AM59: 23.38 | AN59: 21.29 | AO59: 20.95 | AP59: 20.94874 | AQ59: 21 | AR59: 21.44 | AS59: 21.44 | AT59: 23.19 | AU59: 22.2 | AV59: 21.96 | AW59: 19.829145 | AX59: 22.687407 | AY59: 34.09 | AZ59: 26.76 | BB59: =(+AF59-AJ59)/AJ59 -> 5.0723334e-06
A60: P00003 | B60: Wetspray | C60: =SUMIF('Asset Allocation'!$F$1:$I$270,Calc!A60,'Asset Allocation'!I:I) -> 62661.96 | D60: 29 | E60: P00003 | F60: =SUMIF(Wages!$O$2:$P$220,Calc!E60,Wages!$P$2:$P$220) -> 1 | G60: =SUMIF(Wages!$O$2:$AD$192,Calc!E60,Wages!$AD$2:$AD$192) -> 179330.04 | J60: =+G60/L60 -> 1.5566844 | L60: =40*48*60 -> 115200 | M60: =+$D60/$D$61*M$57 -> 19475.81 | N60: =+$D60/$D$61*N$57 -> 1271.6085 | P60: =+P$57*$C60/$C$61 -> 3089.4282 | Q60: =+Q$57*$C60/$C$61 -> 3562.2281 | W60: =+$W$57*F60/$F$61 -> 8211.8517 | Y60: =+G60 -> 179330.04 | Z60: =+M60+P60+S60+V60 -> 22565.239 | AA60: =+N60+Q60+T60+W60 -> 13045.688 | AC60: =+Y60/L60 -> 1.5566844 | AD60: =+Z60/$L60 -> 0.19587881 | AE60: =+AA60/$L60 -> 0.11324382 | AF60: =SUM(AC60:AE60) -> 1.865807 | AG60: x | AH60: =+(AF60-AJ60)/AJ60 -> -0.0022422465 | AJ60: =VLOOKUP(E60,Syspro!$A$2:$F$91,6,FALSE) -> 1.87 | AK60: 1.87 | AL60: 1.8093084 | AM60: 1.72 | AN60: 1.63 | AO60: 1.7 | AP60: 1.6975675 | AQ60: 1.65 | AR60: 1.59 | AS60: 1.59 | AT60: 1.58 | AU60: 1.54 | AV60: 1.59 | AW60: 1.4883672 | AX60: 1.4024574 | AY60: 34.09 | AZ60: 26.76 | BB60: =(+AF60-AJ60)/AJ60 -> -0.0022422465
B61: Powder | C61: =SUM(C58:C60) -> 2421547.3 | D61: =SUM(D58:D60) -> 540 | F61: =SUM(F58:F60) -> 11 | L61: =SUM(L58:L60) -> 345600 | AB61: x
A63: 02PWET | B63: Wetspray PTA | C63: =SUMIF('Asset Allocation'!$F$1:$I$270,Calc!A63,'Asset Allocation'!I:I) -> 0 | D63: 0 | E63: 02PWET | F63: =SUMIF(Wages!$O$2:$P$190,Calc!E63,Wages!$P$2:$P$190) -> 1 | G63: =SUMIF(Wages!$O$2:$AD$192,Calc!E63,Wages!$AD$2:$AD$192) -> 179330.04 | J63: =+G63/L63 -> 1.5566844 | L63: =40*48*60 -> 115200 | M63: =+$D63/$D$61*M$57 -> 0 | N63: =+$D63/$D$61*N$57 -> 0 | P63: =+P$57*$C63/$C$61 -> 0 | Q63: =+Q$57*$C63/$C$61 -> 0 | W63: =+$W$57*F63/$F$61 -> 8211.8517 | Y63: =+G63 -> 179330.04 | Z63: =+M63+P63+S63+V63 -> 0 | AA63: =+N63+Q63+T63+W63 -> 8211.8517 | AC63: =+Y63/L63 -> 1.5566844 | AD63: =+Z63/$L63 -> 0 | AE63: =+AA63/$L63 -> 0.071283435 | AF63: =SUM(AC63:AE63) -> 1.6279678 | AG63: x | AH63: =+(AF63-AJ63)/AJ63 -> -0.0012467459 | AJ63: =VLOOKUP(E63,Syspro!$A$2:$F$91,6,FALSE) -> 1.63 | AK63: 1.63 | AL63: 1.5964527 | AM63: 1.51 | AN63: 1.43 | AO63: 1.37 | AP63: 1.3661123 | AQ63: 1.54 | AR63: 1.59 | AS63: 1.59 | AT63: 1.58 | AU63: 1.54 | AV63: 1.59 | AW63: 1.4883672 | AX63: 1.4024574 | AY63: 34.09 | AZ63: 26.76 | BB63: =(+AF63-AJ63)/AJ63 -> -0.0012467459
B65: Ottery
A66: P00004 | B66: Powder Coating Ottery | C66: =SUMIF('Asset Allocation'!$F$1:$I$270,Calc!A66,'Asset Allocation'!I:I) -> 0 | D66: 0 | E66: P00004 | F66: =SUMIF(Wages!$O$2:$P$190,Calc!E66,Wages!$P$2:$P$190) -> 0 | G66: =SUMIF(Wages!$O$2:$AD$192,Calc!E66,Wages!$AD$2:$AD$192) -> 0 | AJ66: =VLOOKUP(E66,Syspro!$A$2:$F$91,6,FALSE) -> 0 | AK66: 0 | AM66: 0 | AN66: 0 | AO66: 0 | AQ66: 0 | AR66: 0 | AS66: 0 | AT66: 0 | AU66: 0 | AV66: 18.57 | AW66: 16.934017 | AX66: 16.969238 | AY66: 34.09 | AZ66: 26.76 | BB66: =(+AF66-AW66)/AW66 -> -1
A67: P00005 | B67: Chemical Treatment Ottery | C67: =SUMIF('Asset Allocation'!$F$1:$I$270,Calc!A67,'Asset Allocation'!I:I) -> 0 | D67: 0 | E67: P00005 | F67: =SUMIF(Wages!$O$2:$P$190,Calc!E67,Wages!$P$2:$P$190) -> 0 | G67: =SUMIF(Wages!$O$2:$AD$192,Calc!E67,Wages!$AD$2:$AD$192) -> 0 | AJ67: 0 | AK67: 0 | AM67: 0 | AN67: 0 | AO67: 0 | AQ67: 0 | AR67: 0 | AS67: 0 | AT67: 0 | AU67: 0 | AV67: 2.92 | AW67: 2.6800509 | AX67: 2.5084993 | AY67: 34.09 | AZ67: 26.76 | BB67: =(+AF67-AW67)/AW67 -> -1
B68: Total | F68: =SUM(F66:F67) -> 0
A71: Press | B71: Changed to Machine Minutes as more staff than Machines | E71: Press | M71: =HLOOKUP($B$76,Overhead!$L:$L,M$1,FALSE) -> 191372.93 | N71: =HLOOKUP($B$76,Overhead!$L:$L,N$1,FALSE) -> 12495.107 | P71: =HLOOKUP($B$76,Overhead!$L:$L,P$1,FALSE) -> 217072.3 | Q71: =HLOOKUP($B$76,Overhead!$L:$L,Q$1,FALSE) -> 219677.81 | S71: =HLOOKUP($B$76,Overhead!$L:$L,S$1,FALSE) -> 828149.11 | T71: =HLOOKUP($B$76,Overhead!$L:$L,T$1,FALSE) -> 263692.03 | W71: =HLOOKUP($B$76,Overhead!$L:$L,W$1,FALSE) -> 32847.407 | Y71: =SUM(Y73:Y75) -> 749517.16 | Z71: =SUM(Z73:Z75) -> 978820.4 | AA71: =SUM(AA73:AA75) -> 403231.85
A72: PS00001 | B72: Hydraulic | C72: =SUMIF('Asset Allocation'!$F$1:$I$270,Calc!A72,'Asset Allocation'!I:I) -> 903204.05 | D72: 65 | E72: PS00001 | F72: 1 | G72: =SUMIF(Wages!$O$2:$AD$192,Calc!E72,Wages!$AD$2:$AD$192) -> 217338.04 | I72: 1.81 | J72: =+G72/L72 -> 1.886615 | L72: =40*48*60*F72 -> 115200 | M72: =+$D72/$D$76*M$71 -> 63790.976 | N72: =+$D72/$D$76*N$71 -> 4165.0355 | P72: =+P$71*$C72/$C$76 -> 50736.656 | Q72: =+Q$71*$C72/$C$76 -> 51345.647 | S72: =+S75 -> 207037.28 | T72: =+T75 -> 65923.007 | W72: =+W75 -> 8211.8517 | Y72: =+G72 -> 217338.04 | Z72: =+M72+P72+S72+V72 -> 321564.91 | AA72: =+N72+Q72+T72+W72 -> 129645.54 | AC72: =+Y72/L72 -> 1.886615 | AD72: =+Z72/$L72 -> 2.7913621 | AE72: =+AA72/$L72 -> 1.1253953 | AF72: =SUM(AC72:AE72) -> 5.8033723 | AG72: x | AH72: =+(AF72-AJ72)/AJ72 -> -0.0011407333 | AJ72: =VLOOKUP(E72,Syspro!$A$2:$F$91,6,FALSE) -> 5.81 | AK72: 5.79 | AL72: 5.0098913 | AM72: 4.62 | AN72: 4.48 | AO72: 4.15 | AP72: 4.1449563 | AQ72: 4.82 | AR72: 4.75 | AS72: 4.75 | AT72: 4.98 | AU72: 4.88 | AV72: 4.48 | AW72: 3.7160623 | AX72: 3.8362062 | AY72: 7.08 | AZ72: 6.45 | BB72: =(+AF72-AJ72)/AJ72 -> -0.0011407333
A73: PS00002 | B73: HME | C73: =SUMIF('Asset Allocation'!$F$1:$I$270,Calc!A73,'Asset Allocation'!I:I) -> 588955.93 | D73: 65 | E73: PS00002 | F73: 1 | G73: =SUMIF(Wages!$O$2:$AD$192,Calc!E73,Wages!$AD$2:$AD$192) -> 266089.56 | I73: 1.81 | J73: =+G73/L73 -> 2.3098052 | L73: =40*48*60*F73 -> 115200 | M73: =+$D73/$D$76*M$71 -> 63790.976 | N73: =+$D73/$D$76*N$71 -> 4165.0355 | P73: =+P$71*$C73/$C$76 -> 33084.057 | Q73: =+Q$71*$C73/$C$76 -> 33481.164 | S73: =+S71/4 -> 207037.28 | T73: =+T71/4 -> 65923.007 | W73: =+W71/4 -> 8211.8517 | Y73: =+G73 -> 266089.56 | Z73: =+M73+P73+S73+V73 -> 303912.31 | AA73: =+N73+Q73+T73+W73 -> 111781.06 | AC73: =+Y73/L73 -> 2.3098052 | AD73: =+Z73/$L73 -> 2.6381277 | AE73: =+AA73/$L73 -> 0.97032169 | AF73: =SUM(AC73:AE73) -> 5.9182546 | AG73: x | AH73: =+(AF73-AJ73)/AJ73 -> -0.00029483334 | AJ73: =VLOOKUP(E73,Syspro!$A$2:$F$91,6,FALSE) -> 5.92 | AK73: 5.86 | AL73: 5.2690756 | AM73: 4.85 | AN73: 5.78 | AO73: 5.45 | AP73: 5.4493629 | AQ73: 5.83 | AR73: 5.7 | AS73: 5.7 | AT73: 5.18 | AU73: 5.04 | AV73: 6.41 | AW73: 6.3172089 | AX73: 6.3205154 | AY73: 7.08 | AZ73: 6.45 | BB73: =(+AF73-AJ73)/AJ73 -> -0.00029483334
A74: PS00003 | B74: Tos | C74: =SUMIF('Asset Allocation'!$F$1:$I$270,Calc!A74,'Asset Allocation'!I:I) -> 1665656 | D74: 65 | E74: PS00003 | F74: 1 | G74: =SUMIF(Wages!$O$2:$AD$192,Calc!E74,Wages!$AD$2:$AD$192) -> 266089.56 | I74: 1.81 | J74: =+G74/L74 -> 2.3098052 | L74: =40*48*60*F74 -> 115200 | M74: =+$D74/$D$76*M$71 -> 63790.976 | N74: =+$D74/$D$76*N$71 -> 4165.0355 | P74: =+P$71*$C74/$C$76 -> 93566.691 | Q74: =+Q$71*$C74/$C$76 -> 94689.769 | S74: =+S73 -> 207037.28 | T74: =+T73 -> 65923.007 | W74: =+W73 -> 8211.8517 | Y74: =+G74 -> 266089.56 | Z74: =+M74+P74+S74+V74 -> 364394.94 | AA74: =+N74+Q74+T74+W74 -> 172989.66 | AC74: =+Y74/L74 -> 2.3098052 | AD74: =+Z74/$L74 -> 3.1631506 | AE74: =+AA74/$L74 -> 1.5016464 | AF74: =SUM(AC74:AE74) -> 6.9746021 | AG74: x | AH74: =+(AF74-AJ74)/AJ74 -> 0.00066027865 | AJ74: =VLOOKUP(E74,Syspro!$A$2:$F$91,6,FALSE) -> 6.97 | AK74: 7.03 | AL74: 6.3184798 | AM74: 5.9 | AN74: 5.79 | AO74: 5.38 | AP74: 5.3724565 | AQ74: 5.92 | AR74: 5.8 | AS74: 5.8 | AT74: 5.67 | AU74: 5.56 | AV74: 6.32 | AW74: 7.2659664 | AX74: 7.4891487 | AY74: 7.08 | AZ74: 6.45 | BB74: =(+AF74-AJ74)/AJ74 -> 0.00066027865
A75: PS00004 | B75: Efurt | C75: =SUMIF('Asset Allocation'!$F$1:$I$270,Calc!A75,'Asset Allocation'!I:I) -> 706462.75 | D75: 65 | E75: PS00004 | F75: 1 | G75: =SUMIF(Wages!$O$2:$AD$192,Calc!E75,Wages!$AD$2:$AD$192) -> 217338.04 | I75: 1.81 | J75: =+G75/L75 -> 1.886615 | L75: =40*48*60*F75 -> 115200 | M75: =+$D75/$D$76*M$71 -> 63790.976 | N75: =+$D75/$D$76*N$71 -> 4165.0355 | P75: =+P$71*$C75/$C$76 -> 39684.895 | Q75: =+Q$71*$C75/$C$76 -> 40161.231 | S75: =+S74 -> 207037.28 | T75: =+T74 -> 65923.007 | W75: =+W74 -> 8211.8517 | Y75: =+G75 -> 217338.04 | Z75: =+M75+P75+S75+V75 -> 310513.15 | AA75: =+N75+Q75+T75+W75 -> 118461.13 | AC75: =+Y75/L75 -> 1.886615 | AD75: =+Z75/$L75 -> 2.6954266 | AE75: =+AA75/$L75 -> 1.0283084 | AF75: =SUM(AC75:AE75) -> 5.61035 | AG75: x | AH75: =+(AF75-AJ75)/AJ75 -> -0.0017170869 | AJ75: =VLOOKUP(E75,Syspro!$A$2:$F$91,6,FALSE) -> 5.62 | AK75: 5.56 | AL75: 4.7487016 | AM75: 4.43 | AN75: 5.25 | AO75: 4.8 | AP75: 4.8016488 | AQ75: 5.45 | AR75: 5.33 | AS75: 5.33 | AT75: 4.95 | AU75: 4.83 | AV75: 7.7 | AW75: 6.1000625 | AX75: 6.053045 | AY75: 7.08 | AZ75: 6.45 | BB75: =(+AF75-AJ75)/AJ75 -> -0.0017170869
B76: Press | C76: =SUM(C72:C75) -> 3864278.7 | D76: =SUM(D73:D75) -> 195 | F76: =SUM(F72:F75) -> 4 | AB76: x | AG76: x
A77: PS00005 | B77: Bending Brakes | E77: =+A77 -> PS00005 | L77: =40*48*60*F77 -> 0 | AB77: M00002 | AC77: =+AC5 -> 4.0758935 | AD77: =+AD5 -> 1.2807816 | AE77: =+AE5 -> 0.78307628 | AF77: =SUM(AC77:AE77) -> 6.1397513 | AG77: x | AH77: =+(AF77-AJ77)/AJ77 -> -4.0497278e-05 | AJ77: =VLOOKUP(E77,Syspro!$A$2:$F$91,6,FALSE) -> 6.14 | AK77: 7.52 | AL77: 7.0896489 | AM77: 6.56 | AN77: 4.02 | AO77: =+AF77-AJ77 -> -0.00024865328
A78: PS00006 | B78: Spot Welding | E78: =+A78 -> PS00006 | L78: =40*48*60*F78 -> 0 | AB78: M00003 | AC78: =+AC6 -> 3.1383226 | AD78: =+AD6 -> 0.85632259 | AE78: =+AE6 -> 0.40169841 | AF78: =SUM(AC78:AE78) -> 4.3963435 | AG78: x | AH78: =+(AF78-AJ78)/AJ78 -> -0.00083101205 | AJ78: =VLOOKUP(E78,Syspro!$A$2:$F$91,6,FALSE) -> 4.4 | AK78: 4.42 | AL78: 3.9685487 | AM78: 4.15 | AN78: 4.07 | AO78: =+AF78-AJ78 -> -0.003656453
A79: PS00007 | B79: Grinding | E79: =+A79 -> PS00007 | L79: =40*48*60*F79 -> 0 | AB79: M00004 | AC79: =+AC7 -> 2.7792546 | AD79: =+AD7 -> 2.4115359 | AE79: =+AE7 -> 0.52805206 | AF79: =SUM(AC79:AE79) -> 5.7188426 | AG79: x | AH79: =+(AF79-AJ79)/AJ79 -> -0.00020234211 | AJ79: =VLOOKUP(E79,Syspro!$A$2:$F$91,6,FALSE) -> 5.72 | AK79: 5.71 | AL79: 5.3915324 | AM79: 5.34 | AN79: 2.96 | AO79: =+AF79-AJ79 -> -0.0011573969
A80: PS00008 | B80: Notching | E80: =+A80 -> PS00008 | L80: =40*48*60*F80 -> 0 | AB80: M00005 | AC80: =+AC8 -> 2.7792546 | AD80: =+AD8 -> 0.80310378 | AE80: =+AE8 -> 0.34744906 | AF80: =SUM(AC80:AE80) -> 3.9298074 | AG80: x | AH80: =+(AF80-AJ80)/AJ80 -> -0.043842471 | AJ80: =VLOOKUP(E80,Syspro!$A$2:$F$91,6,FALSE) -> 4.11 | AK80: 3.94 | AL80: 3.690239 | AM80: 3.63 | AN80: 3.89 | AO80: =+AF80-AJ80 -> -0.18019255
A81: PS00009 | B81: Rolling | E81: =+A81 -> PS00009 | L81: =40*48*60*F81 -> 0 | AB81: M00006 | AC81: =+AC10 -> 2.2871621 | AD81: =+AD10 -> 0.75594005 | AE81: =+AE10 -> 0.34113228 | AF81: =SUM(AC81:AE81) -> 3.3842344 | AG81: x | AH81: =+(AF81-AJ81)/AJ81 -> -0.0017007537 | AJ81: =VLOOKUP(E81,Syspro!$A$2:$F$91,6,FALSE) -> 3.39 | AK81: 3.4 | AL81: 3.1886977 | AM81: 3.25 | AN81: 3.76 | AO81: =+AF81-AJ81 -> -0.0057655549
A82: PS00010 | B82: Mig Welding | E82: =+A82 -> PS00010 | L82: =40*48*60*F82 -> 0 | AB82: M00008 | AC82: =+AC13 -> 3.918419 | AD82: =+AD13 -> 0.94740762 | AE82: =+AE13 -> 0.33953221 | AF82: =SUM(AC82:AE82) -> 5.2053589 | AG82: x | AH82: =+(AF82-AJ82)/AJ82 -> -0.00089081561 | AJ82: =VLOOKUP(E82,Syspro!$A$2:$F$91,6,FALSE) -> 5.21 | AK82: 5.21 | AL82: 4.9506932 | AM82: 4.84 | AN82: 4.15 | AO82: =+AF82-AJ82 -> -0.0046411493
A83: PS00011 | B83: Miscellaneous | E83: =+A83 -> PS00011 | L83: =40*48*60*F83 -> 0 | AB83: M00099 | AC83: =+AC12 -> 2.8897955 | AD83: =+AD12 -> 0.82537217 | AE83: =+AE12 -> 0.37350091 | AF83: =SUM(AC83:AE83) -> 4.0886686 | AG83: x | AH83: =+(AF83-AJ83)/AJ83 -> -0.00032552493 | AJ83: =VLOOKUP(E83,Syspro!$A$2:$F$91,6,FALSE) -> 4.09 | AK83: 4.11 | AL83: 3.7800581 | AM83: 4.05 | AN83: 4.07 | AO83: =+AF83-AJ83 -> -0.001331397
A86: Flex | E86: Flex
A87: X00001 | B87: Flex Ducting | C87: =SUMIF('Asset Allocation'!$F$1:$I$270,Calc!A87,'Asset Allocation'!I:I) -> 351270.5 | D87: 95 | E87: X00001 | F87: =SUMIF(Wages!$O$2:$P$190,Calc!E87,Wages!$P$2:$P$190) -> 2 | G87: =SUMIF(Wages!$O$2:$AD$192,Calc!E87,Wages!$AD$2:$AD$192) -> 548473.1 | I87: 2.33 | J87: =+G87/L87 -> 2.3805256 | L87: =+F87*40*48*60 -> 230400 | M87: =HLOOKUP($B$88,Overhead!$N:$N,M$1,FALSE) -> 125349.19 | N87: =HLOOKUP($B$88,Overhead!$N:$N,N$1,FALSE) -> 8184.2948 | P87: =HLOOKUP($B$88,Overhead!$N:$N,P$1,FALSE) -> 10853.615 | Q87: =HLOOKUP($B$88,Overhead!$N:$N,Q$1,FALSE) -> 19969.143 | S87: =HLOOKUP($B$88,Overhead!$N:$N,S$1,FALSE) -> 294557.75 | T87: =HLOOKUP($B$88,Overhead!$N:$N,T$1,FALSE) -> 94906.406 | W87: =HLOOKUP($B$88,Overhead!$N:$N,W$1,FALSE) -> 16423.703 | Y87: =+G87 -> 548473.1 | Z87: =+M87+P87+S87+V87 -> 430760.56 | AA87: =+N87+Q87+T87+W87 -> 139483.55 | AC87: =+Y87/L87 -> 2.3805256 | AD87: =+Z87/$L87 -> 1.8696205 | AE87: =+AA87/$L87 -> 0.60539734 | AF87: =SUM(AC87:AE87) -> 4.8555435 | AG87: x | AH87: =+(AF87-AJ87)/AJ87 -> -0.00091698532 | AJ87: =VLOOKUP(E87,Syspro!$A$2:$F$91,6,FALSE) -> 4.86 | AK87: 4.79 | AL87: 4.6206935 | AM87: 4.3 | AN87: 4.02 | AO87: 3.86 | AP87: 3.8640254 | AQ87: 3.84 | AR87: 3.71 | AS87: 3.71 | AT87: 3.8 | AU87: 3.71 | AV87: 3.87 | AW87: 3.7631285 | AX87: 3.6800102 | AY87: 2.34 | AZ87: 2.33 | BB87: =(+AF87-AJ87)/AJ87 -> -0.00091698532
B88: Flex | C88: =SUM(C87) -> 351270.5 | D88: =SUM(D87) -> 95 | F88: =SUM(F87) -> 2
A90: Injection | E90: Injection | J90: =SUM(G91:G94) -> 530306.47 | M90: =HLOOKUP($B$96,Overhead!$O:$O,M$1,FALSE) -> 95686.964 | N90: =HLOOKUP($B$96,Overhead!$O:$O,N$1,FALSE) -> 6247.5533 | P90: =HLOOKUP($B$96,Overhead!$O:$O,P$1,FALSE) -> 32560.845 | Q90: =HLOOKUP($B$96,Overhead!$O:$O,Q$1,FALSE) -> 70447.196 | S90: =HLOOKUP($B$96,Overhead!$O:$O,S$1,FALSE) -> 317955.73 | T90: =HLOOKUP($B$96,Overhead!$O:$O,T$1,FALSE) -> 161919.25 | W90: =HLOOKUP($B$96,Overhead!$O:$O,W$1,FALSE) -> 32847.407
A91: INJ00001 | B91: Arburg All Rounder | C91: =+'Asset Allocation'!I327 -> 466471 | D91: 33 | E91: INJ00001 | F91: 1 | G91: =SUMIF(Wages!$O$2:$AD$206,Calc!E91,Wages!$AD$2:$AD$206) -> 176070.44 | J91: =+J90/3/$L$91 -> 1.5344516 | L91: =+F91*40*48*60 -> 115200 | M91: =+$D91/$D$96*$M$90 -> 23564.7 | N91: =+D91/$D$96*$N$90 -> 1538.5765 | P91: =+P$90*$C91/$C$96 -> 12256.722 | Q91: =+Q$90*$C91/$C$96 -> 26518.1 | S91: =+S90/3 -> 105985.24 | T91: =+T90/3 -> 53973.083 | W91: =+W90/3 -> 10949.136 | Y91: =+$G$96/3 -> 176768.82 | Z91: =+M91+P91+S91+V91 -> 141806.67 | AA91: =+N91+Q91+T91+W91 -> 92978.895 | AC91: =+Y91/$L$91 -> 1.5344516 | AD91: =+Z91/$L91 -> 1.2309606 | AE91: =+AA91/$L91 -> 0.80710846 | AF91: =SUM(AC91:AE91) -> 3.5725207 | AG91: x | AH91: =+(AF91-AJ91)/AJ91 -> 0.00070608265 | AJ91: =VLOOKUP(E91,Syspro!$A$2:$F$91,6,FALSE) -> 3.57 | AK91: 3.54 | AL91: 3.3712238 | AM91: 3.16 | AN91: 3.22 | AO91: 3.13 | AP91: 3.1244751 | AQ91: 3.26 | AR91: 3.76 | AS91: 0 | AT91: 0 | AU91: 0 | AV91: 0 | AW91: 0 | AX91: 0 | AY91: 0 | AZ91: 0 | BB91: =(+AF91-AJ91)/AJ91 -> 0.00070608265
A92: INJ00002 | B92: Arburg 25Ton | C92: =+'Asset Allocation'!I328 -> 406471 | D92: 33 | E92: INJ00002 | F92: 1 | G92: =SUMIF(Wages!$O$2:$AD$206,Calc!E92,Wages!$AD$2:$AD$206) -> 176070.44 | J92: =+$J$90/3/$L92 -> 1.5344516 | L92: =+F92*40*48*60 -> 115200 | M92: =+D92/$D$96*$M$90 -> 23564.7 | N92: =+D92/$D$96*$N$90 -> 1538.5765 | P92: =+P$90*$C92/$C$96 -> 10680.197 | Q92: =+Q$90*$C92/$C$96 -> 23107.2 | S92: =+S91 -> 105985.24 | T92: =+T91 -> 53973.083 | W92: =+W91 -> 10949.136 | Y92: =+$G$96/3 -> 176768.82 | Z92: =+M92+P92+S92+V92 -> 140230.14 | AA92: =+N92+Q92+T92+W92 -> 89567.995 | AC92: =+Y92/L92 -> 1.5344516 | AD92: =+Z92/$L92 -> 1.2172755 | AE92: =+AA92/$L92 -> 0.77749995 | AF92: =SUM(AC92:AE92) -> 3.5292271 | AG92: x | AH92: =+(AF92-AJ92)/AJ92 -> -0.00021895429 | AJ92: =VLOOKUP(E92,Syspro!$A$2:$F$91,6,FALSE) -> 3.53 | AK92: 3.49 | AL92: 3.3304642 | AM92: 3.12 | AN92: 3.18 | AO92: 3.09 | AP92: 3.0944654 | AQ92: 3.22 | AR92: 0 | AS92: 0 | AT92: 0 | AU92: 0 | AV92: 0 | AW92: 0 | AX92: 0 | AY92: 0 | AZ92: 0 | BB92: =(+AF92-AJ92)/AJ92 -> -0.00021895429
A93: INJ00003 | B93: Victor 90 | C93: =+'Asset Allocation'!I329 -> 366271 | D93: 34 | E93: INJ00003 | F93: 1 | G93: =SUMIF(Wages!$O$2:$AD$206,Calc!E93,Wages!$AD$2:$AD$206) -> 178165.6 | J93: =+$J$90/3/$L93 -> 1.5344516 | L93: =+F93*40*48*60 -> 115200 | M93: =+D93/$D$96*$M$90 -> 24278.782 | N93: =+D93/$D$96*$N$90 -> 1585.2001 | P93: =+P$90*$C93/$C$96 -> 9623.9252 | Q93: =+Q$90*$C93/$C$96 -> 20821.897 | S93: =+S91 -> 105985.24 | T93: =+T91 -> 53973.083 | W93: =+W91 -> 10949.136 | Y93: =+$G$96/3 -> 176768.82 | Z93: =+M93+P93+S93+V93 -> 139887.95 | AA93: =+N93+Q93+T93+W93 -> 87329.315 | AC93: =+Y93/L93 -> 1.5344516 | AD93: =+Z93/$L93 -> 1.2143051 | AE93: =+AA93/$L93 -> 0.75806697 | AF93: =SUM(AC93:AE93) -> 3.5068237 | AG93: x | AH93: =+(AF93-AJ93)/AJ93 -> 0.013532864 | AJ93: =VLOOKUP(E93,Syspro!$A$2:$F$91,6,FALSE) -> 3.46 | AK93: 3.46 | AL93: 3.3097958 | AM93: 3.09 | AN93: 3.17 | AO93: 3.09 | AP93: 3.0905391 | AQ93: 3.22 | AR93: 0 | AS93: 0 | AT93: 0 | AU93: 0 | AV93: 0 | AW93: 0 | AX93: 0 | AY93: 0 | AZ93: 0 | BB93: =(+AF93-AJ93)/AJ93 -> 0.013532864
A94: INJ0004 | B94: Flashing | D94: 34 | E94: INJ0004 | F94: 1 | G94: =SUMIF(Wages!$O$2:$AD$206,Calc!E94,Wages!$AD$2:$AD$206) -> 0 | J94: =+$J$90/3/$L94 -> 1.5344516 | L94: =+F94*40*48*60 -> 115200 | M94: =+D94/$D$96*$M$90 -> 24278.782 | N94: =+D94/$D$96*$N$90 -> 1585.2001 | P94: =+P$90*$C94/$C$96 -> 0 | Q94: =+Q$90*$C94/$C$96 -> 0 | S94: =+S92 -> 105985.24 | T94: =+T92 -> 53973.083 | W94: =+W92 -> 10949.136 | Y94: =+$G$96/3 -> 176768.82 | Z94: =+M94+P94+S94+V94 -> 130264.03 | AA94: =+N94+Q94+T94+W94 -> 66507.419 | AC94: =+Y94/L94 -> 1.5344516 | AD94: =+Z94/$L94 -> 1.1307641 | AE94: =+AA94/$L94 -> 0.57732134 | AF94: =SUM(AC94:AE94) -> 3.2425371 | AG94: x | AH94: =+(AF94-AJ94)/AJ94 -> 0.00078304352 | AJ94: =VLOOKUP(E94,Syspro!$A$2:$F$91,6,FALSE) -> 3.24 | AK94: 3.15 | AL94: 3.0430932 | AM94: 2.84 | AN94: 2.95 | AO94: 2.9 | AP94: 2.8972411 | AQ94: 3.01 | AR94: 0 | AS94: 0 | AT94: 0 | AU94: 0 | AV94: 0 | AW94: 0 | AX94: 0 | AY94: 0 | AZ94: 0 | BB94: =(+AF94-AJ94)/AJ94 -> 0.00078304352
B96: Injection | C96: =SUM(C91:C94) -> 1239213 | D96: =SUM(D91:D94) -> 134 | F96: =SUM(F91:F94) -> 4 | G96: =SUM(G91:G94) -> 530306.47
A98: Laser | E98: Laser
A99: L00001 | C99: =+'Asset Allocation'!I336 -> 1289500 | D99: 60 | E99: L00001 | F99: 1 | G99: =SUMIF(Wages!$O$2:$AD$231,Calc!E99,Wages!$AD$2:$AD$231) -> 312932.33 | I99: 2.06 | J99: =+G99/L99 -> 2.7164264 | L99: =+F99*40*48*60 -> 115200 | M99: =HLOOKUP($B$104,Overhead!$P:$P,M$1,FALSE) -> 117694.88 | N99: =HLOOKUP($B$104,Overhead!$P:$P,N$1,FALSE) -> 7684.4905 | P99: =HLOOKUP($B$104,Overhead!$P:$P,P$1,FALSE) -> 21707.23 | Q99: =HLOOKUP($B$104,Overhead!$P:$P,Q$1,FALSE) -> 65306.704 | S99: =HLOOKUP($B$104,Overhead!$P:$P,S$1,FALSE) -> 373479.88 | T99: =HLOOKUP($B$104,Overhead!$P:$P,T$1,FALSE) -> 100001.27 | W99: =HLOOKUP($B$104,Overhead!$P:$P,W$1,FALSE) -> 37774.518 | Y99: =+G99 -> 312932.33 | Z99: =+M99+P99+S99+V99 -> 512881.99 | AA99: =+N99+Q99+T99+W99 -> 210766.98 | AC99: =+Y99/L99 -> 2.7164264 | AD99: =+Z99/$L99 -> 4.4521006 | AE99: =+AA99/$L99 -> 1.8295745 | AF99: =SUM(AC99:AE99) -> 8.9981015 | AG99: x | AH99: =+(AF99-AJ99)/AJ99 -> -0.00021094167 | AJ99: =VLOOKUP(E99,Syspro!$A$2:$F$91,6,FALSE) -> 9 | AK99: 8.97 | AL99: 8.4000028 | AM99: 7.86 | AN99: 7.26 | AO99: 6.96 | AP99: 6.9494925 | AQ99: 7.23 | AR99: 0 | AS99: 0 | AT99: 0 | AU99: 0 | AV99: 0 | AW99: 0 | AX99: 0 | AY99: 0 | AZ99: 0 | BB99: =(+AF99-AJ99)/AJ99 -> -0.00021094167
B100: Laser | C100: =SUM(C99) -> 1289500 | D100: =SUM(D99) -> 60 | F100: =SUM(F99) -> 1
A102: Prep | E102: Prep
A103: R00001 | C103: =+'Asset Allocation'!I227 -> 1148788.3 | D103: 65 | E103: R00001 | F103: 4.6 | G103: =SUMIF(Wages!$O$2:$AD$192,Calc!E103,Wages!$AD$2:$AD$192) -> 1692844 | I103: 2.06 | J103: =+G103/L103 -> 3.1945275 | L103: =+F103*40*48*60 -> 529920 | M103: =HLOOKUP($B$104,Overhead!$P:$P,M$1,FALSE) -> 117694.88 | N103: =HLOOKUP($B$104,Overhead!$P:$P,N$1,FALSE) -> 7684.4905 | P103: =HLOOKUP($B$104,Overhead!$P:$P,P$1,FALSE) -> 21707.23 | Q103: =HLOOKUP($B$104,Overhead!$P:$P,Q$1,FALSE) -> 65306.704 | S103: =HLOOKUP($B$104,Overhead!$P:$P,S$1,FALSE) -> 373479.88 | T103: =HLOOKUP($B$104,Overhead!$P:$P,T$1,FALSE) -> 100001.27 | W103: =HLOOKUP($B$104,Overhead!$P:$P,W$1,FALSE) -> 37774.518 | Y103: =+G103 -> 1692844 | Z103: =+M103+P103+S103+V103 -> 512881.99 | AA103: =+N103+Q103+T103+W103 -> 210766.98 | AC103: =+Y103/L103 -> 3.1945275 | AD103: =+Z103/$L103 -> 0.96784796 | AE103: =+AA103/$L103 -> 0.39773358 | AF103: =SUM(AC103:AE103) -> 4.560109 | AG103: x | AH103: =+(AF103-AJ103)/AJ103 -> 2.3913917e-05 | AJ103: =VLOOKUP(E103,Syspro!$A$2:$F$91,6,FALSE) -> 4.56 | AK103: 4.55 | AL103: 5.080116 | AM103: 4.79 | AN103: 4.18 | AO103: 4.12 | AP103: 4.1202749 | AQ103: 4.03 | AR103: 4.04 | AS103: 4.04 | AT103: 4.18 | AU103: 4.03 | AV103: 3.73 | AW103: 3.4985212 | AX103: 3.3481015 | AZ103: 2.51 | BB103: =(+AF103-AJ103)/AJ103 -> 2.3913917e-05
B104: Prep | C104: =SUM(C103) -> 1148788.3 | D104: =SUM(D103) -> 65 | F104: =SUM(F103) -> 4.6
C105: =+C104+C88+C76++C68+C61+C54+C48+C51+C37+C34+C26+C23+C14+C100+C96 -> 19643069 | D105: =+D104+D88+D76+D68+D61+D54+D48+D51+D37+D34+D26+D23+D14+D100+D96 -> 2861 | F105: =+F14+F23+F25+F34+F36+F48+F50+F53+F61+F68+F76+F87+F103 -> 64.2 | AF105: =SUM(AF5:AF103) -> 268.01234 | AH105: =+(AF105-AJ105)/AJ105 -> -0.00055064806 | AJ105: =SUM(AJ5:AJ103) -> 268.16 | AK105: 269.79 | AL105: 254.98529 | AM105: 239.74 | AN105: 222.79 | AO105: 187.97 | AP105: 187.97513 | AQ105: 188.51 | AR105: 162.2 | AS105: 165.15 | AT105: 168.11 | BB105: =(+AF105-AJ105)/AJ105 -> -0.00055064806
B107: Recon
B108: Total Excl PTA | C108: =+C105-C37 -> 19597192
B109: AssetAllocation | C109: =+'Asset Allocation'!K340 -> 19597192

Sheet Asset Allocation
A1: PTA | K1: Lansdowne Asset recon | O1: Years SinceBought | P1: Average Age x Price to get Weighting for R&M | Q1: Sensitivity to Breakdowns(Scale1-5)
A2: P&M782 | B2: Compressor and Riveter | C2: 42217 | D2: 6057.02 | F2: 01PTA | G2: Pta | H2: 1 | I2: =+D2*H2 -> 6057.02 | N2: =NOW() -> 46204.531 | O2: =_xlfn.DAYS(N2,C2)/365 -> 10.923288 | P2: =+O2*I2 -> 66162.572
A3: P&M823 | B3: Electrical Fan | C3: 42644 | D3: 12116.23 | F3: 01PTA | G3: Pta | H3: 1 | I3: =+D3*H3 -> 12116.23 | N3: =NOW() -> 46204.531 | O3: =_xlfn.DAYS(N3,C3)/365 -> 9.7534247 | P3: =+O3*I3 -> 118174.74
A4: F&F654 | B4: Container and Shelves | C4: 40848 | D4: 27703.98 | F4: 01PTA | G4: Pta | H4: 1 | I4: =+D4*H4 -> 27703.98 | N4: =NOW() -> 46204.531 | O4: =_xlfn.DAYS(N4,C4)/365 -> 14.673973 | P4: =+O4*I4 -> 406527.44
C5: PTAWET | I5: =SUM(I2:I4) -> 45877.23 | Q5: 1 | R5: =SUM(P2:P4)*Q5 -> 590864.75 | S5: =+R5/$R$338 -> 0.0011013506
A6: Trumpf
A7: P&M697 | B7: Trumpf CNC Press | C7: 41275 | D7: 3626679 | F7: 05 | G7: Ott | H7: 1 | I7: =+D7*H7 -> 3626679 | N7: =NOW() -> 46204.531 | O7: =_xlfn.DAYS(N7,C7)/365 -> 13.50411 | P7: =+O7*I7 -> 48975071
A8: P&M792 | B8: Air Dryer and Drains | C8: 42370 | D8: 124550 | F8: 05 | G8: Ott | H8: 1 | I8: =+D8*H8 -> 124550 | N8: =NOW() -> 46204.531 | O8: =_xlfn.DAYS(N8,C8)/365 -> 10.50411 | P8: =+O8*I8 -> 1308286.8
A9: P&M804 | B9: Reconnecting Air Dryer and Piping | C9: 42430 | D9: 33923 | F9: 05 | G9: Ott | H9: 1 | I9: =+D9*H9 -> 33923 | N9: =NOW() -> 46204.531 | O9: =_xlfn.DAYS(N9,C9)/365 -> 10.339726 | P9: =+O9*I9 -> 350754.53
A10: P&M812 | B10: Air Dryer Trumpf | C10: 42522 | D10: 15057 | F10: 05 | G10: Ott | H10: 1 | I10: =+D10*H10 -> 15057 | N10: =NOW() -> 46204.531 | O10: =_xlfn.DAYS(N10,C10)/365 -> 10.087671 | P10: =+O10*I10 -> 151890.07
A11: TOO610 | B11: Die and Punches as per INV23442 | C11: 40238 | D11: 10735 | F11: 05 | G11: Ott | H11: 1 | I11: =+D11*H11 -> 10735 | N11: =NOW() -> 46204.531 | O11: =_xlfn.DAYS(N11,C11)/365 -> 16.345205 | P11: =+O11*I11 -> 175465.78
A12: TOO621 | B12: 1KVA UPS | C12: 40330 | D12: 2707.5 | F12: 05 | G12: Ott | H12: 1 | I12: =+D12*H12 -> 2707.5 | N12: =NOW() -> 46204.531 | O12: =_xlfn.DAYS(N12,C12)/365 -> 16.093151 | P12: =+O12*I12 -> 43572.205
A13: TOO696 | B13: Various Trumf tools 30 000 Eur | C13: 41275 | D13: 327210 | F13: 05 | G13: Ott | H13: 1 | I13: =+D13*H13 -> 327210 | N13: =NOW() -> 46204.531 | O13: =_xlfn.DAYS(N13,C13)/365 -> 13.50411 | P13: =+O13*I13 -> 4418679.7
A14: TOO711 | B14: Louvre Tool - Trumpf | C14: 41365 | D14: 12898 | F14: 05 | G14: Ott | H14: 1 | I14: =+D14*H14 -> 12898 | N14: =NOW() -> 46204.531 | O14: =_xlfn.DAYS(N14,C14)/365 -> 13.257534 | P14: =+O14*I14 -> 170995.68
A15: TOO721 | B15: Roll Splitting Tool | C15: 41456 | D15: 39817 | F15: 05 | G15: Ott | H15: 1 | I15: =+D15*H15 -> 39817 | N15: =NOW() -> 46204.531 | O15: =_xlfn.DAYS(N15,C15)/365 -> 13.008219 | P15: =+O15*I15 -> 517948.26
A16: TOO739 | B16: Trumpf Tooling | C16: 41730 | D16: 8800 | F16: 05 | G16: Ott | H16: 1 | I16: =+D16*H16 -> 8800 | N16: =NOW() -> 46204.531 | O16: =_xlfn.DAYS(N16,C16)/365 -> 12.257534 | P16: =+O16*I16 -> 107866.3
A17: TOO777 | B17: Roller Cutting Tool | C17: 42156 | D17: 19300 | F17: 05 | G17: Ott | H17: 1 | I17: =+D17*H17 -> 19300 | N17: =NOW() -> 46204.531 | O17: =_xlfn.DAYS(N17,C17)/365 -> 11.090411 | P17: =+O17*I17 -> 214044.93
A18: TOO961 | B18: Trumph Additional set Dies & punches | C18: 43556 | D18: 22380 | F18: 05 | G18: Ott | H18: 1 | I18: =+D18*H18 -> 22380 | N18: =NOW() -> 46204.531 | O18: =_xlfn.DAYS(N18,C18)/365 -> 7.2547945 | P18: =+O18*I18 -> 162362.3
... A20: TOO802 | B20: VRD Outer Edge | C20: 42401 | D20: 35000 | F20: 05 | G20: Ott | H20: 1 | I20: =+D20*H20 -> 35000 | N20: =NOW() -> 46204.531 | O20: =_xlfn.DAYS(N20,C20)/365 -> 10.419178 | P20: =+O20*I20 -> 364671.23
C21: Trumpf | I21: =SUM(I7:I20) -> 4317281 | J21: x | K21: =+I21 -> 4317281 | Q21: 4 | R21: =SUM(P7:P20)*Q21 -> 2.2870015e+08 | S21: =+R21/$R$338 -> 0.42628885
A22: DiffuserAssembly
A23: TOO459 | B23: Bayonet Fitting | C23: 39387 | D23: 94000 | F23: A00003 | G23: Lan | H23: 1 | I23: =+D23*H23 -> 94000 | N23: =NOW() -> 46204.531 | O23: =_xlfn.DAYS(N23,C23)/365 -> 18.676712 | P23: =+O23*I23 -> 1755611
A24: TOO349 | B24: SPINNING DIE/JIG SWIRL PLATE | C24: 38565 | D24: 2900 | F24: A00005 | G24: Lan | H24: 1 | I24: =+D24*H24 -> 2900 | N24: =NOW() -> 46204.531 | O24: =_xlfn.DAYS(N24,C24)/365 -> 20.928767 | P24: =+O24*I24 -> 60693.425
A25: TOO350 | B25: SPINNING DIE/JIG MED SWIRL Rnd | C25: 38565 | D25: 2900 | F25: A00005 | G25: Lan | H25: 1 | I25: =+D25*H25 -> 2900 | N25: =NOW() -> 46204.531 | O25: =_xlfn.DAYS(N25,C25)/365 -> 20.928767 | P25: =+O25*I25 -> 60693.425
A26: TOO450 | B26: Wall Stat Design and Mould | C26: 39326 | D26: 126700 | F26: A00005 | G26: Lan | H26: 1 | I26: =+D26*H26 -> 126700 | N26: =NOW() -> 46204.531 | O26: =_xlfn.DAYS(N26,C26)/365 -> 18.843836 | P26: =+O26*I26 -> 2387514
A27: T00151 | B27: Vortex Testing Tubes | C27: 37288 | D27: 5419.38 | F27: A00006 | G27: Lan | H27: 1 | I27: =+D27*H27 -> 5419.38 | N27: =NOW() -> 46204.531 | O27: =_xlfn.DAYS(N27,C27)/365 -> 24.427397 | P27: =+O27*I27 -> 132381.35
C28: Assembly | I28: =SUM(I23:I27) -> 231919.38 | J28: x | K28: =+I28 -> 231919.38 | Q28: 1 | R28: =SUM(P14:P27)*Q28 -> 6148210.7 | S28: =+R28/$R$338 -> 0.011460044
A31: Dampers
A32: TOO443 | B32: Mitre Saw LS101034 | C32: 39173 | D32: 7850 | F32: D00001 | G32: Ott | H32: 1 | I32: =+D32*H32 -> 7850 | N32: =NOW() -> 46204.531 | O32: =_xlfn.DAYS(N32,C32)/365 -> 19.263014 | P32: =+O32*I32 -> 151214.66
A33: TOO453 | B33: VLN Piercing Tool | C33: 39326 | D33: 8770 | F33: D00001 | G33: Ott | H33: 1 | I33: =+D33*H33 -> 8770 | N33: =NOW() -> 46204.531 | O33: =_xlfn.DAYS(N33,C33)/365 -> 18.843836 | P33: =+O33*I33 -> 165260.44
A34: TOO904 | B34: Makita slide Mitre Saw (Damper dept) | C34: 43040 | D34: 7578.11 | F34: D00001 | G34: Ott | H34: 1 | I34: =+D34*H34 -> 7578.11 | N34: =NOW() -> 46204.531 | O34: =_xlfn.DAYS(N34,C34)/365 -> 8.6684932 | P34: =+O34*I34 -> 65690.795
A35: TOO985 | B35: GCM 12GDL Gliding/Sliding double bevel saw | C35: 44075 | D35: 13042.61 | F35: D00001 | H35: 1 | I35: =+D35*H35 -> 13042.61 | N35: =NOW() -> 46204.531 | O35: =_xlfn.DAYS(N35,C35)/365 -> 5.8328767 | P35: =+O35*I35 -> 76075.936
A36: TOO937 | B36: 1.6mm Notching Machine | C36: 43282 | D36: 5647.83 | F36: D00003 | G36: Ott | H36: 1 | I36: =+D36*H36 -> 5647.83 | N36: =NOW() -> 46204.531 | O36: =_xlfn.DAYS(N36,C36)/365 -> 8.0054795 | P36: =+O36*I36 -> 45213.587
A37: P&M647 | B37: Aliminium Welder | C37: 40787 | D37: 11135 | F37: D00004 | G37: Ott | H37: 1 | I37: =+D37*H37 -> 11135 | N37: =NOW() -> 46204.531 | O37: =_xlfn.DAYS(N37,C37)/365 -> 14.841096 | P37: =+O37*I37 -> 165255.6
A38: P&M713 | B38: Tig Welder | C38: 41395 | D38: 8000 | F38: D00004 | G38: Ott | H38: 1 | I38: =+D38*H38 -> 8000 | N38: =NOW() -> 46204.531 | O38: =_xlfn.DAYS(N38,C38)/365 -> 13.175342 | P38: =+O38*I38 -> 105402.74
A39: TOO495 | B39: ALUMINIUM TIG WELDER | C39: 39539 | D39: 9188 | F39: D00004 | G39: Ott | H39: 1 | I39: =+D39*H39 -> 9188 | N39: =NOW() -> 46204.531 | O39: =_xlfn.DAYS(N39,C39)/365 -> 18.260274 | P39: =+O39*I39 -> 167775.4
A40: P&M365 | B40: PNEUMATIC RIVETER | C40: 38626 | D40: 4672.24 | F40: D00004 | H40: 1 | I40: =+D40*H40 -> 4672.24 | N40: =NOW() -> 46204.531 | O40: =_xlfn.DAYS(N40,C40)/365 -> 20.761644 | P40: =+O40*I40 -> 97003.383
A41: TOO422 | B41: Power Fastner - For RA Griles | C41: 39142 | D41: 22797 | F41: D00005 | G41: Ott | H41: 1 | I41: =+D41*H41 -> 22797 | N41: =NOW() -> 46204.531 | O41: =_xlfn.DAYS(N41,C41)/365 -> 19.347945 | P41: =+O41*I41 -> 441075.11
A42: TOO439 | B42: Extrusion Radius Notching Tool | C42: 39264 | D42: 5470 | F42: D00005 | G42: Ott | H42: 1 | I42: =+D42*H42 -> 5470 | N42: =NOW() -> 46204.531 | O42: =_xlfn.DAYS(N42,C42)/365 -> 19.013699 | P42: =+O42*I42 -> 104004.93
A43: TOO683 | B43: Electric Crimper | C43: 41183 | D43: 9500 | F43: D00005 | G43: Ott | H43: 1 | I43: =+D43*H43 -> 9500 | N43: =NOW() -> 46204.531 | O43: =_xlfn.DAYS(N43,C43)/365 -> 13.756164 | P43: =+O43*I43 -> 130683.56
A44: TOO703 | B44: Hinge Tool | C44: 41306 | D44: 36193 | F44: D00005 | G44: Ott | H44: 1 | I44: =+D44*H44 -> 36193 | N44: =NOW() -> 46204.531 | O44: =_xlfn.DAYS(N44,C44)/365 -> 13.419178 | P44: =+O44*I44 -> 485680.31
A45: TOO956 | B45: Modify RAG Tool | C45: 43525 | D45: 19020 | F45: D00005 | G45: Ott | H45: 1 | I45: =+D45*H45 -> 19020 | N45: =NOW() -> 46204.531 | O45: =_xlfn.DAYS(N45,C45)/365 -> 7.339726 | P45: =+O45*I45 -> 139601.59
A46: TOO796 | B46: RAG Grille Tool | C46: 42401 | D46: 87956 | F46: D00005 | G46: Ott | H46: 1 | I46: =+D46*H46 -> 87956 | N46: =NOW() -> 46204.531 | O46: =_xlfn.DAYS(N46,C46)/365 -> 10.419178 | P46: =+O46*I46 -> 916429.23
A47: TOO331 | B47: 2 Stage VLN form tool | C47: 38384 | D47: 24000 | F47: D00006 | G47: Ott | H47: 1 | I47: =+D47*H47 -> 24000 | N47: =NOW() -> 46204.531 | O47: =_xlfn.DAYS(N47,C47)/365 -> 21.424658 | P47: =+O47*I47 -> 514191.78
A48: TOO332 | B48: Modification to VLN Levers tool | C48: 38411 | D48: 4320 | F48: D00006 | G48: Ott | H48: 1 | I48: =+D48*H48 -> 4320 | N48: =NOW() -> 46204.531 | O48: =_xlfn.DAYS(N48,C48)/365 -> 21.350685 | P48: =+O48*I48 -> 92234.959
A49: TOO565 | B49: ALUMINIUM DIE CHANGES DIE 32449/32450/32451 | C49: 39995 | D49: 15731 | F49: D00006 | G49: Ott | H49: 1 | I49: =+D49*H49 -> 15731 | N49: =NOW() -> 46204.531 | O49: =_xlfn.DAYS(N49,C49)/365 -> 17.010959 | P49: =+O49*I49 -> 267599.39
A50: TOO590 | B50: Modification PHB 4 and 3 | C50: 40118 | D50: 12800 | F50: D00006 | G50: Ott | H50: 1 | I50: =+D50*H50 -> 12800 | N50: =NOW() -> 46204.531 | O50: =_xlfn.DAYS(N50,C50)/365 -> 16.673973 | P50: =+O50*I50 -> 213426.85
A51: TOO597 | B51: Aluminium Die 32450A | C51: 40026 | D51: 3997 | F51: D00006 | G51: Ott | H51: 1 | I51: =+D51*H51 -> 3997 | N51: =NOW() -> 46204.531 | O51: =_xlfn.DAYS(N51,C51)/365 -> 16.926027 | P51: =+O51*I51 -> 67653.332
A52: TOO600 | B52: Various Dies | C52: 40087 | D52: 4212 | F52: D00006 | G52: Ott | H52: 1 | I52: =+D52*H52 -> 4212 | N52: =NOW() -> 46204.531 | O52: =_xlfn.DAYS(N52,C52)/365 -> 16.758904 | P52: =+O52*I52 -> 70588.504
... A66: TOO1051 | B66: Bosch GCM 12GDL doubel bevel saw | C66: 45505 | D66: 13730.43 | F66: D00001 | G66: Ott | H66: 1 | I66: =+D66*H66 -> 13730.43 | N66: =NOW() -> 46204.531 | O66: =_xlfn.DAYS(N66,C66)/365 -> 1.9150685 | P66: =+O66*I66 -> 26294.714
C67: Dampers | I67: =SUM(I32:I66) -> 654673.44 | J67: x | K67: =+I67 -> 654673.44 | Q67: 1 | R67: =SUM(P32:P66)*Q67 -> 7545356.3 | S67: =+R67/$R$338 -> 0.014064273
A72: DESPATCH
A73: TOO690 | B73: Artwork Stereo Boxes | C73: 41214 | D73: 5128 | F73: F00001 | G73: LAN | H73: 1 | I73: =+D73*H73 -> 5128 | N73: =NOW() -> 46204.531 | O73: =_xlfn.DAYS(N73,C73)/365 -> 13.671233 | P73: =+O73*I73 -> 70106.082
A74: TOO699 | B74: Carton Die CT4107 | C74: 41275 | D74: 4330 | F74: F00001 | G74: LAN | H74: 1 | I74: =+D74*H74 -> 4330 | N74: =NOW() -> 46204.531 | O74: =_xlfn.DAYS(N74,C74)/365 -> 13.50411 | P74: =+O74*I74 -> 58472.795
A75: TOO700 | B75: Carton Die CT4109 | C75: 41275 | D75: 6911 | F75: F00001 | G75: LAN | H75: 1 | I75: =+D75*H75 -> 6911 | N75: =NOW() -> 46204.531 | O75: =_xlfn.DAYS(N75,C75)/365 -> 13.50411 | P75: =+O75*I75 -> 93326.901
A76: TOO773 | B76: Dies New Box | C76: 42095 | D76: 13250 | F76: F00001 | G76: LAN | H76: 1 | I76: =+D76*H76 -> 13250 | N76: =NOW() -> 46204.531 | O76: =_xlfn.DAYS(N76,C76)/365 -> 11.257534 | P76: =+O76*I76 -> 149162.33
A77: VEH2725 | B77: Toyota Hino | C77: 41609 | D77: 228733 | F77: F00001 | G77: LAN | H77: 1 | I77: =+D77*H77 -> 228733 | N77: =NOW() -> 46204.531 | O77: =_xlfn.DAYS(N77,C77)/365 -> 12.589041 | P77: =+O77*I77 -> 2879529.1
A78: P&M661 | B78: Strapping Machine | C78: 40969 | D78: 7800 | F78: F00001 | G78: LAN | H78: 1 | I78: =+D78*H78 -> 7800 | N78: =NOW() -> 46204.531 | O78: =_xlfn.DAYS(N78,C78)/365 -> 14.342466 | P78: =+O78*I78 -> 111871.23
A79: VEH2750 | B79: Isuzu KB250 | C79: 41883 | D79: 172643.86 | F79: F00001 | G79: LAN | H79: 1 | I79: =+D79*H79 -> 172643.86 | N79: =NOW() -> 46204.531 | O79: =_xlfn.DAYS(N79,C79)/365 -> 11.838356 | P79: =+O79*I79 -> 2043819.5
A80: VEH444 | B80: Trailer 3000 x 1700 x300 | C80: 39326 | D80: 17061.4 | F80: F00001 | G80: LAN | H80: 1 | I80: =+D80*H80 -> 17061.4 | N80: =NOW() -> 46204.531 | O80: =_xlfn.DAYS(N80,C80)/365 -> 18.843836 | P80: =+O80*I80 -> 321502.22
A81: VEH2774 | B81: Toyota Dyna | C81: 42156 | D81: 239762.5 | F81: F00001 | G81: OTT | H81: 1 | I81: =+D81*H81 -> 239762.5 | N81: =NOW() -> 46204.531 | O81: =_xlfn.DAYS(N81,C81)/365 -> 11.090411 | P81: =+O81*I81 -> 2659064.7
A82: VEH2800 | B82: Isuzu Long Wheen Base Bakkie | C82: 42401 | D82: 238991.78 | F82: F00001 | G82: OTT | H82: 1 | I82: =+D82*H82 -> 238991.78 | N82: =NOW() -> 46204.531 | O82: =_xlfn.DAYS(N82,C82)/365 -> 10.419178 | P82: =+O82*I82 -> 2490097.9
A83: VEH444 | B83: Trailer 3000 x 1700 x300 | C83: 39326 | D83: 17061.4 | F83: F00001 | G83: OTT | H83: 1 | I83: =+D83*H83 -> 17061.4 | N83: =NOW() -> 46204.531 | O83: =_xlfn.DAYS(N83,C83)/365 -> 18.843836 | P83: =+O83*I83 -> 321502.22
C84: DESPATCH | I84: =SUM(I73:I83) -> 951672.94 | K84: =+I84 -> 951672.94 | Q84: 1 | R84: =SUM(P73:P83)*Q84 -> 11198455 | S84: =+R84/$R$338 -> 0.020873517
A86: MANUFACTURING
A87: TOO745 | B87: Bending Brake Tools | C87: 41791 | D87: 23220 | F87: M00001 | G87: LAN | H87: 1 | I87: =+D87*H87 -> 23220 | N87: =NOW() -> 46204.531 | O87: =_xlfn.DAYS(N87,C87)/365 -> 12.090411 | P87: =+O87*I87 -> 280739.34
A88: TOO764 | B88: L Shaped Tool | C88: 41974 | D88: 6960 | F88: M00001 | G88: LAN | H88: 1 | I88: =+D88*H88 -> 6960 | N88: =NOW() -> 46204.531 | O88: =_xlfn.DAYS(N88,C88)/365 -> 11.589041 | P88: =+O88*I88 -> 80659.726
A89: P&M66 | B89: Press Brake | C89: 34700 | D89: 154016 | F89: M00001 | G89: LAN | H89: 1 | I89: =+D89*H89 -> 154016 | N89: =NOW() -> 46204.531 | O89: =_xlfn.DAYS(N89,C89)/365 -> 31.517808 | P89: =+O89*I89 -> 4854246.8
A90: P&M75 | B90: Monitor Press Brake 2 | C90: 36465 | D90: 3886 | F90: M00001 | G90: LAN | H90: 1 | I90: =+D90*H90 -> 3886 | N90: =NOW() -> 46204.531 | O90: =_xlfn.DAYS(N90,C90)/365 -> 26.682192 | P90: =+O90*I90 -> 103687
A91: P&M742 | B91: Bending Brake | C91: 41760 | D91: 465600 | F91: M00001 | G91: LAN | H91: 1 | I91: =+D91*H91 -> 465600 | N91: =NOW() -> 46204.531 | O91: =_xlfn.DAYS(N91,C91)/365 -> 12.175342 | P91: =+O91*I91 -> 5668839.5
A92: P&M906 | B92: Pressbrake Hydraulic Intellifab | C92: 43040 | D92: 153532.35 | F92: M00001 | G92: LAN | H92: 1 | I92: =+D92*H92 -> 153532.35 | N92: =NOW() -> 46204.531 | O92: =_xlfn.DAYS(N92,C92)/365 -> 8.6684932 | P92: =+O92*I92 -> 1330894.1
A93: P&M315 | B93: Ermakson CNC Press Brake & Tooling | C93: 38322 | D93: 227278.39 | F93: M00001 | G93: LAN | H93: 1 | I93: =+D93*H93 -> 227278.39 | N93: =NOW() -> 46204.531 | O93: =_xlfn.DAYS(N93,C93)/365 -> 21.594521 | P93: =+O93*I93 -> 4907967.9
A94: TOO942 | B94: Dies & Punches for Press Brake Bender | C94: 43313 | D94: 48489.12 | F94: M00001 | G94: LAN | H94: 1 | I94: =+D94*H94 -> 48489.12 | N94: =NOW() -> 46204.531 | O94: =_xlfn.DAYS(N94,C94)/365 -> 7.9205479 | P94: =+O94*I94 -> 384060.4
A95: P&M967 | B95: Durma CNC Press Brake AD-S25100 | C95: 43556 | D95: 1260000 | F95: M00001 | G95: LAN | H95: 1 | I95: =+D95*H95 -> 1260000 | N95: =NOW() -> 46204.531 | O95: =_xlfn.DAYS(N95,C95)/365 -> 7.2547945 | P95: =+O95*I95 -> 9141041.1
A96: TOO341 | B96: Weld Tip Sharpener | C96: 38412 | D96: 1519.78 | F96: M00002 | G96: LAN | H96: 1 | I96: =+D96*H96 -> 1519.78 | N96: =NOW() -> 46204.531 | O96: =_xlfn.DAYS(N96,C96)/365 -> 21.347945 | P96: =+O96*I96 -> 32444.18
A97: P&M801 | B97: 50KVA Series 90 Spot Welder | C97: 42401 | D97: 84364 | F97: M00002 | G97: LAN | H97: 1 | I97: =+D97*H97 -> 84364 | N97: =NOW() -> 46204.531 | O97: =_xlfn.DAYS(N97,C97)/365 -> 10.419178 | P97: =+O97*I97 -> 879003.54
A98: P&M801 | B98: 50KVA Series 90 Spot Welder | D98: 42182 | F98: M00002 | G98: LAN | H98: 1 | I98: =+D98*H98 -> 42182 | N98: =NOW() -> 46204.531 | O98: =_xlfn.DAYS(N98,C98)/365 -> 126.5863 | P98: =+O98*I98 -> 5339663.4
A99: P&M291 | B99: Mig Welder | C99: 38169 | D99: 10800 | F99: M00002 | H99: 1 | I99: =+D99*H99 -> 10800 | N99: =NOW() -> 46204.531 | O99: =_xlfn.DAYS(N99,C99)/365 -> 22.013699 | P99: =+O99*I99 -> 237747.95
A100: P&M314 | B100: 2 x SpotWelders (PS 2 WRITTEN OFF) | C100: 38352 | D100: 68840 | F100: M00002 | H100: 1 | I100: =+D100*H100 -> 68840 | N100: =NOW() -> 46204.531 | O100: =_xlfn.DAYS(N100,C100)/365 -> 21.512329 | P100: =+O100*I100 -> 1480908.7
A101: P&M874 | B101: CFW Mobile Griding Dust unit | C101: 42856 | D101: 9456 | F101: M00003 | G101: LAN | H101: 1 | I101: =+D101*H101 -> 9456 | N101: =NOW() -> 46204.531 | O101: =_xlfn.DAYS(N101,C101)/365 -> 9.1726027 | P101: =+O101*I101 -> 86736.132
A102: P&M876 | B102: Electrical installation grinding Stations | C102: 42856 | D102: 43800 | F102: M00003 | G102: LAN | H102: 1 | I102: =+D102*H102 -> 43800 | N102: =NOW() -> 46204.531 | O102: =_xlfn.DAYS(N102,C102)/365 -> 9.1726027 | P102: =+O102*I102 -> 401760
A103: TOO488 | B103: Hole Punch | C103: 39539 | D103: 2500 | F103: M00004 | G103: LAN | H103: 1 | I103: =+D103*H103 -> 2500 | N103: =NOW() -> 46204.531 | O103: =_xlfn.DAYS(N103,C103)/365 -> 18.260274 | P103: =+O103*I103 -> 45650.685
A104: P&M366 | B104: HAND KNOTCHER | C104: 38626 | D104: 3520 | F104: M00004 | G104: LAN | H104: 1 | I104: =+D104*H104 -> 3520 | N104: =NOW() -> 46204.531 | O104: =_xlfn.DAYS(N104,C104)/365 -> 20.761644 | P104: =+O104*I104 -> 73080.986
A105: TOO605 | B105: Flypress tool to Bend Plate | C105: 40210 | D105: 6680 | F105: M00004 | G105: LAN | H105: 1 | I105: =+D105*H105 -> 6680 | N105: =NOW() -> 46204.531 | O105: =_xlfn.DAYS(N105,C105)/365 -> 16.421918 | P105: =+O105*I105 -> 109698.41
A106: P&M850 | B106: Roller Machine | C106: 42736 | D106: 29600 | F106: M00006 | G106: LAN | H106: 1 | I106: =+D106*H106 -> 29600 | N106: =NOW() -> 46204.531 | O106: =_xlfn.DAYS(N106,C106)/365 -> 9.5013699 | P106: =+O106*I106 -> 281240.55
A107: P&M850 | B107: Roller Machine | C107: 42736 | D107: 29600 | F107: M00006 | G107: LAN | H107: 1 | I107: =+D107*H107 -> 29600 | N107: =NOW() -> 46204.531 | O107: =_xlfn.DAYS(N107,C107)/365 -> 9.5013699 | P107: =+O107*I107 -> 281240.55
A108: P&M849 | B108: CMZ Jenny / Beader | C108: 42736 | D108: 22000 | F108: M00007 | G108: LAN | H108: 1 | I108: =+D108*H108 -> 22000 | N108: =NOW() -> 46204.531 | O108: =_xlfn.DAYS(N108,C108)/365 -> 9.5013699 | P108: =+O108*I108 -> 209030.14
A109: P&M849 | B109: CMZ Jenny / Beader | C109: 42736 | D109: 22000 | F109: M00007 | G109: LAN | H109: 1 | I109: =+D109*H109 -> 22000 | N109: =NOW() -> 46204.531 | O109: =_xlfn.DAYS(N109,C109)/365 -> 9.5013699 | P109: =+O109*I109 -> 209030.14
A110: P&M833 | B110: Thermax 250MIG Welder | C110: 42675 | D110: 14946 | F110: M00008 | G110: LAN | H110: 1 | I110: =+D110*H110 -> 14946 | N110: =NOW() -> 46204.531 | O110: =_xlfn.DAYS(N110,C110)/365 -> 9.6684932 | P110: =+O110*I110 -> 144505.3
A111: P&M778 | B111: CNC Guilotene | C111: 42186 | D111: 200000 | F111: M00014 | G111: LAN | H111: 1 | I111: =+D111*H111 -> 200000 | N111: =NOW() -> 46204.531 | O111: =_xlfn.DAYS(N111,C111)/365 -> 11.008219 | P111: =+O111*I111 -> 2201643.8
A112: P&M905 | B112: Guillotine Motorised SMAC | C112: 43040 | D112: 62767.15 | F112: M00014 | G112: LAN | H112: 1 | I112: =+D112*H112 -> 62767.15 | N112: =NOW() -> 46204.531 | O112: =_xlfn.DAYS(N112,C112)/365 -> 8.6684932 | P112: =+O112*I112 -> 544096.61
A113: P&M979 | B113: Pancake Heater Coiling Machine | C113: 43952 | D113: 129490.78 | F113: M00099 | G113: LAN | H113: 1 | I113: =+D113*H113 -> 129490.78 | N113: =NOW() -> 46204.531 | O113: =_xlfn.DAYS(N113,C113)/365 -> 6.169863 | P113: =+O113*I113 -> 798940.37
C114: MANUFACTURING | I114: =SUM(I87:I113) -> 3127047.6 | J114: x | K114: =+I114 -> 3127047.6 | M114: =AVERAGE(C87:C113) -> 41120.731 | Q114: 2 | R114: =SUM(P87:P113)*Q114 -> 80217114 | S114: =+R114/$R$338 -> 0.14952182
A118: PowderCoating
A119: P&M582 | B119: Wetspray Boothe | C119: 40210 | D119: 62661.96 | F119: P00003 | G119: OTT | H119: 1 | I119: =+D119*H119 -> 62661.96 | N119: =NOW() -> 46204.531 | O119: =_xlfn.DAYS(N119,C119)/365 -> 16.421918 | P119: =+O119*I119 -> 1029029.6
A120: P&M583 | B120: Compressor GA26+P and Cabling | C120: 40210 | D120: 140696.5 | F120: P00002 | G120: OTT | H120: 1 | I120: =+D120*H120 -> 140696.5 | N120: =NOW() -> 46204.531 | O120: =_xlfn.DAYS(N120,C120)/365 -> 16.421918 | P120: =+O120*I120 -> 2310506.4
A121: P&M702 | B121: Stripping Baths | C121: 41306 | D121: 53739.29 | F121: P00001 | G121: LAN | H121: 1 | I121: =+D121*H121 -> 53739.29 | N121: =NOW() -> 46204.531 | O121: =_xlfn.DAYS(N121,C121)/365 -> 13.419178 | P121: =+O121*I121 -> 721137.1
A122: P&M798 | B122: 2 x Airstatic Units | C122: 42401 | D122: 48000 | F122: P00002 | G122: OTT | H122: 1 | I122: =+D122*H122 -> 48000 | N122: =NOW() -> 46204.531 | O122: =_xlfn.DAYS(N122,C122)/365 -> 10.419178 | P122: =+O122*I122 -> 500120.55
A123: P&M863 | B123: Powder Coating Plant | C123: 42767 | D123: 1480871.8 | F123: P00002 | G123: LAN | H123: 1 | I123: =+D123*H123 -> 1480871.8 | N123: =NOW() -> 46204.531 | O123: =_xlfn.DAYS(N123,C123)/365 -> 9.4164384 | P123: =+O123*I123 -> 13944538
A124: P&M867 | B124: Powder Coating Additions | C124: 42795 | D124: 331740.42 | F124: P00002 | G124: LAN | H124: 1 | I124: =+D124*H124 -> 331740.42 | N124: =NOW() -> 46204.531 | O124: =_xlfn.DAYS(N124,C124)/365 -> 9.339726 | P124: =+O124*I124 -> 3098364.6
...

Sheet Wages
A1: Damper | J1: Efficiency | L1: Workcentres | P1: Time Allocation | Q1: Amnt per Hour | S1: Annual | T1: Bonus | U1: GainShare | V1: UIF | W1: Pension | X1: Sick Pay Fund | Y1: Dispute Levy | Z1: ADM and TEC Levy | AA1: SDL | AB1: Total | AC1: Efficiency | AD1: Amnt
A2: W0000066 | B2: Leslie | C2: Basson | D2: 7711115085081 | E2: M | F2: C | G2: Damper Cutting/Set-up Assem | H2: DAMPER | I2: 72.85 | J2: 0.5 | K2: OTT | L2: Damper Assembly | M2: 0.45 | O2: D00006 | P2: =+M2 -> 0.45 | Q2: =+$I$2*P2 -> 32.7825 | S2: =+Q2*40*52 -> 68187.6 | T2: =+S2*0.0833 -> 5680.0271 | U2: =+T2 -> 5680.0271 | V2: =+S2*0.01 -> 681.876 | W2: =+S2*0.083 -> 5659.5708 | X2: =+S2*0.0018 -> 122.73768 | Y2: =0.71*52*P2 -> 16.614 | Z2: =172*12*P2 -> 928.8 | AA2: =+(S2+T2+U2)*0.01 -> 795.47654 | AB2: =SUM(S2:AA2) -> 87752.729 | AC2: =IF(+J2>0,J2,AC1) -> 0.5 | AD2: =+AB2/AC2 -> 175505.46
K3: OTT | L3: Cutting | M3: 0.45 | O3: D00001 | P3: =+M3 -> 0.45 | Q3: =+$I$2*P3 -> 32.7825 | S3: =+Q3*40*52 -> 68187.6 | T3: =+S3*0.0833 -> 5680.0271 | U3: =+T3 -> 5680.0271 | V3: =+S3*0.01 -> 681.876 | W3: =+S3*0.083 -> 5659.5708 | X3: =+S3*0.0018 -> 122.73768 | Y3: =0.71*52*P3 -> 16.614 | Z3: =172*12*P3 -> 928.8 | AA3: =+(S3+T3+U3)*0.01 -> 795.47654 | AB3: =SUM(S3:AA3) -> 87752.729 | AC3: =IF(+J3>0,J3,AC2) -> 0.5 | AD3: =+AB3/AC3 -> 175505.46
K4: OTT | L4: Notching | M4: 0.1 | O4: D00003 | P4: =+M4 -> 0.1 | Q4: =+$I$2*P4 -> 7.285 | S4: =+Q4*40*52 -> 15152.8 | T4: =+S4*0.0833 -> 1262.2282 | U4: =+T4 -> 1262.2282 | V4: =+S4*0.01 -> 151.528 | W4: =+S4*0.083 -> 1257.6824 | X4: =+S4*0.0018 -> 27.27504 | Y4: =0.71*52*P4 -> 3.692 | Z4: =172*12*P4 -> 206.4 | AA4: =+(S4+T4+U4)*0.01 -> 176.77256 | AB4: =SUM(S4:AA4) -> 19500.606 | AC4: =IF(+J4>0,J4,AC3) -> 0.5 | AD4: =+AB4/AC4 -> 39001.213
A6: W0000022 | B6: Dale | C6: Fortune | E6: M | F6: C | G6: Leading Hand/Damper Assembl | H6: DAMPER | I6: 109.2 | J6: 0.75 | K6: OTT | L6: Damper Assembly | M6: 0.7 | O6: D00006 | P6: =+M6 -> 0.7 | Q6: =+I6*P6 -> 76.44 | S6: =+Q6*40*52 -> 158995.2 | T6: =+S6*0.0833 -> 13244.3 | U6: =+T6 -> 13244.3 | V6: =+S6*0.01 -> 1589.952 | W6: =+S6*0.083 -> 13196.602 | X6: =+S6*0.0018 -> 286.19136 | Y6: =0.71*52*P6 -> 25.844 | Z6: =172*12*P6 -> 1444.8 | AA6: =+(S6+T6+U6)*0.01 -> 1854.838 | AB6: =SUM(S6:AA6) -> 203882.03 | AC6: =IF(+J6>0,J6,AC5) -> 0.75 | AD6: =+AB6/AC6 -> 271842.7
K7: OTT | L7: Cutting | M7: 0.3 | O7: D00001 | P7: =+M7 -> 0.3 | Q7: =+$I$6*P7 -> 32.76 | S7: =+Q7*40*52 -> 68140.8 | T7: =+S7*0.0833 -> 5676.1286 | U7: =+T7 -> 5676.1286 | V7: =+S7*0.01 -> 681.408 | W7: =+S7*0.083 -> 5655.6864 | X7: =+S7*0.0018 -> 122.65344 | Y7: =0.71*52*P7 -> 11.076 | Z7: =172*12*P7 -> 619.2 | AA7: =+(S7+T7+U7)*0.01 -> 794.93057 | AB7: =SUM(S7:AA7) -> 87378.012 | AC7: =IF(+J7>0,J7,AC6) -> 0.75 | AD7: =+AB7/AC7 -> 116504.02
A9: CON389 | B9: Petula | C9: Amos | E9: F | F9: C | G9: Damper Assembler | H9: DAMPER | I9: 89.52 | J9: 0.5 | K9: OTT | L9: Testing | M9: 0.3 | O9: D00007 | P9: =+M9 -> 0.3 | Q9: =+$I$9*P9 -> 26.856 | S9: =+Q9*40*52 -> 55860.48 | T9: =+S9*0.0833 -> 4653.178 | U9: =+T9 -> 4653.178 | V9: =+S9*0.01 -> 558.6048 | W9: =+S9*0.083 -> 4636.4198 | X9: =+S9*0.0018 -> 100.54886 | Y9: =0.71*52*P9 -> 11.076 | Z9: =172*12*P9 -> 619.2 | AA9: =+(S9+T9+U9)*0.01 -> 651.66836 | AB9: =SUM(S9:AA9) -> 71744.354 | AC9: =IF(+J9>0,J9,AC8) -> 0.5 | AD9: =+AB9/AC9 -> 143488.71
K10: OTT | L10: Damper Assembly | M10: 0.3 | O10: D00006 | P10: =+M10 -> 0.3 | Q10: =+$I$9*P10 -> 26.856 | S10: =+Q10*40*52 -> 55860.48 | T10: =+S10*0.0833 -> 4653.178 | U10: =+T10 -> 4653.178 | V10: =+S10*0.01 -> 558.6048 | W10: =+S10*0.083 -> 4636.4198 | X10: =+S10*0.0018 -> 100.54886 | Y10: =0.71*52*P10 -> 11.076 | Z10: =172*12*P10 -> 619.2 | AA10: =+(S10+T10+U10)*0.01 -> 651.66836 | AB10: =SUM(S10:AA10) -> 71744.354 | AC10: =IF(+J10>0,J10,AC9) -> 0.5 | AD10: =+AB10/AC10 -> 143488.71
K11: OTT | L11: Notching | M11: 0.1 | O11: D00003 | P11: =+M11 -> 0.1 | Q11: =+$I$9*P11 -> 8.952 | S11: =+Q11*40*52 -> 18620.16 | T11: =+S11*0.0833 -> 1551.0593 | U11: =+T11 -> 1551.0593 | V11: =+S11*0.01 -> 186.2016 | W11: =+S11*0.083 -> 1545.4733 | X11: =+S11*0.0018 -> 33.516288 | Y11: =0.71*52*P11 -> 3.692 | Z11: =172*12*P11 -> 206.4 | AA11: =+(S11+T11+U11)*0.01 -> 217.22279 | AB11: =SUM(S11:AA11) -> 23914.785 | AC11: =IF(+J11>0,J11,AC10) -> 0.5 | AD11: =+AB11/AC11 -> 47829.569
K12: OTT | L12: Grille Assembly | M12: 0.3 | O12: D00005 | P12: =+M12 -> 0.3 | Q12: =+$I$9*P12 -> 26.856 | S12: =+Q12*40*52 -> 55860.48 | T12: =+S12*0.0833 -> 4653.178 | U12: =+T12 -> 4653.178 | V12: =+S12*0.01 -> 558.6048 | W12: =+S12*0.083 -> 4636.4198 | X12: =+S12*0.0018 -> 100.54886 | Y12: =0.71*52*P12 -> 11.076 | Z12: =172*12*P12 -> 619.2 | AA12: =+(S12+T12+U12)*0.01 -> 651.66836 | AB12: =SUM(S12:AA12) -> 71744.354 | AC12: =IF(+J12>0,J12,AC10) -> 0.5 | AD12: =+AB12/AC12 -> 143488.71
A15: CON469B | B15: Reuben | C15: Presence | E15: M | F15: C | G15: Welder/Damper Assembler | H15: DAMPER | I15: 87.84 | J15: 0.5 | K15: OTT | L15: Cutting | M15: 0.5 | O15: D00001 | P15: =+M15 -> 0.5 | Q15: =+$I$15*P15 -> 43.92 | S15: =+Q15*40*52 -> 91353.6 | T15: =+S15*0.0833 -> 7609.7549 | U15: =+T15 -> 7609.7549 | V15: =+S15*0.01 -> 913.536 | W15: =+S15*0.083 -> 7582.3488 | X15: =+S15*0.0018 -> 164.43648 | Y15: =0.71*52*P15 -> 18.46 | Z15: =172*12*P15 -> 1032 | AA15: =+(S15+T15+U15)*0.01 -> 1065.7311 | AB15: =SUM(S15:AA15) -> 117349.62 | AC15: =IF(+J15>0,J15,AC14) -> 0.5 | AD15: =+AB15/AC15 -> 234699.24
L16: Welding | M16: 0.4 | O16: D00004 | P16: =+M16 -> 0.4 | Q16: =+$I$15*P16 -> 35.136 | S16: =+Q16*40*52 -> 73082.88 | T16: =+S16*0.0833 -> 6087.8039 | U16: =+T16 -> 6087.8039 | V16: =+S16*0.01 -> 730.8288 | W16: =+S16*0.083 -> 6065.879 | X16: =+S16*0.0018 -> 131.54918 | Y16: =0.71*52*P16 -> 14.768 | Z16: =172*12*P16 -> 825.6 | AA16: =+(S16+T16+U16)*0.01 -> 852.58488 | AB16: =SUM(S16:AA16) -> 93879.698 | AC16: =+AC15 -> 0.5 | AD16: =+AB16/AC16 -> 187759.4
L17: Brushing | M17: 0.1 | O17: D00002 | P17: =+M17 -> 0.1 | Q17: =+$I$15*P17 -> 8.784 | S17: =+Q17*40*52 -> 18270.72 | T17: =+S17*0.0833 -> 1521.951 | U17: =+T17 -> 1521.951 | V17: =+S17*0.01 -> 182.7072 | W17: =+S17*0.083 -> 1516.4698 | X17: =+S17*0.0018 -> 32.887296 | Y17: =0.71*52*P17 -> 3.692 | Z17: =172*12*P17 -> 206.4 | AA17: =+(S17+T17+U17)*0.01 -> 213.14622 | AB17: =SUM(S17:AA17) -> 23469.924 | AC17: =IF(+J17>0,J17,AC15) -> 0.5 | AD17: =+AB17/AC17 -> 46939.849
A19: CON184A | B19: Goodman | C19: Puza | E19: M | F19: A | G19: Welding/Damper Assembly | H19: DAMPER | I19: 81.61 | J19: 0.5 | K19: OTT | L19: Welding | M19: 1 | O19: D00004 | P19: =+M19 -> 1 | Q19: =+I19*P19 -> 81.61 | S19: =+Q19*40*52 -> 169748.8 | T19: =+S19*0.0833 -> 14140.075 | U19: =+T19 -> 14140.075 | V19: =+S19*0.01 -> 1697.488 | W19: =+S19*0.083 -> 14089.15 | X19: =+S19*0.0018 -> 305.54784 | Y19: =0.71*52*P19 -> 36.92 | Z19: =172*12*P19 -> 2064 | AA19: =+(S19+T19+U19)*0.01 -> 1980.2895 | AB19: =SUM(S19:AA19) -> 218202.35 | AC19: =IF(+J19>0,J19,AC18) -> 0.5 | AD19: =+AB19/AC19 -> 436404.69
L20: Damper Assembly | M20: 0 | O20: D00006 | P20: =+M20 -> 0 | Q20: =+I19*P20 -> 0 | S20: =+Q20*40*52 -> 0 | T20: =+S20*0.0833 -> 0 | U20: =+T20 -> 0 | V20: =+S20*0.01 -> 0 | W20: =+S20*0.075 -> 0 | X20: =+S20*0.0018 -> 0 | Y20: =0.71*52*P20 -> 0 | Z20: =172*12*P20 -> 0 | AA20: =+(S20+T20+U20)*0.01 -> 0 | AB20: =SUM(S20:AA20) -> 0 | AC20: =IF(+J20>0,J20,AC19) -> 0.5 | AD20: =+AB20/AC20 -> 0
A22: W0000083 | B22: Riyaaz | C22: Davids | E22: M | F22: C | G22: Welder/Damper Assembler | H22: DAMPER | I22: 72.85 | J22: 0.5 | K22: OTT | L22: Cutting | M22: 0.45 | O22: D00001 | P22: =+M22 -> 0.45 | Q22: =+$I$22*P22 -> 32.7825 | S22: =+Q22*40*52 -> 68187.6 | T22: =+S22*0.0833 -> 5680.0271 | U22: =+T22 -> 5680.0271 | V22: =+S22*0.01 -> 681.876 | W22: =+S22*0.083 -> 5659.5708 | X22: =+S22*0.0018 -> 122.73768 | Y22: =0.71*52*P22 -> 16.614 | Z22: =172*12*P22 -> 928.8 | AA22: =+(S22+T22+U22)*0.01 -> 795.47654 | AB22: =SUM(S22:AA22) -> 87752.729 | AC22: =IF(+J22>0,J22,AC20) -> 0.5 | AD22: =+AB22/AC22 -> 175505.46
L23: Damper Assembly | M23: 0.45 | O23: D00006 | P23: =+M23 -> 0.45 | Q23: =+$I$22*P23 -> 32.7825 | S23: =+Q23*40*52 -> 68187.6 | T23: =+S23*0.0833 -> 5680.0271 | U23: =+T23 -> 5680.0271 | V23: =+S23*0.01 -> 681.876 | W23: =+S23*0.083 -> 5659.5708 | X23: =+S23*0.0018 -> 122.73768 | Y23: =0.71*52*P23 -> 16.614 | Z23: =172*12*P23 -> 928.8 | AA23: =+(S23+T23+U23)*0.01 -> 795.47654 | AB23: =SUM(S23:AA23) -> 87752.729 | AC23: =IF(+J23>0,J23,AC20) -> 0.5 | AD23: =+AB23/AC23 -> 175505.46
L24: Notching | M24: 0.1 | O24: D00003 | P24: =+M24 -> 0.1 | Q24: =+$I$22*P24 -> 7.285 | S24: =+Q24*40*52 -> 15152.8 | T24: =+S24*0.0833 -> 1262.2282 | U24: =+T24 -> 1262.2282 | V24: =+S24*0.01 -> 151.528 | W24: =+S24*0.083 -> 1257.6824 | X24: =+S24*0.0018 -> 27.27504 | Y24: =0.71*52*P24 -> 3.692 | Z24: =172*12*P24 -> 206.4 | AA24: =+(S24+T24+U24)*0.01 -> 176.77256 | AB24: =SUM(S24:AA24) -> 19500.606 | AC24: =IF(+J24>0,J24,AC22) -> 0.5 | AD24: =+AB24/AC24 -> 39001.213
A26: W0000084 | B26: John | C26: Overmeyer | E26: M | F26: C | G26: Welder/Damper Assembler | H26: DAMPER | I26: 72.85 | J26: 0.5 | K26: OTT | L26: Cutting | M26: 0.45 | O26: D00001 | P26: =+M26 -> 0.45 | Q26: =+$I$26*P26 -> 32.7825 | S26: =+Q26*40*52 -> 68187.6 | T26: =+S26*0.0833 -> 5680.0271 | U26: =+T26 -> 5680.0271 | V26: =+S26*0.01 -> 681.876 | W26: =+S26*0.083 -> 5659.5708 | X26: =+S26*0.0018 -> 122.73768 | Y26: =0.71*52*P26 -> 16.614 | Z26: =172*12*P26 -> 928.8 | AA26: =+(S26+T26+U26)*0.01 -> 795.47654 | AB26: =SUM(S26:AA26) -> 87752.729 | AC26: =IF(+J26>0,J26,AC23) -> 0.5 | AD26: =+AB26/AC26 -> 175505.46
L27: Damper Assembly | M27: 0.45 | O27: D00006 | P27: =+M27 -> 0.45 | Q27: =+$I$26*P27 -> 32.7825 | S27: =+Q27*40*52 -> 68187.6 | T27: =+S27*0.0833 -> 5680.0271 | U27: =+T27 -> 5680.0271 | V27: =+S27*0.01 -> 681.876 | W27: =+S27*0.083 -> 5659.5708 | X27: =+S27*0.0018 -> 122.73768 | Y27: =0.71*52*P27 -> 16.614 | Z27: =172*12*P27 -> 928.8 | AA27: =+(S27+T27+U27)*0.01 -> 795.47654 | AB27: =SUM(S27:AA27) -> 87752.729 | AC27: =IF(+J27>0,J27,AC23) -> 0.5 | AD27: =+AB27/AC27 -> 175505.46
L28: Notching | M28: 0.1 | O28: D00003 | P28: =+M28 -> 0.1 | Q28: =+$I$26*P28 -> 7.285 | S28: =+Q28*40*52 -> 15152.8 | T28: =+S28*0.0833 -> 1262.2282 | U28: =+T28 -> 1262.2282 | V28: =+S28*0.01 -> 151.528 | W28: =+S28*0.083 -> 1257.6824 | X28: =+S28*0.0018 -> 27.27504 | Y28: =0.71*52*P28 -> 3.692 | Z28: =172*12*P28 -> 206.4 | AA28: =+(S28+T28+U28)*0.01 -> 176.77256 | AB28: =SUM(S28:AA28) -> 19500.606 | AC28: =IF(+J28>0,J28,AC26) -> 0.5 | AD28: =+AB28/AC28 -> 39001.213
A30: W0000065 | B30: Neil | C30: Lamb | E30: M | F30: c | G30: General Worker | H30: DAMPER | I30: 87.84 | J30: 0.5 | K30: OTT | L30: Cutting | M30: 0.15 | O30: D00001 | P30: =+M30 -> 0.15 | Q30: =+$I$30*P30 -> 13.176 | S30: =+Q30*40*52 -> 27406.08 | T30: =+S30*0.0833 -> 2282.9265 | U30: =+T30 -> 2282.9265 | V30: =+S30*0.01 -> 274.0608 | W30: =+S30*0.083 -> 2274.7046 | X30: =+S30*0.0018 -> 49.330944 | Y30: =0.71*52*P30 -> 5.538 | Z30: =172*12*P30 -> 309.6 | AA30: =+(S30+T30+U30)*0.01 -> 319.71933 | AB30: =SUM(S30:AA30) -> 35204.887 | AC30: =IF(+J30>0,J30,AC20) -> 0.5 | AD30: =+AB30/AC30 -> 70409.773
L31: Notching | M31: 0.15 | O31: D00003 | P31: =+M31 -> 0.15 | Q31: =+$I$30*P31 -> 13.176 | S31: =+Q31*40*52 -> 27406.08 | T31: =+S31*0.0833 -> 2282.9265 | U31: =+T31 -> 2282.9265 | V31: =+S31*0.01 -> 274.0608 | W31: =+S31*0.083 -> 2274.7046 | X31: =+S31*0.0018 -> 49.330944 | Y31: =0.71*52*P31 -> 5.538 | Z31: =172*12*P31 -> 309.6 | AA31: =+(S31+T31+U31)*0.01 -> 319.71933 | AB31: =SUM(S31:AA31) -> 35204.887 | AC31: =IF(+J31>0,J31,AC30) -> 0.5 | AD31: =+AB31/AC31 -> 70409.773
K32: OTT | L32: Cutting | M32: 0.7 | O32: D00001 | P32: =+M32 -> 0.7 | Q32: =+$I$30*P32 -> 61.488 | S32: =+Q32*40*52 -> 127895.04 | T32: =+S32*0.0833 -> 10653.657 | U32: =+T32 -> 10653.657 | V32: =+S32*0.01 -> 1278.9504 | W32: =+S32*0.083 -> 10615.288 | X32: =+S32*0.0018 -> 230.21107 | Y32: =0.71*52*P32 -> 25.844 | Z32: =172*12*P32 -> 1444.8 | AA32: =+(S32+T32+U32)*0.01 -> 1492.0235 | AB32: =SUM(S32:AA32) -> 164289.47 | AC32: =IF(+J32>0,J32,AC31) -> 0.5 | AD32: =+AB32/AC32 -> 328578.94
A34: OTHER001 | B34: Other | E34: M | F34: C | G34: General Worker | H34: DAMPER | I34: 72.85 | J34: 0.5 | K34: OTT | L34: Brushing | M34: 0.1 | O34: D00002 | P34: =+M34 -> 0.1 | Q34: =+$I$34*P34 -> 7.285 | S34: =+Q34*40*52 -> 15152.8 | T34: =+S34*0.0833 -> 1262.2282 | U34: =+T34 -> 1262.2282 | V34: =+S34*0.01 -> 151.528 | W34: =+S34*0.083 -> 1257.6824 | X34: =+S34*0.0018 -> 27.27504 | Y34: =0.71*52*P34 -> 3.692 | Z34: =172*12*P34 -> 206.4 | AA34: =+(S34+T34+U34)*0.01 -> 176.77256 | AB34: =SUM(S34:AA34) -> 19500.606 | AC34: =IF(+J34>0,J34,AC6) -> 0.5 | AD34: =+AB34/AC34 -> 39001.213
K35: OTT | L35: Notching | M35: 0.1 | O35: D00003 | P35: =+M35 -> 0.1 | Q35: =+$I$34*P35 -> 7.285 | S35: =+Q35*40*52 -> 15152.8 | T35: =+S35*0.0833 -> 1262.2282 | U35: =+T35 -> 1262.2282 | V35: =+S35*0.01 -> 151.528 | W35: =+S35*0.083 -> 1257.6824 | X35: =+S35*0.0018 -> 27.27504 | Y35: =0.71*52*P35 -> 3.692 | Z35: =172*12*P35 -> 206.4 | AA35: =+(S35+T35+U35)*0.01 -> 176.77256 | AB35: =SUM(S35:AA35) -> 19500.606 | AC35: =IF(+J35>0,J35,AC31) -> 0.5 | AD35: =+AB35/AC35 -> 39001.213
K36: OTT | L36: Grille Assembly | M36: 0.4 | O36: D00005 | P36: =+M36 -> 0.4 | Q36: =+$I$34*P36 -> 29.14 | S36: =+Q36*40*52 -> 60611.2 | T36: =+S36*0.0833 -> 5048.913 | U36: =+T36 -> 5048.913 | V36: =+S36*0.01 -> 606.112 | W36: =+S36*0.083 -> 5030.7296 | X36: =+S36*0.0018 -> 109.10016 | Y36: =0.71*52*P36 -> 14.768 | Z36: =172*12*P36 -> 825.6 | AA36: =+(S36+T36+U36)*0.01 -> 707.09026 | AB36: =SUM(S36:AA36) -> 78002.426 | AC36: =IF(+J36>0,J36,AC31) -> 0.5 | AD36: =+AB36/AC36 -> 156004.85
K37: OTT | L37: Damper Assembly | M37: 0.4 | O37: D00006 | P37: =+M37 -> 0.4 | Q37: =+$I$34*P37 -> 29.14 | S37: =+Q37*40*52 -> 60611.2 | T37: =+S37*0.0833 -> 5048.913 | U37: =+T37 -> 5048.913 | V37: =+S37*0.01 -> 606.112 | W37: =+S37*0.083 -> 5030.7296 | X37: =+S37*0.0018 -> 109.10016 | Y37: =0.71*52*P37 -> 14.768 | Z37: =172*12*P37 -> 825.6 | AA37: =+(S37+T37+U37)*0.01 -> 707.09026 | AB37: =SUM(S37:AA37) -> 78002.426 | AC37: =IF(+J37>0,J37,AC32) -> 0.5 | AD37: =+AB37/AC37 -> 156004.85
A39: Despatch
A40: CON049 | B40: Sean | C40: Ontong | E40: M | F40: C | G40: Supervisor | H40: DESPATCH | I40: 111.14 | J40: 0.75 | K40: LANS | L40: Despatch | M40: 1 | O40: F00001 | P40: =+M40 -> 1 | Q40: =+I40*P40 -> 111.14 | S40: =+Q40*40*52 -> 231171.2 | T40: =+S40*0.0833 -> 19256.561 | U40: =+T40 -> 19256.561 | V40: =+S40*0.01 -> 2311.712 | W40: =+S40*0.083 -> 19187.21 | X40: =+S40*0.0018 -> 416.10816 | Y40: =0.71*52*P40 -> 36.92 | Z40: =172*12*P40 -> 2064 | AA40: =+(S40+T40+U40)*0.01 -> 2696.8432 | AB40: =SUM(S40:AA40) -> 296397.11 | AC40: =IF(+J40>0,J40,AC35) -> 0.75 | AD40: =+AB40/AC40 -> 395196.15
A41: SWL004 | B41: Ebriham | C41: Fredericks | E41: M | F41: C | G41: Picker/Packer | H41: DESPATCH | I41: 76.04 | J41: 0.5 | K41: LANS | L41: Despatch | M41: 1 | O41: F00001 | P41: =+M41 -> 1 | Q41: =+I41*P41 -> 76.04 | S41: =+Q41*40*52 -> 158163.2 | T41: =+S41*0.0833 -> 13174.995 | U41: =+T41 -> 13174.995 | V41: =+S41*0.01 -> 1581.632 | W41: =+S41*0.083 -> 13127.546 | X41: =+S41*0.0018 -> 284.69376 | Y41: =0.71*52*P41 -> 36.92 | Z41: =172*12*P41 -> 2064 | AA41: =+(S41+T41+U41)*0.01 -> 1845.1319 | AB41: =SUM(S41:AA41) -> 203453.11 | AC41: =IF(+J41>0,J41,AC39) -> 0.5 | AD41: =+AB41/AC41 -> 406906.22
A42: W0000017 | B42: Brandon | C42: Jaftha | E42: M | F42: C | G42: Leading Hand/De | H42: DESPATCH | I42: 81.61 | J42: 0.5 | K42: LANS | L42: Despatch | M42: 1 | O42: F00001 | P42: =+M42 -> 1 | Q42: =+I42*P42 -> 81.61 | S42: =+Q42*40*52 -> 169748.8 | T42: =+S42*0.0833 -> 14140.075 | U42: =+T42 -> 14140.075 | V42: =+S42*0.01 -> 1697.488 | W42: =+S42*0.083 -> 14089.15 | X42: =+S42*0.0018 -> 305.54784 | Y42: =0.71*52*P42 -> 36.92 | Z42: =172*12*P42 -> 2064 | AA42: =+(S42+T42+U42)*0.01 -> 1980.2895 | AB42: =SUM(S42:AA42) -> 218202.35 | AC42: =IF(+J42>0,J42,AC41) -> 0.5 | AD42: =+AB42/AC42 -> 436404.69
A43: W0000074 | B43: Van Wyk DLM | E43: M | F43: C | H43: DESPATCH | I43: 66.93 | J43: 0.5 | K43: LANS | L43: Despatch | M43: 1 | O43: F00001 | P43: =+M43 -> 1 | Q43: =+I43*P43 -> 66.93 | S43: =+Q43*40*52 -> 139214.4 | T43: =+S43*0.0833 -> 11596.56 | U43: =+T43 -> 11596.56 | V43: =+S43*0.01 -> 1392.144 | W43: =+S43*0.083 -> 11554.795 | X43: =+S43*0.0018 -> 250.58592 | Y43: =0.71*52*P43 -> 36.92 | Z43: =172*12*P43 -> 2064 | AA43: =+(S43+T43+U43)*0.01 -> 1624.0752 | AB43: =SUM(S43:AA43) -> 179330.04 | AC43: =IF(+J43>0,J43,#REF!) -> 0.5 | AD43: =+AB43/AC43 -> 358660.08
A44: W0000044 | B44: Bernard | C44: Manel | E44: M | F44: C | G44: Delivery Driver | H44: DESPATCH | I44: 81.61 | J44: 0.5 | K44: LANS | L44: Despatch | M44: 1 | O44: F00001 | P44: =+M44 -> 1 | Q44: =+I44*P44 -> 81.61 | S44: =+Q44*40*52 -> 169748.8 | T44: =+S44*0.0833 -> 14140.075 | U44: =+T44 -> 14140.075 | V44: =+S44*0.01 -> 1697.488 | W44: =+S44*0.083 -> 14089.15 | X44: =+S44*0.0018 -> 305.54784 | Y44: =0.71*52*P44 -> 36.92 | Z44: =172*12*P44 -> 2064 | AA44: =+(S44+T44+U44)*0.01 -> 1980.2895 | AB44: =SUM(S44:AA44) -> 218202.35 | AC44: =IF(+J44>0,J44,AC43) -> 0.5 | AD44: =+AB44/AC44 -> 436404.69
A45: W0000052 | B45: Phanuel | C45: Tlou | E45: M | F45: A | G45: Delivery Driver | H45: DESPATCH | I45: 81.61 | J45: 0.5 | K45: LANS | L45: Despatch | M45: 1 | O45: F00001 | P45: =+M45 -> 1 | Q45: =+I45*P45 -> 81.61 | S45: =+Q45*40*52 -> 169748.8 | T45: =+S45*0.0833 -> 14140.075 | U45: =+T45 -> 14140.075 | V45: =+S45*0.01 -> 1697.488 | W45: =+S45*0.083 -> 14089.15 | X45: =+S45*0.0018 -> 305.54784 | Y45: =0.71*52*P45 -> 36.92 | Z45: =172*12*P45 -> 2064 | AA45: =+(S45+T45+U45)*0.01 -> 1980.2895 | AB45: =SUM(S45:AA45) -> 218202.35 | AC45: =IF(+J45>0,J45,AC44) -> 0.5 | AD45: =+AB45/AC45 -> 436404.69
A46: W0000064 | B46: Mpendulo | C46: Yekele | E46: M | F46: A | G46: Driver- Code 10 | H46: DESPATCH | I46: 81.61 | J46: 0.5 | K46: LANS | L46: Despatch | M46: 1 | O46: F00001 | P46: =+M46 -> 1 | Q46: =+I46*P46 -> 81.61 | S46: =+Q46*40*52 -> 169748.8 | T46: =+S46*0.0833 -> 14140.075 | U46: =+T46 -> 14140.075 | V46: =+S46*0.01 -> 1697.488 | W46: =+S46*0.083 -> 14089.15 | X46: =+S46*0.0018 -> 305.54784 | Y46: =0.71*52*P46 -> 36.92 | Z46: =172*12*P46 -> 2064 | AA46: =+(S46+T46+U46)*0.01 -> 1980.2895 | AB46: =SUM(S46:AA46) -> 218202.35 | AC46: =IF(+J46>0,J46,AC45) -> 0.5 | AD46: =+AB46/AC46 -> 436404.69
A47: W0000005 | B47: Omar | C47: Karriem | E47: M | F47: A | G47: Driver- Code 10 | H47: DESPATCH | I47: 75.43 | J47: 0.5 | K47: LANS | L47: Despatch | M47: 1 | O47: F00001 | P47: =+M47 -> 1 | Q47: =+I47*P47 -> 75.43 | S47: =+Q47*40*52 -> 156894.4 | T47: =+S47*0.0833 -> 13069.304 | U47: =+T47 -> 13069.304 | V47: =+S47*0.01 -> 1568.944 | W47: =+S47*0.083 -> 13022.235 | X47: =+S47*0.0018 -> 282.40992 | Y47: =0.71*52*P47 -> 36.92 | Z47: =172*12*P47 -> 2064 | AA47: =+(S47+T47+U47)*0.01 -> 1830.3301 | AB47: =SUM(S47:AA47) -> 201837.85 | AC47: =IF(+J47>0,J47,AC46) -> 0.5 | AD47: =+AB47/AC47 -> 403675.69
A50: PREPARATION
A51: CON285 | B51: Nkosiyethu | C51: Skeyi | E51: M | F51: A | G51: Electric Prep Assembler | H51: PREPARATION | I51: 78.33 | J51: 0.75 | K51: LANS | L51: Preparations | M51: 1 | O51: R00001 | P51: =+M51 -> 1 | Q51: =+P51*I51 -> 78.33 | S51: =+Q51*40*52 -> 162926.4 | T51: =+S51*0.0833 -> 13571.769 | U51: =+T51 -> 13571.769 | V51: =+S51*0.01 -> 1629.264 | W51: =+S51*0.083 -> 13522.891 | X51: =+S51*0.0018 -> 293.26752 | Y51: =0.71*52*P51 -> 36.92 | Z51: =172*12*P51 -> 2064 | AA51: =+(S51+T51+U51)*0.01 -> 1900.6994 | AB51: =SUM(S51:AA51) -> 209516.98 | AC51: =IF(+J51>0,J51,AC50) -> 0.75 | AD51: =+AB51/AC51 -> 279355.97
A52: CON377B | B52: Shaheed | C52: Dreyer | E52: M | F52: C | G52: Electrical Prep Assembler | H52: PREPARATION | I52: 78.33 | J52: 0.5 | K52: LANS | L52: Induction Channel Assembly | M52: 1 | O52: A00001 | P52: =+M52 -> 1 | Q52: =+P52*I52 -> 78.33 | S52: =+Q52*40*52 -> 162926.4 | T52: =+S52*0.0833 -> 13571.769 | U52: =+T52 -> 13571.769 | V52: =+S52*0.01 -> 1629.264 | W52: =+S52*0.083 -> 13522.891 | X52: =+S52*0.0018 -> 293.26752 | Y52: =0.71*52*P52 -> 36.92 | Z52: =172*12*P52 -> 2064 | AA52: =+(S52+T52+U52)*0.01 -> 1900.6994 | AB52: =SUM(S52:AA52) -> 209516.98 | AC52: =IF(+J52>0,J52,AC51) -> 0.5 | AD52: =+AB52/AC52 -> 419033.96
A53: W0000075 | B53: Davids Y | E53: M | F53: C | G53: Electrical Prep Assembler | H53: PREPARATION | I53: 72.85 | J53: 0.5 | K53: LANS | L53: Induction Channel Assembly | M53: 1 | O53: A00001 | P53: =+M53 -> 1 | Q53: =+P53*I53 -> 72.85 | S53: =+Q53*40*52 -> 151528 | T53: =+S53*0.0833 -> 12622.282 | U53: =+T53 -> 12622.282 | V53: =+S53*0.01 -> 1515.28 | W53: =+S53*0.083 -> 12576.824 | X53: =+S53*0.0018 -> 272.7504 | Y53: =0.71*52*P53 -> 36.92 | Z53: =172*12*P53 -> 2064 | AA53: =+(S53+T53+U53)*0.01 -> 1767.7256 | AB53: =SUM(S53:AA53) -> 195006.06 | AC53: =IF(+J53>0,J53,AC52) -> 0.5 | AD53: =+AB53/AC53 -> 390012.13
A54: W0000085 | B54: Mlaba S | E54: F | F54: C | G54: Motor Assembler/Prep | H54: PREPARATION | I54: 69.66 | J54: 0.5 | K54: LANS | L54: Preparations | M54: 1 | O54: R00001 | P54: =+M54 -> 1 | Q54: =+P54*I54 -> 69.66 | S54: =+Q54*40*52 -> 144892.8 | T54: =+S54*0.0833 -> 12069.57 | U54: =+T54 -> 12069.57 | V54: =+S54*0.01 -> 1448.928 | W54: =+S54*0.083 -> 12026.102 | X54: =+S54*0.0018 -> 260.80704 | Y54: =0.71*52*P54 -> 36.92 | Z54: =172*12*P54 -> 2064 | AA54: =+(S54+T54+U54)*0.01 -> 1690.3194 | AB54: =SUM(S54:AA54) -> 186559.02 | AC54: =IF(+J54>0,J54,AC52) -> 0.5 | AD54: =+AB54/AC54 -> 373118.03
A55: CON467B | B55: Beulah | C55: Morkel | E55: F | F55: C | G55: Motor Assembler/Prep | H55: PREPARATION | I55: 78.33 | J55: 0.5 | K55: LANS | L55: Preparations | M55: 1 | O55: R00001 | P55: =+M55 -> 1 | Q55: =+P55*I55 -> 78.33 | S55: =+Q55*40*52 -> 162926.4 | T55: =+S55*0.0833 -> 13571.769 | U55: =+T55 -> 13571.769 | V55: =+S55*0.01 -> 1629.264 | W55: =+S55*0.083 -> 13522.891 | X55: =+S55*0.0018 -> 293.26752 | Y55: =0.71*52*P55 -> 36.92 | Z55: =172*12*P55 -> 2064 | AA55: =+(S55+T55+U55)*0.01 -> 1900.6994 | AB55: =SUM(S55:AA55) -> 209516.98 | AC55: =IF(+J55>0,J55,AC53) -> 0.5 | AD55: =+AB55/AC55 -> 419033.96
A56: CON529 | B56: Graham | C56: Bailey | E56: M | F56: C | G56: Electrical Prep Assembler | H56: PREPARATION | I56: 75.43 | J56: 0.5 | K56: LANS | L56: Preparations | M56: 1 | O56: R00001 | P56: =+M56 -> 1 | Q56: =+P56*I56 -> 75.43 | S56: =+Q56*40*52 -> 156894.4 | T56: =+S56*0.0833 -> 13069.304 | U56: =+T56 -> 13069.304 | V56: =+S56*0.01 -> 1568.944 | W56: =+S56*0.083 -> 13022.235 | X56: =+S56*0.0018 -> 282.40992 | Y56: =0.71*52*P56 -> 36.92 | Z56: =172*12*P56 -> 2064 | AA56: =+(S56+T56+U56)*0.01 -> 1830.3301 | AB56: =SUM(S56:AA56) -> 201837.85 | AC56: =IF(+J56>0,J56,AC55) -> 0.5 | AD56: =+AB56/AC56 -> 403675.69
A58: Diffuser Assembly
A60: CON533 | B60: Rashied | C60: Isaacs | E60: M | F60: C | G60: Diffuser CCD Assembler | H60: DIFFUSER | I60: 75.43 | J60: 0.5 | K60: LANS | L60: Constant Volume Diffuser Ass | M60: 1 | O60: A00002 | P60: =+M60 -> 1 | Q60: =+I60*P60 -> 75.43 | S60: =+Q60*40*52 -> 156894.4 | T60: =+S60*0.0833 -> 13069.304 | U60: =+T60 -> 13069.304 | V60: =+S60*0.01 -> 1568.944 | W60: =+S60*0.083 -> 13022.235 | X60: =+S60*0.0018 -> 282.40992 | Y60: =0.71*52*P60 -> 36.92 | Z60: =172*12*P60 -> 2064 | AA60: =+(S60+T60+U60)*0.01 -> 1830.3301 | AB60: =SUM(S60:AA60) -> 201837.85 | AC60: =IF(+J60>0,J60,#REF!) -> 0.5 | AD60: =+AB60/AC60 -> 403675.69
A62: W0000026 | B62: Eugene | C62: Smith | E62: M | F62: C | G62: Diffuser CCD Assembler | H62: DIFFUSER | I62: 75.43 | J62: 0.5 | K62: LANS | L62: Constant Volume Diffuser Ass | M62: 1 | O62: A00002 | P62: =+M62 -> 1 | Q62: =+I62*P62 -> 75.43 | S62: =+Q62*40*52 -> 156894.4 | T62: =+S62*0.0833 -> 13069.304 | U62: =+T62 -> 13069.304 | V62: =+S62*0.01 -> 1568.944 | W62: =+S62*0.083 -> 13022.235 | X62: =+S62*0.0018 -> 282.40992 | Y62: =0.71*52*P62 -> 36.92 | Z62: =172*12*P62 -> 2064 | AA62: =+(S62+T62+U62)*0.01 -> 1830.3301 | AB62: =SUM(S62:AA62) -> 201837.85 | AC62: =IF(+J62>0,J62,AC61) -> 0.5 | AD62: =+AB62/AC62 -> 403675.69
L63: Diffuser Sub-Assembly | M63: 0 | O63: A00003 | P63: =+M63 -> 0 | Q63: =+I62*P63 -> 0 | S63: =+Q63*40*52 -> 0 | T63: =+S63*0.0833 -> 0 | U63: =+T63 -> 0 | V63: =+S63*0.01 -> 0 | W63: =+S63*0.075 -> 0 | X63: =+S63*0.0018 -> 0 | Y63: =0.71*52*P63 -> 0 | Z63: =172*12*P63 -> 0 | AA63: =+(S63+T63+U63)*0.01 -> 0 | AB63: =SUM(S63:AA63) -> 0 | AC63: =IF(+J63>0,J63,AC62) -> 0.5 | AD63: =+AB63/AC63 -> 0
A65: W0000051 | B65: Tshehla S | E65: M | F65: C | G65: Diffuser/Trim/Heater Assemb | H65: DIFFUSER | I65: 72.85 | J65: 0.5 | K65: LANS | L65: Diffuser Sub-Assembly | M65: 1 | O65: A00003 | P65: =+M65 -> 1 | Q65: =+I65*P65 -> 72.85 | S65: =+Q65*40*52 -> 151528 | T65: =+S65*0.0833 -> 12622.282 | U65: =+T65 -> 12622.282 | V65: =+S65*0.01 -> 1515.28 | W65: =+S65*0.083 -> 12576.824 | X65: =+S65*0.0018 -> 272.7504 | Y65: =0.71*52*P65 -> 36.92 | Z65: =172*12*P65 -> 2064 | AA65: =+(S65+T65+U65)*0.01 -> 1767.7256 | AB65: =SUM(S65:AA65) -> 195006.06 | AC65: =IF(+J65>0,J65,AC64) -> 0.5 | AD65: =+AB65/AC65 -> 390012.13
A68: W0000076 | B68: Ravens KC | E68: M | F68: C | G68: Diffuser Trim/Sub Assembler | H68: MANUFACTURING | I68: 72.85 | J68: 0.5 | K68: LANS | L68: Diffuser Sub-Assembly | M68: 1 | O68: A00003 | P68: =+M68 -> 1 | Q68: =+I68*P68 -> 72.85 | S68: =+Q68*40*52 -> 151528 | T68: =+S68*0.0833 -> 12622.282 | U68: =+T68 -> 12622.282 | V68: =+S68*0.01 -> 1515.28 | W68: =+S68*0.083 -> 12576.824 | X68: =+S68*0.0018 -> 272.7504 | Y68: =0.71*52*P68 -> 36.92 | Z68: =172*12*P68 -> 2064 | AA68: =+(S68+T68+U68)*0.01 -> 1767.7256 | AB68: =SUM(S68:AA68) -> 195006.06 | AC68: =IF(+J68>0,J68,AC67) -> 0.5 | AD68: =+AB68/AC68 -> 390012.13
A70: CON466C | B70: Saliem | C70: Davids | E70: M | F70: C | G70: Diffuser Final Assembly | H70: DIFFUSER | I70: 81.61 | J70: 0.5 | K70: LANS | L70: Diffuser Final Assembly | M70: 1 | O70: A00004 | P70: =+M70 -> 1 | Q70: =+I70*P70 -> 81.61 | S70: =+Q70*40*52 -> 169748.8 | T70: =+S70*0.0833 -> 14140.075 | U70: =+T70 -> 14140.075 | V70: =+S70*0.01 -> 1697.488 | W70: =+S70*0.083 -> 14089.15 | X70: =+S70*0.0018 -> 305.54784 | Y70: =0.71*52*P70 -> 36.92 | Z70: =172*12*P70 -> 2064 | AA70: =+(S70+T70+U70)*0.01 -> 1980.2895 | AB70: =SUM(S70:AA70) -> 218202.35 | AC70: =IF(+J70>0,J70,AC69) -> 0.5 | AD70: =+AB70/AC70 -> 436404.69
A72: W0000077 | B72: Manuel MY | E72: M | F72: C | G72: Diffuser Final Assembly | H72: DIFFUSER | I72: 72.85 | J72: 0.5 | K72: LANS | L72: Diffuser Final Assembly | M72: 1 | O72: A00004 | P72: =+M72 -> 1 | Q72: =+I72*P72 -> 72.85 | S72: =+Q72*40*52 -> 151528 | T72: =+S72*0.0833 -> 12622.282 | U72: =+T72 -> 12622.282 | V72: =+S72*0.01 -> 1515.28 | W72: =+S72*0.083 -> 12576.824 | X72: =+S72*0.0018 -> 272.7504 | Y72: =0.71*52*P72 -> 36.92 | Z72: =172*12*P72 -> 2064 | AA72: =+(S72+T72+U72)*0.01 -> 1767.7256 | AB72: =SUM(S72:AA72) -> 195006.06 | AC72: =IF(+J72>0,J72,AC70) -> 0.5 | AD72: =+AB72/AC72 -> 390012.13
A74: CON490B | B74: Ashwin | C74: Geduld | E74: M | F74: C | G74: Heater Neck/Trim/Sub Assemb | H74: DIFFUSER | I74: 78.33 | J74: 0.5 | K74: LANS | L74: Diffuser Sub-Assembly | M74: 0.25 | O74: A00003 | P74: =+M74 -> 0.25 | Q74: =+P74*I74 -> 19.5825 | S74: =+Q74*40*52 -> 40731.6 | T74: =+S74*0.0833 -> 3392.9423 | U74: =+T74 -> 3392.9423 | V74: =+S74*0.01 -> 407.316 | W74: =+S74*0.083 -> 3380.7228 | X74: =+S74*0.0018 -> 73.31688 | Y74: =0.71*52*P74 -> 9.23 | Z74: =172*12*P74 -> 516 | AA74: =+(S74+T74+U74)*0.01 -> 475.17485 | AB74: =SUM(S74:AA74) -> 52379.245 | AC74: =IF(+J74>0,J74,AC73) -> 0.5 | AD74: =+AB74/AC74 -> 104758.49
L75: Diffuser Final Assembly | M75: 0 | O75: A00004 | P75: =+M75 -> 0 | Q75: =+I74*P75 -> 0 | S75: =+Q75*40*52 -> 0 | T75: =+S75*0.0833 -> 0 | U75: =+T75 -> 0 | V75: =+S75*0.01 -> 0 | W75: =+S75*0.083 -> 0 | X75: =+S75*0.0018 -> 0 | Y75: =0.71*52*P75 -> 0 | Z75: =172*12*P75 -> 0 | AA75: =+(S75+T75+U75)*0.01 -> 0 | AB75: =SUM(S75:AA75) -> 0 | AC75: =IF(+J75>0,J75,AC74) -> 0.5 | AD75: =+AB75/AC75 -> 0
L76: Testing | M76: 0.8 | O76: A00005 | P76: =+M76 -> 0.8 | Q76: =+I74*P76 -> 62.664 | S76: =+Q76*40*52 -> 130341.12 | T76: =+S76*0.0833 -> 10857.415 | U76: =+T76 -> 10857.415 | V76: =+S76*0.01 -> 1303.4112 | W76: =+S76*0.083 -> 10818.313 | X76: =+S76*0.0018 -> 234.61402 | Y76: =0.71*52*P76 -> 29.536 | Z76: =172*12*P76 -> 1651.2 | AA76: =+(S76+T76+U76)*0.01 -> 1520.5595 | AB76: =SUM(S76:AA76) -> 167613.58 | AC76: =IF(+J76>0,J76,AC75) -> 0.5 | AD76: =+AB76/AC76 -> 335227.17
A79: W0000007 | B79: Jason | C79: Overmeyer | E79: M | F79: C | G79: Diffuser Trim Assembler | H79: DIFFUSER | I79: 78.33 | J79: 0.5 | K79: LANS | L79: Diffuser Sub-Assembly | M79: 1 | O79: A00003 | P79: =+M79 -> 1 | Q79: =+P79*I79 -> 78.33 | S79: =+Q79*40*52 -> 162926.4 | T79: =+S79*0.0833 -> 13571.769 | U79: =+T79 -> 13571.769 | V79: =+S79*0.01 -> 1629.264 | W79: =+S79*0.083 -> 13522.891 | X79: =+S79*0.0018 -> 293.26752 | Y79: =0.71*52*P79 -> 36.92 | Z79: =172*12*P79 -> 2064 | AA79: =+(S79+T79+U79)*0.01 -> 1900.6994 | AB79: =SUM(S79:AA79) -> 209516.98 | AC79: =IF(+J79>0,J79,AC78) -> 0.5 | AD79: =+AB79/AC79 -> 419033.96
A82: CON459B | B82: Gary | C82: Daniels | E82: M | F82: C | G82: Leading Hand/Final Diffuser | H82: DIFFUSER | I82: 92.77 | J82: 0.75 | K82: LANS | L82: Diffuser Sub-Assembly | M82: 0.35 | O82: A00003 | P82: =+M82 -> 0.35 | Q82: =+P82*I82 -> 32.4695 | S82: =+Q82*40*52 -> 67536.56 | T82: =+S82*0.0833 -> 5625.7954 | U82: =+T82 -> 5625.7954 | V82: =+S82*0.01 -> 675.3656 | W82: =+S82*0.083 -> 5605.5345 | X82: =+S82*0.0018 -> 121.56581 | Y82: =0.71*52*P82 -> 12.922 | Z82: =172*12*P82 -> 722.4 | AA82: =+(S82+T82+U82)*0.01 -> 787.88151 | AB82: =SUM(S82:AA82) -> 86713.82 | AC82: =IF(+J82>0,J82,AC81) -> 0.75 | AD82: =+AB82/AC82 -> 115618.43
L83: Diffuser Final Assembly | M83: 0.3 | O83: R00001 | P83: =+M83 -> 0.3 | Q83: =+I82*P83 -> 27.831 | S83: =+Q83*40*52 -> 57888.48 | T83: =+S83*0.0833 -> 4822.1104 | U83: =+T83 -> 4822.1104 | V83: =+S83*0.01 -> 578.8848 | W83: =+S83*0.083 -> 4804.7438 | X83: =+S83*0.0018 -> 104.19926 | Y83: =0.71*52*P83 -> 11.076 | Z83: =172*12*P83 -> 619.2 | AA83: =+(S83+T83+U83)*0.01 -> 675.32701 | AB83: =SUM(S83:AA83) -> 74326.132 | AC83: =IF(+J83>0,J83,AC82) -> 0.75 | AD83: =+AB83/AC83 -> 99101.509
L84: Diffuser Final Assembly | M84: 0.35 | O84: A00004 | P84: =+M84 -> 0.35 | Q84: =+I82*P84 -> 32.4695 | S84: =+Q84*40*52 -> 67536.56 | T84: =+S84*0.0833 -> 5625.7954 | U84: =+T84 -> 5625.7954 | V84: =+S84*0.01 -> 675.3656 | W84: =+S84*0.083 -> 5605.5345 | X84: =+S84*0.0018 -> 121.56581 | Y84: =0.71*52*P84 -> 12.922 | Z84: =172*12*P84 -> 722.4 | AA84: =+(S84+T84+U84)*0.01 -> 787.88151 | AB84: =SUM(S84:AA84) -> 86713.82 | AC84: =IF(+J84>0,J84,AC83) -> 0.75 | AD84: =+AB84/AC84 -> 115618.43
A86: DIF032 | B86: Rudewaan | C86: Davids | E86: M | F86: C | G86: Supervisor | H86: DIFFUSER | I86: 111.14 | J86: 0.75 | K86: LANS | L86: Diffuser Final Assembly | M86: 0.35 | O86: A00004 | P86: =+M86 -> 0.35 | Q86: =+I86*P86 -> 38.899 | S86: =+Q86*40*52 -> 80909.92 | T86: =+S86*0.0833 -> 6739.7963 | U86: =+T86 -> 6739.7963 | V86: =+S86*0.01 -> 809.0992 | W86: =+S86*0.083 -> 6715.5234 | X86: =+S86*0.0018 -> 145.63786 | Y86: =0.71*52*P86 -> 12.922 | Z86: =172*12*P86 -> 722.4 | AA86: =+(S86+T86+U86)*0.01 -> 943.89513 | AB86: =SUM(S86:AA86) -> 103738.99 | AC86: =IF(+J86>0,J86,AC85) -> 0.75 | AD86: =+AB86/AC86 -> 138318.65
L87: Preparations | M87: 0.3 | O87: R00001 | P87: =+M87 -> 0.3 | Q87: =+I86*P87 -> 33.342 | S87: =+Q87*40*52 -> 69351.36 | T87: =+S87*0.0833 -> 5776.9683 | U87: =+T87 -> 5776.9683 | V87: =+S87*0.01 -> 693.5136 | W87: =+S87*0.083 -> 5756.1629 | X87: =+S87*0.0018 -> 124.83245 | Y87: =0.71*52*P87 -> 11.076 | Z87: =172*12*P87 -> 619.2 | AA87: =+(S87+T87+U87)*0.01 -> 809.05297 | AB87: =SUM(S87:AA87) -> 88919.134 | AC87: =+AC86 -> 0.75 | AD87: =+AB87/AC87 -> 118558.85
L88: Diffuser Sub-Assembly | M88: 0.35 | O88: A00003 | P88: =+M88 -> 0.35 | Q88: =+I86*P88 -> 38.899 | S88: =+Q88*40*52 -> 80909.92 | T88: =+S88*0.0833 -> 6739.7963 | U88: =+T88 -> 6739.7963 | V88: =+S88*0.01 -> 809.0992 | W88: =+S88*0.083 -> 6715.5234 | X88: =+S88*0.0018 -> 145.63786 | Y88: =0.71*52*P88 -> 12.922 | Z88: =172*12*P88 -> 722.4 | AA88: =+(S88+T88+U88)*0.01 -> 943.89513 | AB88: =SUM(S88:AA88) -> 103738.99 | AC88: =IF(+J88>0,J88,AC86) -> 0.75 | AD88: =+AB88/AC88 -> 138318.65
A90: Flex Duct
A91: W0000036 | B91: Lucky | C91: Nombewu | E91: M | F91: C | G91: Flex Duct Operator | H91: FLEX DUCTING DEPARTMENT | I91: 78.33 | J91: 0.75 | K91: LANS | L91: DUCTING | M91: 1 | O91: X00001 | P91: =+M91 -> 1 | Q91: =+P91*I91 -> 78.33 | S91: =+Q91*40*52 -> 162926.4 | T91: =+S91*0.0833 -> 13571.769 | U91: =+T91 -> 13571.769 | V91: =+S91*0.01 -> 1629.264 | W91: =+S91*0.083 -> 13522.891 | X91: =+S91*0.0018 -> 293.26752 | Y91: =0.71*52*P91 -> 36.92 | Z91: =172*12*P91 -> 2064 | AA91: =+(S91+T91+U91)*0.01 -> 1900.6994 | AB91: =SUM(S91:AA91) -> 209516.98 | AC91: =IF(+J91>0,J91,AC90) -> 0.75 | AD91: =+AB91/AC91 -> 279355.97
A92: W0000048 | B92: RustonIsaacs | C92: Flex Duct Opera | G92: Flex Duct Operator | H92: FLEX DUCTING DEPARTMENT | I92: 75.43 | J92: 0.75 | K92: LANS | L92: DUCTING | M92: 1 | O92: X00001 | P92: =+M92 -> 1 | Q92: =+P92*I92 -> 75.43 | S92: =+Q92*40*52 -> 156894.4 | T92: =+S92*0.0833 -> 13069.304 | U92: =+T92 -> 13069.304 | V92: =+S92*0.01 -> 1568.944 | W92: =+S92*0.083 -> 13022.235 | X92: =+S92*0.0018 -> 282.40992 | Y92: =0.71*52*P92 -> 36.92 | Z92: =172*12*P92 -> 2064 | AA92: =+(S92+T92+U92)*0.01 -> 1830.3301 | AB92: =SUM(S92:AA92) -> 201837.85 | AC92: =IF(+J92>0,J92,#REF!) -> 0.75 | AD92: =+AB92/AC92 -> 269117.13
A96: Manufacturing
A98: W0000030 | B98: Leon | C98: Du Preez | E98: M | F98: C | G98: Guilotene Operator | H98: MANUFACTURING | I98: 87.84 | J98: 0.5 | K98: LANS | L98: Guilotene | M98: 0.7 | O98: M00014 | P98: =+M98 -> 0.7 | Q98: =+$I$98*P98 -> 61.488 | S98: =+Q98*40*52 -> 127895.04 | T98: =+S98*0.0833 -> 10653.657 | U98: =+T98 -> 10653.657 | V98: =+S98*0.01 -> 1278.9504 | W98: =+S98*0.083 -> 10615.288 | X98: =+S98*0.0018 -> 230.21107 | Y98: =0.71*52*P98 -> 25.844 | Z98: =172*12*P98 -> 1444.8 | AA98: =+(S98+T98+U98)*0.01 -> 1492.0235 | AB98: =SUM(S98:AA98) -> 164289.47 | AC98: =IF(+J98>0,J98,AC97) -> 0.5 | AD98: =+AB98/AC98 -> 328578.94
K99: LANS | L99: Rolling | M99: 0.1 | O99: M00006 | P99: =+M99 -> 0.1 | Q99: =+$I$98*P99 -> 8.784 | S99: =+Q99*40*52 -> 18270.72 | T99: =+S99*0.0833 -> 1521.951 | U99: =+T99 -> 1521.951 | V99: =+S99*0.01 -> 182.7072 | W99: =+S99*0.083 -> 1516.4698 | X99: =+S99*0.0018 -> 32.887296 | Y99: =0.71*52*P99 -> 3.692 | Z99: =172*12*P99 -> 206.4 | AA99: =+(S99+T99+U99)*0.01 -> 213.14622 | AB99: =SUM(S99:AA99) -> 23469.924 | AC99: =IF(+J99>0,J99,AC98) -> 0.5 | AD99: =+AB99/AC99 -> 46939.849
K100: LANS | L100: Beading | M100: 0.1 | O100: M00007 | P100: =+M100 -> 0.1 | Q100: =+$I$98*P100 -> 8.784 | S100: =+Q100*40*52 -> 18270.72 | T100: =+S100*0.0833 -> 1521.951 | U100: =+T100 -> 1521.951 | V100: =+S100*0.01 -> 182.7072 | W100: =+S100*0.083 -> 1516.4698 | X100: =+S100*0.0018 -> 32.887296 | Y100: =0.71*52*P100 -> 3.692 | Z100: =172*12*P100 -> 206.4 | AA100: =+(S100+T100+U100)*0.01 -> 213.14622 | AB100: =SUM(S100:AA100) -> 23469.924 | AC100: =IF(+J100>0,J100,AC99) -> 0.5 | AD100: =+AB100/AC100 -> 46939.849
K101: LANS | L101: Spot Welding | M101: 0.1 | O101: M00002 | P101: =+M101 -> 0.1 | Q101: =+$I$98*P101 -> 8.784 | S101: =+Q101*40*52 -> 18270.72 | T101: =+S101*0.0833 -> 1521.951 | U101: =+T101 -> 1521.951 | V101: =+S101*0.01 -> 182.7072 | W101: =+S101*0.083 -> 1516.4698 | X101: =+S101*0.0018 -> 32.887296 | Y101: =0.71*52*P101 -> 3.692 | Z101: =172*12*P101 -> 206.4 | AA101: =+(S101+T101+U101)*0.01 -> 213.14622 | AB101: =SUM(S101:AA101) -> 23469.924 | AC101: =IF(+J101>0,J101,AC100) -> 0.5 | AD101: =+AB101/AC101 -> 46939.849
A103: W0000041 | B103: Lyle | C103: Weber | E103: M | F103: C | G103: Bending/Press Brake Setter/ | H103: MANUFACTURING | I103: 92.77 | J103: 0.5 | K103: LANS | L103: Bending Brakes | M103: 1 | O103: M00001 | P103: =+M103 -> 1 | Q103: =+P103*I103 -> 92.77 | S103: =+Q103*40*52 -> 192961.6 | T103: =+S103*0.0833 -> 16073.701 | U103: =+T103 -> 16073.701 | V103: =+S103*0.01 -> 1929.616 | W103: =+S103*0.083 -> 16015.813 | X103: =+S103*0.0018 -> 347.33088 | Y103: =0.71*52*P103 -> 36.92 | Z103: =172*12*P103 -> 2064 | AA103: =+(S103+T103+U103)*0.01 -> 2251.09 | AB103: =SUM(S103:AA103) -> 247753.77 | AC103: =IF(+J103>0,J103,AC102) -> 0.5 | AD103: =+AB103/AC103 -> 495507.54
A107: W0000009 | B107: Chadley | C107: Sasman | E107: M | F107: C | G107: Welder | H107: MANUFACTURING | I107: 87.84 | J107: 0.5 | K107: LANS | L107: Spot Welding | M107: 0.25 | O107: M00002 | P107: =+M107 -> 0.25 | Q107: =+$I$107*P107 -> 21.96 | S107: =+Q107*40*52 -> 45676.8 | T107: =+S107*0.0833 -> 3804.8774 | U107: =+T107 -> 3804.8774 | V107: =+S107*0.01 -> 456.768 | W107: =+S107*0.083 -> 3791.1744 | X107: =+S107*0.0018 -> 82.21824 | Y107: =0.71*52*P107 -> 9.23 | Z107: =172*12*P107 -> 516 | AA107: =+(S107+T107+U107)*0.01 -> 532.86555 | AB107: =SUM(S107:AA107) -> 58674.811 | AC107: =IF(+$J$107>0,$J$107,#REF!) -> 0.5 | AD107: =+AB107/AC107 -> 117349.62
L108: Mig Welding | M108: 0.5 | O108: M00008 | P108: =+M108 -> 0.5 | Q108: =+$I$107*P108 -> 43.92 | S108: =+Q108*40*52 -> 91353.6 | T108: =+S108*0.0833 -> 7609.7549 | U108: =+T108 -> 7609.7549 | V108: =+S108*0.01 -> 913.536 | W108: =+S108*0.083 -> 7582.3488 | X108: =+S108*0.0018 -> 164.43648 | Y108: =0.71*52*P108 -> 18.46 | Z108: =172*12*P108 -> 1032 | AA108: =+(S108+T108+U108)*0.01 -> 1065.7311 | AB108: =SUM(S108:AA108) -> 117349.62 | AC108: =IF(+$J$107>0,$J$107,#REF!) -> 0.5 | AD108: =+AB108/AC108 -> 234699.24
L109: Miscelaneous | M109: 0.25 | O109: M00099 | P109: =+M109 -> 0.25 | Q109: =+$I$107*P109 -> 21.96 | S109: =+Q109*40*52 -> 45676.8 | T109: =+S109*0.0833 -> 3804.8774 | U109: =+T109 -> 3804.8774 | V109: =+S109*0.01 -> 456.768 | W109: =+S109*0.083 -> 3791.1744 | X109: =+S109*0.0018 -> 82.21824 | Y109: =0.71*52*P109 -> 9.23 | Z109: =172*12*P109 -> 516 | AA109: =+(S109+T109+U109)*0.01 -> 532.86555 | AB109: =SUM(S109:AA109) -> 58674.811 | AC109: =IF(+$J$107>0,$J$107,#REF!) -> 0.5 | AD109: =+AB109/AC109 -> 117349.62
A111: W0000080 | B111: Sinton | C111: Isaacs | E111: M | F111: C | G111: General Worker | H111: MANUFACTURING | I111: 72.85 | J111: 0.75 | K111: LANS | L111: Spot Welding | M111: 0.25 | O111: M00002 | P111: =+M111 -> 0.25 | Q111: =+P111*I111 -> 18.2125 | S111: =+Q111*40*52 -> 37882 | T111: =+S111*0.0833 -> 3155.5706 | U111: =+T111 -> 3155.5706 | V111: =+S111*0.01 -> 378.82 | W111: =+S111*0.083 -> 3144.206 | X111: =+S111*0.0018 -> 68.1876 | Y111: =0.71*52*P111 -> 9.23 | Z111: =172*12*P111 -> 516 | AA111: =+(S111+T111+U111)*0.01 -> 441.93141 | AB111: =SUM(S111:AA111) -> 48751.516 | AC111: =IF(+J111>0,J111,AC108) -> 0.75 | AD111: =+AB111/AC111 -> 65002.022
K112: LANS | L112: Miscelaneous | M112: 0.25 | O112: M00099 | P112: =+M112 -> 0.25 | Q112: =+P112*I111 -> 18.2125 | S112: =+Q112*40*52 -> 37882 | T112: =+S112*0.0833 -> 3155.5706 | U112: =+T112 -> 3155.5706 | V112: =+S112*0.01 -> 378.82 | W112: =+S112*0.083 -> 3144.206 | X112: =+S112*0.0018 -> 68.1876 | Y112: =0.71*52*P112 -> 9.23 | Z112: =172*12*P112 -> 516 | AA112: =+(S112+T112+U112)*0.01 -> 441.93141 | AB112: =SUM(S112:AA112) -> 48751.516 | AC112: =IF(+J112>0,J112,AC111) -> 0.75 | AD112: =+AB112/AC112 -> 65002.022
K113: LANS | L113: Rolling | M113: 0.5 | O113: M00006 | P113: =+M113 -> 0.5 | Q113: =+P113*I111 -> 36.425 | S113: =+Q113*40*52 -> 75764 | T113: =+S113*0.0833 -> 6311.1412 | U113: =+T113 -> 6311.1412 | V113: =+S113*0.01 -> 757.64 | W113: =+S113*0.083 -> 6288.412 | X113: =+S113*0.0018 -> 136.3752 | Y113: =0.71*52*P113 -> 18.46 | Z113: =172*12*P113 -> 1032 | AA113: =+(S113+T113+U113)*0.01 -> 883.86282 | AB113: =SUM(S113:AA113) -> 97503.032 | AC113: =IF(+J113>0,J113,AC112) -> 0.75 | AD113: =+AB113/AC113 -> 130004.04
A115: W0000081 | B115: Africa CG | E115: M | F115: C | G115: General Worker | H115: MANUFACTURING | I115: 72.85 | J115: 0.75 | K115: LANS | L115: Spot Welding | M115: 0.25 | O115: M00002 | P115: =+M115 -> 0.25 | Q115: =+P115*I115 -> 18.2125 | S115: =+Q115*40*52 -> 37882 | T115: =+S115*0.0833 -> 3155.5706 | U115: =+T115 -> 3155.5706 | V115: =+S115*0.01 -> 378.82 | W115: =+S115*0.083 -> 3144.206 | X115: =+S115*0.0018 -> 68.1876 | Y115: =0.71*52*P115 -> 9.23 | Z115: =172*12*P115 -> 516 | AA115: =+(S115+T115+U115)*0.01 -> 441.93141 | AB115: =SUM(S115:AA115) -> 48751.516 | AC115: =IF(+J115>0,J115,AC112) -> 0.75 | AD115: =+AB115/AC115 -> 65002.022
K116: LANS | L116: Miscelaneous | M116: 0.25 | O116: M00099 | P116: =+M116 -> 0.25 | Q116: =+P116*I115 -> 18.2125 | S116: =+Q116*40*52 -> 37882 | T116: =+S116*0.0833 -> 3155.5706 | U116: =+T116 -> 3155.5706 | V116: =+S116*0.01 -> 378.82 | W116: =+S116*0.083 -> 3144.206 | X116: =+S116*0.0018 -> 68.1876 | Y116: =0.71*52*P116 -> 9.23 | Z116: =172*12*P116 -> 516 | AA116: =+(S116+T116+U116)*0.01 -> 441.93141 | AB116: =SUM(S116:AA116) -> 48751.516 | AC116: =IF(+J116>0,J116,AC115) -> 0.75 | AD116: =+AB116/AC116 -> 65002.022
K117: LANS | L117: Rolling | M117: 0.5 | O117: M00006 | P117: =+M117 -> 0.5 | Q117: =+P117*I115 -> 36.425 | S117: =+Q117*40*52 -> 75764 | T117: =+S117*0.0833 -> 6311.1412 | U117: =+T117 -> 6311.1412 | V117: =+S117*0.01 -> 757.64 | W117: =+S117*0.083 -> 6288.412 | X117: =+S117*0.0018 -> 136.3752 | Y117: =0.71*52*P117 -> 18.46 | Z117: =172*12*P117 -> 1032 | AA117: =+(S117+T117+U117)*0.01 -> 883.86282 | AB117: =SUM(S117:AA117) -> 97503.032 | AC117: =IF(+J117>0,J117,AC116) -> 0.75 | AD117: =+AB117/AC117 -> 130004.04
A119: W0000024 | B119: Damian | C119: Ferguson | E119: M | F119: C | G119: Press Brake Operator | H119: MANUFACTURING | I119: 89.52 | J119: 0.5 | K119: LANS | L119: Bending Brakes | M119: 0.8 | O119: M00001 | P119: =+M119 -> 0.8 | Q119: =+P119*$I$119 -> 71.616 | S119: =+Q119*40*52 -> 148961.28 | T119: =+S119*0.0833 -> 12408.475 | U119: =+T119 -> 12408.475 | V119: =+S119*0.01 -> 1489.6128 | W119: =+S119*0.083 -> 12363.786 | X119: =+S119*0.0018 -> 268.1303 | Y119: =0.71*52*P119 -> 29.536 | Z119: =172*12*P119 -> 1651.2 | AA119: =+(S119+T119+U119)*0.01 -> 1737.7823 | AB119: =SUM(S119:AA119) -> 191318.28 | AC119: =IF(+J119>0,J119,AC118) -> 0.5 | AD119: =+AB119/AC119 -> 382636.55
L120: Spot Welding | M120: 0.2 | O120: M00002 | P120: =+M120 -> 0.2 | Q120: =+P120*$I$119 -> 17.904 | S120: =+Q120*40*52 -> 37240.32 | T120: =+S120*0.0833 -> 3102.1187 | U120: =+T120 -> 3102.1187 | V120: =+S120*0.01 -> 372.4032 | W120: =+S120*0.083 -> 3090.9466 | X120: =+S120*0.0018 -> 67.032576 | Y120: =0.71*52*P120 -> 7.384 | Z120: =172*12*P120 -> 412.8 | AA120: =+(S120+T120+U120)*0.01 -> 434.44557 | AB120: =SUM(S120:AA120) -> 47829.569 | AC120: =IF(+J120>0,J120,AC119) -> 0.5 | AD120: =+AB120/AC120 -> 95659.138
A123: MAN014 | B123: Bevan | C123: Bailey | E123: M | F123: C | G123: Supervisor | H123: MANUFACTURING | I123: 121.73 | J123: 0.75 | K123: OTT | L123: Miscelaneous | M123: 0.3 | O123: M00099 | P123: =+M123 -> 0.3 | Q123: =+I123*P123 -> 36.519 | S123: =+Q123*40*52 -> 75959.52 | T123: =+S123*0.0833 -> 6327.428 | U123: =+T123 -> 6327.428 | V123: =+S123*0.01 -> 759.5952 | W123: =+S123*0.083 -> 6304.6402 | X123: =+S123*0.0018 -> 136.72714 | Y123: =0.71*52*P123 -> 11.076 | Z123: =172*12*P123 -> 619.2 | AA123: =+(S123+T123+U123)*0.01 -> 886.14376 | AB123: =SUM(S123:AA123) -> 97331.758 | AC123: =IF(+J123>0,J123,AC122) -> 0.75 | AD123: =+AB123/AC123 -> 129775.68
L124: Guilotene | M124: 0.3 | O124: M00014 | P124: =+M124 -> 0.3 | Q124: =+P124*I123 -> 36.519 | S124: =+Q124*40*52 -> 75959.52 | T124: =+S124*0.0833 -> 6327.428 | U124: =+T124 -> 6327.428 | V124: =+S124*0.01 -> 759.5952 | W124: =+S124*0.083 -> 6304.6402 | X124: =+S124*0.0018 -> 136.72714 | Y124: =0.71*52*P124 -> 11.076 | Z124: =172*12*P124 -> 619.2 | AA124: =+(S124+T124+U124)*0.01 -> 886.14376 | AB124: =SUM(S124:AA124) -> 97331.758 | AC124: =+AC123 -> 0.75 | AD124: =+AB124/AC124 -> 129775.68
L125: Trumpf | M125: 0.4 | O125: 05 | P125: =+M125 -> 0.4 | Q125: =+P125*I123 -> 48.692 | S125: =+Q125*40*52 -> 101279.36 | T125: =+S125*0.0833 -> 8436.5707 | U125: =+T125 -> 8436.5707 | V125: =+S125*0.01 -> 1012.7936 | W125: =+S125*0.083 -> 8406.1869 | X125: =+S125*0.0018 -> 182.30285 | Y125: =0.71*52*P125 -> 14.768 | Z125: =172*12*P125 -> 825.6 | AA125: =+(S125+T125+U125)*0.01 -> 1181.525 | AB125: =SUM(S125:AA125) -> 129775.68 | AC125: =IF(+J125>0,J125,AC124) -> 0.75 | AD125: =+AB125/AC125 -> 173034.24
A128: Press Shop
A129: W0000027 | B129: BrendonAbrahams | C129: All Rounder - M | E129: M | F129: A | G129: Welder/Assembler | H129: Press Shop | I129: 81.61 | J129: 0.5 | L129: Mig Welding | M129: 0.6 | O129: M00008 | P129: =+M129 -> 0.6 | Q129: =+$I$129*P129 -> 48.966 | S129: =+Q129*40*52 -> 101849.28 | T129: =+S129*0.0833 -> 8484.045 | U129: =+T129 -> 8484.045 | V129: =+S129*0.01 -> 1018.4928 | W129: =+S129*0.083 -> 8453.4902 | X129: =+S129*0.0018 -> 183.3287 | Y129: =0.71*52*P129 -> 22.152 | Z129: =172*12*P129 -> 1238.4 | AA129: =+(S129+T129+U129)*0.01 -> 1188.1737 | AB129: =SUM(S129:AA129) -> 130921.41 | AC129: =IF(+J129>0,J129,AC128) -> 0.5 | AD129: =+AB129/AC129 -> 261842.81
L130: Welding | M130: 0.2 | O130: PS00006 | P130: =+M130 -> 0.2 | Q130: =+$I$129*P130 -> 16.322 | S130: =+Q130*40*52 -> 33949.76 | T130: =+S130*0.0833 -> 2828.015 | U130: =+T130 -> 2828.015 | V130: =+S130*0.01 -> 339.4976 | W130: =+S130*0.083 -> 2817.8301 | X130: =+S130*0.0018 -> 61.109568 | Y130: =0.71*52*P130 -> 7.384 | Z130: =172*12*P130 -> 412.8 | AA130: =+(S130+T130+U130)*0.01 -> 396.0579 | AB130: =SUM(S130:AA130) -> 43640.469 | AC130: =IF(+J130>0,J130,AC129) -> 0.5 | AD130: =+AB130/AC130 -> 87280.938
L131: Rolling | M131: 0.2 | O131: PS00009 | P131: =+M131 -> 0.2 | Q131: =+$I$129*P131 -> 16.322 | S131: =+Q131*40*52 -> 33949.76 | T131: =+S131*0.0833 -> 2828.015 | U131: =+T131 -> 2828.015 | V131: =+S131*0.01 -> 339.4976 | W131: =+S131*0.083 -> 2817.8301 | X131: =+S131*0.0018 -> 61.109568 | Y131: =0.71*52*P131 -> 7.384 | Z131: =172*12*P131 -> 412.8 | AA131: =+(S131+T131+U131)*0.01 -> 396.0579 | AB131: =SUM(S131:AA131) -> 43640.469 | AC131: =IF(+J131>0,J131,AC130) -> 0.5 | AD131: =+AB131/AC131 -> 87280.938
A133: W0000016 | B133: Dino | C133: Ray | E133: M | F133: C | G133: Supervisor | H133: Press Shop | I133: 109.2 | J133: 1 | K133: LANS | L133: HME | M133: 0.25 | O133: PS00002 | P133: =+M133 -> 0.25 | Q133: =+P133*$I$133 -> 27.3 | S133: =+Q133*40*52 -> 56784 | T133: =+S133*0.0833 -> 4730.1072 | U133: =+T133 -> 4730.1072 | V133: =+S133*0.01 -> 567.84 | W133: =+S133*0.083 -> 4713.072 | X133: =+S133*0.0018 -> 102.2112 | Y133: =0.71*52*P133 -> 9.23 | Z133: =172*12*P133 -> 516 | AA133: =+(S133+T133+U133)*0.01 -> 662.44214 | AB133: =SUM(S133:AA133) -> 72815.01 | AC133: =IF(+J133>0,J133,AC132) -> 1 | AD133: =+AB133/AC133 -> 72815.01
L134: Erfurt | M134: 0.25 | O134: PS00004 | P134: =+M134 -> 0.25 | Q134: =+P134*$I$133 -> 27.3 | S134: =+Q134*40*52 -> 56784 | T134: =+S134*0.0833 -> 4730.1072 | U134: =+T134 -> 4730.1072 | V134: =+S134*0.01 -> 567.84 | W134: =+S134*0.083 -> 4713.072 | X134: =+S134*0.0018 -> 102.2112 | Y134: =0.71*52*P134 -> 9.23 | Z134: =172*12*P134 -> 516 | AA134: =+(S134+T134+U134)*0.01 -> 662.44214 | AB134: =SUM(S134:AA134) -> 72815.01 | AC134: =IF(+J134>0,J134,AC133) -> 1 | AD134: =+AB134/AC134 -> 72815.01
L135: Tos | M135: 0.25 | O135: PS00003 | P135: =+M135 -> 0.25 | Q135: =+P135*$I$133 -> 27.3 | S135: =+Q135*40*52 -> 56784 | T135: =+S135*0.0833 -> 4730.1072 | U135: =+T135 -> 4730.1072 | V135: =+S135*0.01 -> 567.84 | W135: =+S135*0.083 -> 4713.072 | X135: =+S135*0.0018 -> 102.2112 | Y135: =0.71*52*P135 -> 9.23 | Z135: =172*12*P135 -> 516 | AA135: =+(S135+T135+U135)*0.01 -> 662.44214 | AB135: =SUM(S135:AA135) -> 72815.01 | AC135: =IF(+J135>0,J135,AC134) -> 1 | AD135: =+AB135/AC135 -> 72815.01
L136: Hydraulic | M136: 0.25 | O136: PS00001 | P136: =+M136 -> 0.25 | Q136: =+P136*$I$133 -> 27.3 | S136: =+Q136*40*52 -> 56784 | T136: =+S136*0.0833 -> 4730.1072 | U136: =+T136 -> 4730.1072 | V136: =+S136*0.01 -> 567.84 | W136: =+S136*0.083 -> 4713.072 | X136: =+S136*0.0018 -> 102.2112 | Y136: =0.71*52*P136 -> 9.23 | Z136: =172*12*P136 -> 516 | AA136: =+(S136+T136+U136)*0.01 -> 662.44214 | AB136: =SUM(S136:AA136) -> 72815.01 | AC136: =IF(+J136>0,J136,AC135) -> 1 | AD136: =+AB136/AC136 -> 72815.01
A139: W0000049 | B139: IgylleJacobs | C139: All Rounder - M | E139: M | F139: C | G139: All Rounder - Manufacturing | H139: Press Shop | I139: 72.85 | J139: 1 | K139: LANS | L139: HME | M139: 0.25 | O139: PS00002 | P139: =+M139 -> 0.25 | Q139: =+P139*$I$139 -> 18.2125 | S139: =+Q139*40*52 -> 37882 | T139: =+S139*0.0833 -> 3155.5706 | U139: =+T139 -> 3155.5706 | V139: =+S139*0.01 -> 378.82 | W139: =+S139*0.083 -> 3144.206 | X139: =+S139*0.0018 -> 68.1876 | Y139: =0.71*52*P139 -> 9.23 | Z139: =172*12*P139 -> 516 | AA139: =+(S139+T139+U139)*0.01 -> 441.93141 | AB139: =SUM(S139:AA139) -> 48751.516 | AC139: =IF(+J139>0,J139,AC138) -> 1 | AD139: =+AB139/AC139 -> 48751.516
L140: Rolling | M140: 0.25 | O140: M00006 | P140: =+M140 -> 0.25 | Q140: =+P140*$I$139 -> 18.2125 | S140: =+Q140*40*52 -> 37882 | T140: =+S140*0.0833 -> 3155.5706 | U140: =+T140 -> 3155.5706 | V140: =+S140*0.01 -> 378.82 | W140: =+S140*0.083 -> 3144.206 | X140: =+S140*0.0018 -> 68.1876 | Y140: =0.71*52*P140 -> 9.23 | Z140: =172*12*P140 -> 516 | AA140: =+(S140+T140+U140)*0.01 -> 441.93141 | AB140: =SUM(S140:AA140) -> 48751.516 | AC140: =IF(+J140>0,J140,AC139) -> 1 | AD140: =+AB140/AC140 -> 48751.516
L141: Tos | M141: 0.25 | O141: PS00003 | P141: =+M141 -> 0.25 | Q141: =+P141*$I$139 -> 18.2125 | S141: =+Q141*40*52 -> 37882 | T141: =+S141*0.0833 -> 3155.5706 | U141: =+T141 -> 3155.5706 | V141: =+S141*0.01 -> 378.82 | W141: =+S141*0.083 -> 3144.206 | X141: =+S141*0.0018 -> 68.1876 | Y141: =0.71*52*P141 -> 9.23 | Z141: =172*12*P141 -> 516 | AA141: =+(S141+T141+U141)*0.01 -> 441.93141 | AB141: =SUM(S141:AA141) -> 48751.516 | AC141: =IF(+J141>0,J141,AC140) -> 1 | AD141: =+AB141/AC141 -> 48751.516
L142: Miscellaneous | M142: 0.2 | O142: M00099 | P142: =+M142 -> 0.2 | Q142: =+P142*$I$139 -> 14.57 | S142: =+Q142*40*52 -> 30305.6 | T142: =+S142*0.0833 -> 2524.4565 | U142: =+T142 -> 2524.4565 | V142: =+S142*0.01 -> 303.056 | W142: =+S142*0.083 -> 2515.3648 | X142: =+S142*0.0018 -> 54.55008 | Y142: =0.71*52*P142 -> 7.384 | Z142: =172*12*P142 -> 412.8 | AA142: =+(S142+T142+U142)*0.01 -> 353.54513 | AB142: =SUM(S142:AA142) -> 39001.213 | AC142: =IF(+J142>0,J142,AC141) -> 1 | AD142: =+AB142/AC142 -> 39001.213
A145: MAN120 | B145: Marlon | C145: Parenzee | E145: M | F145: C | G145: Senior Manf. All Rounder | H145: Press Shop | I145: 89.89 | J145: 0.75 | K145: LANS | L145: Bending Brakes | M145: 0.25 | O145: M00001 | P145: =+M145 -> 0.25 | Q145: =+P145*$I$145 -> 22.4725 | S145: =+Q145*40*52 -> 46742.8 | T145: =+S145*0.0833 -> 3893.6752 | U145: =+T145 -> 3893.6752 | V145: =+S145*0.01 -> 467.428 | W145: =+S145*0.083 -> 3879.6524 | X145: =+S145*0.0018 -> 84.13704 | Y145: =0.71*52*M145 -> 9.23 | Z145: =172*12*M145 -> 516 | AA145: =+(S145+T145+U145)*0.01 -> 545.3015 | AB145: =SUM(S145:AA145) -> 60031.899 | AC145: =+$J$145 -> 0.75 | AD145: =+AB145/AC145 -> 80042.533
L146: Welding | M146: 0.25 | O146: M00002 | P146: =+M146 -> 0.25 | Q146: =+P146*$I$145 -> 22.4725 | S146: =+Q146*40*52 -> 46742.8 | T146: =+S146*0.0833 -> 3893.6752 | U146: =+T146 -> 3893.6752 | V146: =+S146*0.01 -> 467.428 | W146: =+S146*0.083 -> 3879.6524 | X146: =+S146*0.0018 -> 84.13704 | Y146: =0.71*52*M146 -> 9.23 | Z146: =172*12*M146 -> 516 | AA146: =+(S146+T146+U146)*0.01 -> 545.3015 | AB146: =SUM(S146:AA146) -> 60031.899 | AC146: =+$J$145 -> 0.75 | AD146: =+AB146/AC146 -> 80042.533
L147: Notching | M147: 0.25 | O147: M00004 | P147: =+M147 -> 0.25 | Q147: =+P147*$I$145 -> 22.4725 | S147: =+Q147*40*52 -> 46742.8 | T147: =+S147*0.0833 -> 3893.6752 | U147: =+T147 -> 3893.6752 | V147: =+S147*0.01 -> 467.428 | W147: =+S147*0.083 -> 3879.6524 | X147: =+S147*0.0018 -> 84.13704 | Y147: =0.71*52*M147 -> 9.23 | Z147: =172*12*M147 -> 516 | AA147: =+(S147+T147+U147)*0.01 -> 545.3015 | AB147: =SUM(S147:AA147) -> 60031.899 | AC147: =+$J$145 -> 0.75 | AD147: =+AB147/AC147 -> 80042.533
...

Sheet Overhead
A1: ***If adding in Rows change row number in Calc Sheet | E1: Manufacturing | F1: Laser | G1: Trumpf | H1: Assembly | I1: AssemblyPTA | J1: Dampers | K1: Powder | L1: Press | M1: Despatch | N1: Flex | O1: Injection | P1: Prep | Q1: Stores | R1: Total
E2: Lansdowne | F2: Lansdowne | G2: Lansdowne | H2: Lansdowne | I2: PTA | J2: Ottery | K2: Lansdowne | L2: Lansdowne | M2: Lansdowne | N2: Lansdowne | O2: Moulding | P2: Lansdowne | R2: Lansdown | S2: PTA | T2: Total
B4: SQM | E4: 315 | F4: 60 | G4: 113 | H4: 576 | I4: 75 | J4: 523 | K4: 379 | L4: 200 | M4: 221 | N4: 131 | O4: 100 | P4: 123 | Q4: 659 | R4: =+E4+G4+H4+J4+K4+L4+M4+N4+P4+Q4+F4+O4 -> 3400 | S4: 75 | T4: =+S4+R4 -> 3475
B5: Staff | E5: =VLOOKUP(E1,Calc!$B$5:$F$104,5,FALSE) -> 9.15 | F5: =VLOOKUP(F1,Calc!$B$5:$F$104,5,FALSE) -> 1 | G5: =VLOOKUP(G1,Calc!$B$5:$F$104,5,FALSE) -> 1 | H5: =VLOOKUP(H1,Calc!$B$5:$F$104,5,FALSE) -> 12.45 | I5: =VLOOKUP(I1,Calc!$B$5:$F$104,5,FALSE) -> 2 | J5: =VLOOKUP(J1,Calc!$B$5:$F$104,5,FALSE) -> 10 | K5: =VLOOKUP(K1,Calc!$B$5:$F$104,5,FALSE) -> 11 | L5: =VLOOKUP(L1,Calc!$B$5:$F$104,5,FALSE) -> 4 | ... P5: =VLOOKUP(P1,Calc!$B$5:$F$104,5,FALSE) -> 4.6 | Q5: 10 | R5: =+E5+G5+H5+J5+K5+L5+M5+N5+P5+Q5 -> 72.2 | T5: =SUM(E5:Q5) -> 79.2
B6: Asset Value | E6: =VLOOKUP(E1,'Asset Allocation'!$C$1:$I$3022,7,FALSE) -> 3127047.6 | F6: =+'Asset Allocation'!I336 -> 1289500 | G6: =VLOOKUP(G1,'Asset Allocation'!$C$1:$I$3022,7,FALSE) -> 4317281 | H6: =VLOOKUP(H1,'Asset Allocation'!$C$1:$I$3022,7,FALSE) -> 231919.38 | I6: 0 | J6: =VLOOKUP(J1,'Asset Allocation'!$C$1:$I$3022,7,FALSE) -> 654673.44 | K6: =VLOOKUP(K1,'Asset Allocation'!$C$1:$I$3022,7,FALSE) -> 2421547.3 | L6: =VLOOKUP(L1,'Asset Allocation'!$C$1:$I$3022,7,FALSE) -> 3864278.7 | M6: =VLOOKUP(M1,'Asset Allocation'!$C$1:$I$3022,7,FALSE) -> 951672.94 | N6: =VLOOKUP(N1,'Asset Allocation'!$C$1:$I$3022,7,FALSE) -> 351270.5 | O6: =VLOOKUP(O1,'Asset Allocation'!$C$1:$I$3022,7,FALSE) -> 1239213 | P6: =VLOOKUP(P1,'Asset Allocation'!$C$1:$I$3022,7,FALSE) -> 1148788.3 | Q6: =VLOOKUP(Q1,'Asset Allocation'!$C$1:$I$3022,7,FALSE) -> 906583.42 | R6: =+E6+G6+H6+J6+K6+L6+M6+N6+P6+Q6+O6+F6 -> 20503776 | T6: =SUM(E6:Q6) -> 20503776
A7: 2 Accounts
B8: Water % | E8: 0.02 | F8: 0.01 | G8: 0.05 | H8: 0.02 | I8: 0.5 | J8: 0.04 | K8: 0.68 | L8: 0.02 | M8: 0.02 | N8: 0.04 | O8: 0.08 | P8: 0.02 | Q8: 0 | R8: =+E8+G8+H8+J8+K8+L8+M8+N8+P8+Q8+O8+F8 -> 1 | S8: =+I8 -> 0.5
B9: Electricity% | E9: 0.1 | F9: 0.06 | G9: 0.1 | H9: 0.03 | I9: 0.5 | J9: 0.08 | K9: 0.2 | L9: 0.15 | M9: 0.03 | N9: 0.05 | O9: 0.1 | P9: 0.05 | Q9: 0.05 | R9: =+E9+G9+H9+J9+K9+L9+M9+N9+P9+Q9+O9+F9 -> 1 | S9: =+I9 -> 0.5
A10: 1 Account
B11: R&M % | C11: Fixed | E11: 0.14 | F11: 0.03 | G11: 0.29 | H11: 0.01 | I11: 0.005 | J11: 0.02 | K11: 0.11 | L11: 0.2 | M11: 0.12 | N11: 0.01 | O11: 0.03 | P11: 0.02 | Q11: =+'Asset Allocation'!S267 -> 0.022072361 | R11: =+E11+G11+H11+J11+K11+L11+M11+N11+P11+Q11+O11+F11 -> 1.0020724
B12: Gas | E12: 0.15 | K12: 0.6 | M12: 0.1 | Q12: 0.15 | R12: =SUM(E12:Q12) -> 1
B13: Consumerables | E13: 0.12 | F13: 0.1 | G13: 0.1 | H13: 0.02 | I13: 0.02 | J13: 0.05 | K13: 0.08 | L13: 0.15 | M13: 0.05 | N13: 0.08 | O13: 0.05 | P13: 0.08 | Q13: 0.1 | R13: =SUM(E13:Q13) -> 1
B14: Tooling | E14: 0.1 | F14: 0 | G14: 0.2 | H14: 0.05 | I14: 0.05 | J14: 0.1 | K14: 0.06 | L14: 0.21 | M14: 0.02 | N14: 0 | O14: 0.15 | P14: 0.05 | Q14: 0.01 | R14: =SUM(E14:Q14) -> 1
B15: Stores | E15: 0.1 | F15: 0.05 | G15: 0.1 | H15: 0.15 | I15: 0.05 | J15: 0.1 | K15: 0.05 | L15: 0.15 | M15: 0.1 | N15: 0.05 | O15: 0.05 | P15: 0.05 | R15: =SUM(E15:Q15) -> 1
B16: Management | E16: 0.15 | F16: 0.03 | G16: 0.07 | H16: 0.15 | I16: 0.05 | J16: 0.1 | K16: 0.1 | L16: 0.1 | M16: 0.05 | N16: 0.05 | O16: 0.05 | P16: 0.1 | R16: =SUM(E16:Q16) -> 1
B17: Maintenace | E17: 0.15 | F17: 0.05 | G17: 0.05 | H17: 0.05 | J17: 0.05 | K17: 0.2 | L17: 0.2 | M17: 0.05 | N17: 0.05 | O17: 0.1 | P17: 0.05 | R17: =SUM(E17:Q17) -> 1
A18: Rates Based SQM
A20: FIXED INDIRECT PRODUCTION COSTS
A22: Rates Based on SQM
A23: Code | C23: 11
A24: Total | C24: YTD | D24: Annualised
A25: 0500/500 | B25: Rates - Ottery | D25: =+C25/$C$23*12 -> 0 | F25: =ROUND(+F$4/$R$4*$D25,0) -> 0 | G25: =ROUND(+G$4/$R$4*$D25,0) -> 0 | J25: =ROUND(+J$4/$R$4*$D25,0) -> 0 | K25: =ROUND(+K$4/$R$4*$D25,0) -> 0 | M25: =ROUND(+M$4/$R$4*$D25,0) -> 0 | R25: =SUM(E25:Q25) -> 0 | U25: Delete
A26: 0500/505 | B26: Rates - Babaza Park | C26: =VLOOKUP(A26,[1]Data!$R$14:$AG$570,16,FALSE) -> 235467.2 | D26: =+C26/$C$23*12 -> 256873.31 | E26: =ROUND(+E$4/$R$4*$D26,0) -> 23799 | F26: =ROUND(+F$4/$R$4*$D26,0) -> 4533 | G26: =ROUND(+G$4/$R$4*$D26,0) -> 8537 | H26: =ROUND(+H$4/$R$4*$D26,0) -> 43517 | J26: =ROUND(+J$4/$R$4*$D26,0) -> 39513 | K26: =ROUND(+K$4/$R$4*$D26,0) -> 28634 | L26: =ROUND(+L$4/$R$4*$D26,0) -> 15110 | M26: =ROUND(+M$4/$R$4*$D26,0) -> 16697 | N26: =ROUND(+N$4/$R$4*$D26,0) -> 9897 | O26: =ROUND(+O$4/$R$4*$D26,0) -> 7555 | P26: =ROUND(+P$4/$R$4*$D26,0) -> 9293 | Q26: =ROUND(+Q$4/$R$4*$D26,0) -> 49788 | R26: =SUM(E26:Q26) -> 256873
A27: 0500/510 | B27: Rates - Pretoria | C27: =VLOOKUP(A27,[1]Data!$R$14:$AG$570,16,FALSE) -> 35966.52 | D27: =+C27/$C$23*12 -> 39236.204 | I27: =+D27 -> 39236.204 | R27: =SUM(E27:Q27) -> 39236.204
A28: Property Based on SQM
A29: Code
A30: Total
A31: 1550/100 | B31: Rent Premises - Pretoria | C31: =VLOOKUP(A31,[1]Data!$R$14:$AG$570,16,FALSE) -> 829563.78 | D31: =+C31/$C$23*12 -> 904978.67 | I31: =+D31*0.5 -> 452489.33 | Q31: =+D31*0.5 -> 452489.33 | R31: =SUM(E31:Q31) -> 904978.67
A32: 1550/150 | B32: Rent Premises - Ottery | D32: =+C32/$C$23*12 -> 0 | F32: =ROUND(+F$4/$R$4*$D32,0) -> 0 | G32: =ROUND(+G$4/$R$4*$D32,0) -> 0 | J32: =ROUND(+J$4/$R$4*$D32,0) -> 0 | K32: =ROUND(+K$4/$R$4*$D32,0) -> 0 | M32: =ROUND(+M$4/$R$4*$D32,0) -> 0 | R32: =SUM(E32:Q32) -> 0 | U32: Delete
B33: 10 Yr Amort Lansdowne | D33: 2455536 | E33: =ROUND(+E$4/$R$4*$D33,0) -> 227498 | F33: =ROUND(+F$4/$R$4*$D33,0) -> 43333 | G33: =ROUND(+G$4/$R$4*$D33,0) -> 81610 | H33: =ROUND(+H$4/$R$4*$D33,0) -> 415997 | J33: =ROUND(+J$4/$R$4*$D33,0) -> 377719 | K33: =ROUND(+K$4/$R$4*$D33,0) -> 273720 | L33: =ROUND(+L$4/$R$4*$D33,0) -> 144443 | M33: =ROUND(+M$4/$R$4*$D33,0) -> 159610 | N33: =ROUND(+N$4/$R$4*$D33,0) -> 94610 | O33: =ROUND(+O$4/$R$4*$D33,0) -> 72222 | P33: =ROUND(+P$4/$R$4*$D33,0) -> 88833 | Q33: =ROUND(+Q$4/$R$4*$D33,0) -> 475941 | R33: =SUM(E33:Q33) -> 2455536
A34: Repairs & Maintenance - Based on SQM
A35: Code
A36: Total
A37: 0500/300 | B37: R&M Building Ottery | D37: =+C37/$C$23*12 -> 0 | F37: =ROUND(+F$4/$R$4*$D37,0) -> 0 | G37: =ROUND(+G$4/$R$4*$D37,0) -> 0 | J37: =ROUND(+J$4/$R$4*$D37,0) -> 0 | K37: =ROUND(+K$4/$R$4*$D37,0) -> 0 | M37: =ROUND(+M$4/$R$4*$D37,0) -> 0 | R37: =SUM(E37:Q37) -> 0 | U37: Delete
A38: 0500/302 | B38: R&M Building Lansdowne | C38: =VLOOKUP(A38,[1]Data!$R$14:$AG$570,16,FALSE) -> 168487.09 | D38: =+C38/$C$23*12 -> 183804.1 | E38: =ROUND(+E$4/$R$4*$D38,0) -> 17029 | F38: =ROUND(+F$4/$R$4*$D38,0) -> 3244 | G38: =ROUND(+G$4/$R$4*$D38,0) -> 6109 | H38: =ROUND(+H$4/$R$4*$D38,0) -> 31139 | J38: =ROUND(+J$4/$R$4*$D38,0) -> 28273 | K38: =ROUND(+K$4/$R$4*$D38,0) -> 20489 | L38: =ROUND(+L$4/$R$4*$D38,0) -> 10812 | M38: =ROUND(+M$4/$R$4*$D38,0) -> 11947 | N38: =ROUND(+N$4/$R$4*$D38,0) -> 7082 | O38: =ROUND(+O$4/$R$4*$D38,0) -> 5406 | P38: =ROUND(+P$4/$R$4*$D38,0) -> 6649 | Q38: =ROUND(+Q$4/$R$4*$D38,0) -> 35626 | R38: =SUM(E38:Q38) -> 183805
A39: 0500/310 | B39: R&M Building PTA | C39: =VLOOKUP(A39,[1]Data!$R$14:$AG$570,16,FALSE) -> 60307.07 | D39: =+C39/$C$23*12 -> 65789.531 | I39: =+D39*0.5 -> 32894.765 | Q39: =+D39*0.5 -> 32894.765 | R39: =SUM(E39:Q39) -> 65789.531
A40: Security costs - Based on SQM
A41: Code
A42: Total
A43: 0500/600 | B43: Security - Alarm - C.T. | C43: =VLOOKUP(A43,[1]Data!$R$14:$AG$570,16,FALSE) -> 6098.23 | D43: =+C43/$C$23*12 -> 6652.6145 | E43: =+$D43*E$4/$T$4 -> 603.04276 | F43: =+$D43*F$4/$T$4 -> 114.86529 | G43: =+$D43*G$4/$T$4 -> 216.32962 | H43: =+$D43*H$4/$T$4 -> 1102.7068 | I43: =+$D$43*I$4/$T$4 -> 143.58161 | J43: =+$D43*J$4/$T$4 -> 1001.2424 | K43: =+$D43*K$4/$T$4 -> 725.56573 | L43: =+$D43*L$4/$T$4 -> 382.88429 | M43: =+$D43*M$4/$T$4 -> 423.08714 | N43: =+$D43*N$4/$T$4 -> 250.78921 | O43: =+$D43*O$4/$T$4 -> 191.44215 | P43: =+$D43*P$4/$T$4 -> 235.47384 | Q43: =+$D43*Q$4/$T$4 -> 1261.6037 | R43: =SUM(E43:Q43) -> 6652.6145 | T43: =ROUND(+V$4/$R$4*$D43,0) -> 0 | U43: Delete | Y43: =+M43+N43+#REF!+Q43+R43+T43 -> #REF!
A44: 0500/610 | B44: Security - Alarms - Babaza Park | C44: =VLOOKUP(A44,[1]Data!$R$14:$AG$570,16,FALSE) -> 321406.92 | D44: =+C44/$C$23*12 -> 350625.73 | E44: =+$D$44*E4/$R$4 -> 32484.443 | F44: =+$D$44*F4/$R$4 -> 6187.5129 | G44: =+$D$44*G4/$R$4 -> 11653.149 | H44: =+$D$44*H4/$R$4 -> 59400.124 | J44: =+$D$44*J4/$R$4 -> 53934.487 | K44: =+$D$44*K4/$R$4 -> 39084.456 | L44: =+$D$44*L4/$R$4 -> 20625.043 | M44: =+$D$44*M4/$R$4 -> 22790.673 | N44: =+$D$44*N4/$R$4 -> 13509.403 | O44: =+$D$44*O4/$R$4 -> 10312.521 | P44: =+$D$44*P4/$R$4 -> 12684.401 | Q44: =+$D$44*Q4/$R$4 -> 67959.517 | R44: =SUM(E44:Q44) -> 350625.73
A45: 0500/620 | B45: Security - Alarms - PTA | C45: =VLOOKUP(A45,[1]Data!$R$14:$AG$570,16,FALSE) -> 9044.25 | D45: =+C45/$C$23*12 -> 9866.4545 | I45: =+D45*0.5 -> 4933.2273 | Q45: =+D45*0.5 -> 4933.2273 | R45: =SUM(E45:Q45) -> 9866.4545
E46: =SUM(E20:E45) -> 301413.49 | F46: =SUM(F20:F45) -> 57412.378 | G46: =SUM(G20:G45) -> 108125.48 | H46: =SUM(H20:H45) -> 551155.83 | I46: =SUM(I20:I45) -> 529697.11 | J46: =SUM(J20:J45) -> 500440.73 | K46: =SUM(K20:K45) -> 362653.02 | L46: =SUM(L20:L45) -> 191372.93 | ... R46: =SUM(R20:R45) -> 4273363.2
A48: VARIABLE INDIRECT PRODUCTION COSTS
A50: Cleaning - Based on SQM
A51: Code
A52: Total
A53: 0500/100 | B53: Cleaning (Factory) | C53: =VLOOKUP(A53,[1]Data!$R$14:$AG$570,16,FALSE) -> 59693.85 | D53: =+C53/$C$23*12 -> 65120.564 | E53: =+$D53*E$4/$R$4 -> 6033.2287 | F53: =+$D53*F$4/$R$4 -> 1149.1864 | G53: =+$D53*G$4/$R$4 -> 2164.3011 | H53: =+$D53*H$4/$R$4 -> 11032.19 | I53: =+$D$43*I$4/$T$4 -> 143.58161 | J53: =+$D53*J$4/$R$4 -> 10017.075 | K53: =+$D53*K$4/$R$4 -> 7259.0275 | L53: =+$D53*L$4/$R$4 -> 3830.6214 | M53: =+$D53*M$4/$R$4 -> 4232.8366 | N53: =+$D53*N$4/$R$4 -> 2509.057 | O53: =+$D53*O$4/$R$4 -> 1915.3107 | P53: =+$D53*P$4/$R$4 -> 2355.8322 | Q53: =+$D53*Q$4/$R$4 -> 12621.897 | R53: =SUM(E53:Q53) -> 65264.145
A55: Fire Safety - Based on SQM
A56: Code
A57: Total | R57: =SUM(E57:Q57) -> 0
A58: 0500/230 | B58: Fire Safety - PTA | C58: =VLOOKUP(A58,[1]Data!$R$14:$AG$570,16,FALSE) -> 688 | D58: =+C58/$C$23*12 -> 750.54545 | I58: =+D58/2 -> 375.27273 | Q58: =+I58 -> 375.27273 | R58: =SUM(E58:Q58) -> 750.54545
A59: 0500/225 | B59: Fire Safety - lansdowne | C59: 9298.3 | D59: =+C59/$C$23*12 -> 10143.6 | E59: =+$D$59*E4/$R$4 -> 939.77471 | F59: =+$D$59*F4/$R$4 -> 179.00471 | G59: =+$D$59*G4/$R$4 -> 337.12553 | H59: =+$D$59*H4/$R$4 -> 1718.4452 | J59: =+$D$59*J4/$R$4 -> 1560.3244 | K59: =+$D$59*K4/$R$4 -> 1130.7131 | L59: =+$D$59*L4/$R$4 -> 596.68235 | M59: =+$D$59*M4/$R$4 -> 659.334 | N59: =+$D$59*N4/$R$4 -> 390.82694 | O59: =+$D$59*O4/$R$4 -> 298.34118 | P59: =+$D$59*P4/$R$4 -> 366.95965 | Q59: =+$D$59*Q4/$R$4 -> 1966.0684 | R59: =SUM(E59:Q59) -> 10143.6
A61: Refuse Removal - Based on SQM
A62: Code
A63: Total
A64: 0500/550 | B64: Refuse Removal - Ottery | C64: =VLOOKUP(A64,[1]Data!$R$14:$AG$570,16,FALSE) -> 0 | D64: =+C64/$C$23*12 -> 0 | R64: =SUM(E64:Q64) -> 0
A65: 0500/555 | B65: Refuse Removal - Babaza Park | C65: =VLOOKUP(A65,[1]Data!$R$14:$AG$570,16,FALSE) -> 125723.26 | D65: =+C65/$C$23*12 -> 137152.65 | E65: =+$D$65*E4/$R$4 -> 12706.789 | F65: =+$D$65*F4/$R$4 -> 2420.3408 | G65: =+$D$65*G4/$R$4 -> 4558.3086 | H65: =+$D$65*H4/$R$4 -> 23235.272 | J65: =+$D$65*J4/$R$4 -> 21097.304 | K65: =+$D$65*K4/$R$4 -> 15288.486 | L65: =+$D$65*L4/$R$4 -> 8067.8028 | M65: =+$D$65*M4/$R$4 -> 8914.9221 | N65: =+$D$65*N4/$R$4 -> 5284.4108 | O65: =+$D$65*O4/$R$4 -> 4033.9014 | P65: =+$D$65*P4/$R$4 -> 4961.6987 | Q65: =+$D$65*Q4/$R$4 -> 26583.41 | R65: =SUM(E65:Q65) -> 137152.65
A66: 0500/560 | B66: Refuse Removal - Pretoria | C66: =VLOOKUP(A66,[1]Data!$R$14:$AG$570,16,FALSE) -> 0 | D66: =+C66/$C$23*12 -> 0 | R66: =SUM(E66:Q66) -> 0
E67: =SUM(E53:E66) -> 19679.793 | F67: =SUM(F53:F66) -> 3748.532 | G67: =SUM(G53:G66) -> 7059.7352 | H67: =SUM(H53:H66) -> 35985.907 | I67: =SUM(I53:I66) -> 518.85434 | J67: =SUM(J53:J66) -> 32674.704 | K67: =SUM(K53:K66) -> 23678.227 | L67: =SUM(L53:L66) -> 12495.107 | ... R67: =SUM(R53:R66) -> 213310.94
A73: Rates Based on Asset Value
A75: FIXED INDIRECT PRODUCTION COSTS
A76: Repairs & Maintenance - Based onR&M%
A77: Code
A78: Total
A79: 0500/350 | B79: R&M Equipment | C79: =VLOOKUP(A79,[1]Data!$R$14:$AG$570,16,FALSE) -> 994914.7 | D79: =+C79/$C$23*12 -> 1085361.5 | E79: =+$D79*E$11 -> 151950.61 | F79: =+$D79*F$11 -> 32560.845 | G79: =+$D79*G$11 -> 314754.83 | H79: =+$D79*H$11 -> 10853.615 | I79: =+$D79*I$11 -> 5426.8075 | J79: =+$D79*J$11 -> 21707.23 | K79: =+$D79*K$11 -> 119389.76 | L79: =+$D79*L$11 -> 217072.3 | ... Q79: =+$D79*Q$11 -> 23956.49 | R79: =SUM(E79:Q79) -> 1093037.6
E81: =SUM(E79:E80) -> 151950.61 | F81: =SUM(F79:F80) -> 32560.845 | G81: =SUM(G79:G80) -> 314754.83 | H81: =SUM(H79:H80) -> 10853.615 | I81: =SUM(I79:I80) -> 5426.8075 | J81: =SUM(J79:J80) -> 21707.23 | K81: =SUM(K79:K80) -> 119389.76 | L81: =SUM(L79:L80) -> 217072.3 | ... Q81: =SUM(Q79:Q80) -> 23956.49
A82: VARIABLE INDIRECT PRODUCTION COSTS
A84: DEPRECIATION - Based on Asset Value
A86: Depreciation - Designs/ Patents
A87: Code
A88: Total
A89: 3900/100 | B89: Depreciation - Designs | C89: =VLOOKUP(A89,[1]Data!$R$14:$AG$570,16,FALSE) -> 41415.14 | D89: =+C89/$C$23*12 -> 45180.153
A90: 3900/300 | B90: Depreciation - Patents | C90: =VLOOKUP(A90,[1]Data!$R$14:$AG$570,16,FALSE) -> 30176.11 | D90: =+C90/$C$23*12 -> 32919.393
A91: Depreciation - Solar
A92: Code
A94: 0800/200 | B94: Depreciatiion - Tools | C94: =VLOOKUP(A94,[1]Data!$R$14:$AG$570,16,FALSE) -> 232559.4 | D94: =+C94/$C$23*12 -> 253701.16
A95: Depreciation - Tools
A96: Code
A98: 0800/100 | B98: Depreciatiion - Tools | C98: =VLOOKUP(A98,[1]Data!$R$14:$AG$570,16,FALSE) -> 223536.87 | D98: =+C98/$C$23*12 -> 243858.4
A99: Depreciation - Plant
A100: Code
A101: Total
A102: 0800/150 | B102: Depreciation -Plant/Equip. | C102: =VLOOKUP(A102,[1]Data!$R$14:$AG$570,16,FALSE) -> 540784.2 | D102: =+C102/$C$23*12 -> 589946.4
D104: =SUM(D89:D102) -> 1165605.5 | E104: =+$D$104*E6/$T$6 -> 177767.45 | F104: =+$D$104*F6/$T$6 -> 73305.928 | G104: =+$D$104*G6/$T$6 -> 245430.24 | H104: =+$D$104*H6/$T$6 -> 13184.231 | I104: =+$D$104*I6/$T$6 -> 0 | J104: =+$D$104*J6/$T$6 -> 37217.095 | K104: =+$D$104*K6/$T$6 -> 137660.94 | L104: =+$D$104*L6/$T$6 -> 219677.81 | ... Q104: =+$D$104*Q6/$T$6 -> 51537.758 | R104: =SUM(E104:Q104) -> 1165605.5
A109: Rates Based on % and Direct Allocations
A111: Fixed INDIRECT PRODUCTION COSTS
A112: Management | D112: =+'Other Overhead'!AB5 -> 1578442.6 | E112: =+$D112*E$16 -> 236766.39 | F112: =+$D112*F$16 -> 47353.278 | G112: =+$D112*G$16 -> 110490.98 | H112: =+$D112*H$16 -> 236766.39 | I112: =+$D112*I$16 -> 78922.131 | J112: =+$D112*J$16 -> 157844.26 | K112: =+$D112*K$16 -> 157844.26 | L112: =+$D112*L$16 -> 157844.26 | ... P112: =+$D112*P$16 -> 157844.26 | R112: =SUM(E112:Q112) -> 1578442.6
A113: Maintenance | D113: =+'Other Overhead'!AB29 -> 467959.56 | E113: =+$D113*E$17 -> 70193.934 | F113: =+$D113*F$17 -> 23397.978 | G113: =+$D113*G$17 -> 23397.978 | H113: =+$D113*H$17 -> 23397.978 | I113: =+$D113*I$17 -> 0 | J113: =+$D113*J$17 -> 23397.978 | K113: =+$D113*K$17 -> 93591.913 | L113: =+$D113*L$17 -> 93591.913 | ... P113: =+$D113*P$17 -> 23397.978 | R113: =SUM(E113:Q113) -> 467959.56
A114: Stores | D114: =+'Other Overhead'!AB24 -> 3844752.9 | E114: =+$D114*E$15 -> 384475.29 | F114: =+$D114*F$15 -> 192237.65 | G114: =+$D114*G$15 -> 384475.29 | H114: =+$D114*H$15 -> 576712.94 | I114: =+$D114*I$15 -> 192237.65 | J114: =+$D114*J$15 -> 384475.29 | K114: =+$D114*K$15 -> 192237.65 | L114: =+$D114*L$15 -> 576712.94 | ... P114: =+$D114*P$15 -> 192237.65 | R114: =SUM(E114:Q114) -> 3844752.9
E115: =SUM(E112:E114) -> 691435.62 | F115: =SUM(F112:F114) -> 262988.9 | G115: =SUM(G112:G114) -> 518364.25 | H115: =SUM(H112:H114) -> 836877.31 | I115: =SUM(I112:I114) -> 271159.78 | J115: =SUM(J112:J114) -> 565717.53 | K115: =SUM(K112:K114) -> 443673.82 | L115: =SUM(L112:L114) -> 828149.11 | ... P115: =SUM(P112:P114) -> 373479.88
A117: Varianble INDIRECT PRODUCTION COSTS
A119: Consumable materials Based on Consumerable %
A120: Code
A121: Total
A122: 0500/150 | B122: Consumables | C122: =VLOOKUP(A122,[1]Data!$R$14:$AG$570,16,FALSE) -> 396766.31 | D122: =+C122/$C$23*12 -> 432835.97 | E122: =+$D$122*E$13 -> 51940.317 | F122: =+$D$122*F$13 -> 43283.597 | G122: =+$D$122*G$13 -> 43283.597 | H122: =+$D$122*H$13 -> 8656.7195 | I122: =+$D$122*I$13 -> 8656.7195 | J122: =+$D$122*J$13 -> 21641.799 | K122: =+$D$122*K$13 -> 34626.878 | L122: =+$D$122*L$13 -> 64925.396 | ... Q122: =+$D$122*Q$13 -> 43283.597 | R122: =SUM(E122:Q122) -> 432835.97
A123: GAS - Powder Coating - powder Coating Plant
A124: Code
A125: Total
A126: 0500/175 | B126: Gas - Ottery PC | D126: =+C126/$C$23*12 -> 0 | K126: =+D126 -> 0 | U126: Delete
...

Sheet Other Overhead
A2: Other - Production Management | F2: Annual | G2: Bonus | H2: GainShare | I2: UIF | J2: Pension and Risk | K2: Sick Pay Fund | L2: Dispute Levy | M2: ADM and TEC Levy | N2: SDL | O2: Total | P2: Efficiency | Q2: Amnt
A3: S646 | B3: TEC011 | C3: R HOOSEN | D3: 56056 | F3: =+D3*12 -> 672672 | G3: =+D3 -> 56056 | H3: 11000 | I3: =177.01*12 -> 2124.12 | J3: =+F3*(0.08+0.033) -> 76011.936 | K3: =+F3*0.01 -> 6726.72 | L3: 36 | M3: =172*12 -> 2064 | N3: =+F3*0.01 -> 6726.72 | O3: =SUM(F3:N3) -> 833417.5 | AB3: =+O3 -> 833417.5
A4: S0000031 | B4: MAN012 | C4: D Muller | D4: 50000 | F4: =+D4*12 -> 600000 | G4: =+D4 -> 50000 | H4: 11000 | I4: =177.01*12 -> 2124.12 | J4: =+F4*(0.08+0.033) -> 67800 | K4: =+F4*0.01 -> 6000 | L4: 37 | M4: =172*12 -> 2064 | N4: =+F4*0.01 -> 6000 | O4: =SUM(F4:N4) -> 745025.12 | AB4: =+O4 -> 745025.12
AB5: =SUM(AB3:AB4) -> 1578442.6
A6: Stores | Q6: Annual | R6: Bonus | S6: GainShare | T6: UIF | U6: Pension | V6: Sick Pay Fund | W6: Dispute Levy | X6: ADM and TEC Levy | Y6: SDL | Z6: Total | AA6: Efficiency | AB6: Amnt
A7: Stores Salary Staff - CTN
B8: ADM023 | C8: E Lewis | D8: 29593 | F8: =+D8*12 -> 355116 | G8: =+D8 -> 29593 | H8: 11000 | I8: =177.01*12 -> 2124.12 | J8: =+F8*(0.08+0.033) -> 40128.108 | K8: =+F8*0.01 -> 3551.16 | L8: 36 | M8: =172*12 -> 2064 | N8: =+F8*0.01 -> 3551.16 | O8: =SUM(F8:N8) -> 447163.55 | AB8: =+O8 -> 447163.55
B9: A Alexander | C9: A Alexander | D9: 16072 | F9: =+D9*12 -> 192864 | G9: =+D9 -> 16072 | H9: 11000 | I9: =177.01*12 -> 2124.12 | J9: =+F9*(0.08+0.033) -> 21793.632 | K9: =+F9*0.01 -> 1928.64 | L9: 36 | M9: =172*12 -> 2064 | N9: =+F9*0.01 -> 1928.64 | O9: =SUM(F9:N9) -> 249811.03 | AB9: =+O9 -> 249811.03
C10: R Samodien | D10: 45000 | F10: =+D10*12 -> 540000 | G10: =+D10 -> 45000 | H10: 11000 | I10: =177.01*12 -> 2124.12 | J10: =+F10*(0.08+0.033) -> 61020 | K10: =+F10*0.01 -> 5400 | L10: 36 | M10: =172*12 -> 2064 | N10: =+F10*0.01 -> 5400 | O10: =SUM(F10:N10) -> 672044.12 | AB10: =+O10 -> 672044.12
A12: Stores Wage Staff | O12: Amnt per Hour
A13: W0000067 | B13: Sedick | C13: Stock Expeditor | D13: =VLOOKUP(A13,Sheet1!$A$81:$D$88,4,FALSE) -> 66.93
A14: W0000054 | B14: AdriaanMatthews | C14: Stores Assistan | D14: =VLOOKUP(A14,Sheet1!$A$81:$D$88,4,FALSE) -> 72.85
A15: W0000025 | B15: Young | C15: Receiving clerk | D15: =VLOOKUP(A15,Sheet1!$A$81:$D$88,4,FALSE) -> 75.43
A16: W0000057 | B16: BrandonSmith | C16: Stores Assistan | D16: =VLOOKUP(A16,Sheet1!$A$81:$D$88,4,FALSE) -> 66.93
A17: CON308A | B17: Duiker | C17: Leading Hand Stores | D17: =VLOOKUP(A17,Sheet1!$A$81:$D$88,4,FALSE) -> 109.2
A18: W0000004 | B18: Sampson Y | C18: Stores Assistant/Pic | D18: =VLOOKUP(A18,Sheet1!$A$81:$D$88,4,FALSE) -> 81.61
A19: W0000079 | B19: Links G | D19: =VLOOKUP(A19,Sheet1!$A$81:$D$88,4,FALSE) -> 66.93
A20: W0000078 | B20: Devito | C20: Stores Assistant/Pic | D20: =VLOOKUP(A20,Sheet1!$A$81:$D$88,4,FALSE) -> 66.93
D21: =SUM(D13:D20) -> 606.81 | O21: =+D21 -> 606.81 | Q21: =+O21*40*52 -> 1262164.8 | R21: =+Q21*0.0833 -> 105138.33 | S21: =+R21 -> 105138.33 | T21: =+Q21*0.01 -> 12621.648 | U21: =+Q21*0.083 -> 104759.68 | V21: =+Q21*0.0018 -> 2271.8966 | W21: =0.71*52 -> 36.92 | X21: =172*12 -> 2064 | Y21: =+(Q21+R21+S21)*0.01 -> 14724.415 | Z21: =SUM(Q21:Y21) -> 1608920 | AA21: 0.75 | AB21: =+Z21/AA21 -> 2145226.7
A22: Stores Salary Staff - PTA
A23: S710 | B23: PTA020 | C23: I MAKUA | D23: 21886 | F23: =+D23*12 -> 262632 | G23: =+D23 -> 21886 | H23: 15000 | I23: =+F23*0.01 -> 2626.32 | J23: =+F23*0.08 -> 21010.56 | K23: =+F23*0.01 -> 2626.32 | L23: 36 | M23: =172*12 -> 2064 | N23: =+F23*0.01 -> 2626.32 | O23: =SUM(F23:N23) -> 330507.52 | AB23: =+O23 -> 330507.52
AB24: =SUM(AB8:AB23) -> 3844752.9
A25: Maintenance
A26: Gerhard | B26: Mong | D26: 109
A27: Dwain | B27: Van Wyk | C27: Maintenance | D27: 66.93
D28: =SUM(D26:D27) -> 175.93 | N28: 1 | O28: =+D28 -> 175.93 | Q28: =+O28*40*52 -> 365934.4 | R28: =+Q28*0.0833 -> 30482.336 | S28: =+R28 -> 30482.336 | T28: =+Q28*0.01 -> 3659.344 | U28: =+Q28*0.083 -> 30372.555 | V28: =+Q28*0.0018 -> 658.68192 | W28: =0.71*52 -> 36.92 | X28: =172*12 -> 2064 | Y28: =+(Q28+R28+S28)*0.01 -> 4268.9907 | Z28: =SUM(Q28:Y28) -> 467959.56 | AA28: 1 | AB28: =+Z28/AA28 -> 467959.56
AB29: =SUM(AB26:AB28) -> 467959.56

Sheet Sheet1
A1: CON184A | B1: Puza G | C1: DAMPER | D1: 81.61 | E1: =VLOOKUP(A1,Wages!$A$2:$A$34,1,FALSE) -> CON184A
A2: CON389 | B2: Amos P | C2: DAMPER | D2: 89.52 | E2: =VLOOKUP(A2,Wages!$A$2:$A$34,1,FALSE) -> CON389
A3: CON469B | B3: Presence R | C3: DAMPER | D3: 87.84 | E3: =VLOOKUP(A3,Wages!$A$2:$A$34,1,FALSE) -> CON469B
A4: W0000022 | B4: Fortune D | C4: DAMPER | D4: 109.2 | E4: =VLOOKUP(A4,Wages!$A$2:$A$34,1,FALSE) -> W0000022
A5: W0000065 | B5: Lamb NM | C5: DAMPER | D5: 87.84 | E5: =VLOOKUP(A5,Wages!$A$2:$A$34,1,FALSE) -> W0000065
A6: W0000066 | B6: Adams TC | C6: DAMPER | D6: 72.85 | E6: =VLOOKUP(A6,Wages!$A$2:$A$34,1,FALSE) -> W0000066
A7: W0000083 | B7: Davids R | C7: DAMPER | D7: 72.85 | E7: =VLOOKUP(A7,Wages!$A$2:$A$34,1,FALSE) -> W0000083
A8: W0000084 | B8: Basson LC | C8: DAMPER | D8: 72.85 | E8: =VLOOKUP(A8,Wages!$A$2:$A$34,1,FALSE) -> W0000084
A10: CON049 | B10: Ontong S | C10: DESPATCH | D10: 111.14
A11: SWL004 | B11: Fredericks E | C11: DESPATCH | D11: 76.04
A12: W0000005 | B12: Karriem OM | C12: DESPATCH | D12: 75.43
A13: W0000017 | B13: Jaftha B | C13: DESPATCH | D13: 81.61
A14: W0000044 | B14: Manel B | C14: DESPATCH | D14: 81.61
A15: W0000052 | B15: Tlou PM | C15: DESPATCH | D15: 81.61
A16: W0000064 | B16: Yekele MCY | C16: DESPATCH | D16: 81.61
A17: W0000085 | B17: Mlaba S | C17: DESPATCH | D17: 66.93
A19: CON285 | B19: Skeyi N G | C19: PREPARATION | D19: 78.33 | E19: =VLOOKUP(A19,Wages!$A$51:$A$56,1,FALSE) -> CON285
A20: CON377B | B20: Dreyer S | C20: PREPARATION | D20: 78.33 | E20: =VLOOKUP(A20,Wages!$A$51:$A$56,1,FALSE) -> CON377B
A21: CON467B | B21: Morkel B | C21: PREPARATION | D21: 78.33 | E21: =VLOOKUP(A21,Wages!$A$51:$A$56,1,FALSE) -> CON467B
A22: CON529 | B22: Bailey G | C22: PREPARATION | D22: 75.43 | E22: =VLOOKUP(A22,Wages!$A$51:$A$56,1,FALSE) -> CON529
A23: W0000075 | B23: Davids Y | C23: PREPARATION | D23: 72.85 | E23: =VLOOKUP(A23,Wages!$A$51:$A$56,1,FALSE) -> W0000075
A25: CON459B | B25: Daniels G | C25: DIFFUSER | D25: 92.77 | E25: =VLOOKUP(A25,Wages!$A$60:$A$86,1,FALSE) -> CON459B
A26: CON466C | B26: Davids S | C26: DIFFUSER | D26: 81.61 | E26: =VLOOKUP(A26,Wages!$A$60:$A$86,1,FALSE) -> CON466C
A27: CON490B | B27: Geduld A | C27: DIFFUSER | D27: 78.33 | E27: =VLOOKUP(A27,Wages!$A$60:$A$86,1,FALSE) -> CON490B
A28: CON533 | B28: Isaacs R | C28: DIFFUSER | D28: 75.43 | E28: =VLOOKUP(A28,Wages!$A$60:$A$86,1,FALSE) -> CON533
A29: DIF032 | B29: Davids R | C29: DIFFUSER | D29: 111.14 | E29: =VLOOKUP(A29,Wages!$A$60:$A$86,1,FALSE) -> DIF032
A30: W0000007 | B30: Overmeyer J | C30: DIFFUSER | D30: 78.33 | E30: =VLOOKUP(A30,Wages!$A$60:$A$86,1,FALSE) -> W0000007
A31: W0000026 | B31: Smith E | C31: DIFFUSER | D31: 75.43 | E31: =VLOOKUP(A31,Wages!$A$60:$A$86,1,FALSE) -> W0000026
A32: W0000051 | B32: Tshehla S | C32: DIFFUSER | D32: 72.85 | E32: =VLOOKUP(A32,Wages!$A$60:$A$86,1,FALSE) -> W0000051
A33: W0000076 | B33: Ravens KC | C33: DIFFUSER | D33: 72.85 | E33: =VLOOKUP(A33,Wages!$A$60:$A$86,1,FALSE) -> W0000076
A34: W0000077 | B34: Manuel MY | C34: DIFFUSER | D34: 72.85 | E34: =VLOOKUP(A34,Wages!$A$60:$A$86,1,FALSE) -> W0000077
A38: W0000036 | B38: Nombewu L | C38: FLEX DUCTING DEPARTMENT | D38: 78.33
A39: W0000048 | B39: Isaacs RC | C39: FLEX DUCTING DEPARTMENT | D39: 75.43
A41: CON009J | B41: Davids E | C41: Injection Moulding Department | D41: 78.33
A42: CON393A | B42: Coakley R | C42: Injection Moulding Department | D42: 81.61
A44: W0000073 | B44: Mong GM | C44: Maintenance | D44: 109.2
A45: W0000074 | B45: Van Wyk DLM | C45: Maintenance | D45: 66.93
A47: MAN014 | B47: Bailey B | C47: MANUFACTURING | D47: 121.73 | E47: =VLOOKUP(A47,Wages!$A$98:$A$126,1,FALSE) -> MAN014
A48: W0000001 | B48: Blythe R | C48: MANUFACTURING | D48: 89.52 | E48: x
A49: W0000009 | B49: Sasman C | C49: MANUFACTURING | D49: 87.84 | E49: =VLOOKUP(A49,Wages!$A$98:$A$126,1,FALSE) -> W0000009
A50: W0000024 | B50: Ferguson D | C50: MANUFACTURING | D50: 89.52 | E50: =VLOOKUP(A50,Wages!$A$98:$A$126,1,FALSE) -> W0000024
A51: W0000030 | B51: Du Preez L | C51: MANUFACTURING | D51: 87.84 | E51: =VLOOKUP(A51,Wages!$A$98:$A$126,1,FALSE) -> W0000030
A52: W0000041 | B52: Weber L | C52: MANUFACTURING | D52: 92.77 | E52: =VLOOKUP(A52,Wages!$A$98:$A$126,1,FALSE) -> W0000041
A53: W0000047 | B53: Langa WB | C53: MANUFACTURING | D53: 87.84 | E53: x
A54: W0000080 | B54: Isaacs S | C54: MANUFACTURING | D54: 72.85 | E54: =VLOOKUP(A54,Wages!$A$98:$A$126,1,FALSE) -> W0000080
A55: W0000081 | B55: Africa CG | C55: MANUFACTURING | D55: 72.85 | E55: =VLOOKUP(A55,Wages!$A$98:$A$126,1,FALSE) -> W0000081
A56: W0000082 | B56: Domeyer V | C56: MANUFACTURING | D56: 72.85 | E56: =VLOOKUP(A56,Wages!$A$98:$A$126,1,FALSE) -> #N/A
A58: MAN120 | B58: Parenzee M | C58: Press Shop | D58: 89.89
A59: W0000016 | B59: Ray D | C59: Press Shop | D59: 109.2
A60: W0000027 | B60: Abrahams B | C60: Press Shop | D60: 81.61
A61: W0000049 | B61: Jacobs I | C61: Press Shop | D61: 72.85
A62: W0000053 | B62: De Kock G | C62: Press Shop | D62: 92.77
A64: POW172 | B64: Veenendaai J | C64: POWDER COATING | D64: 109.2 | E64: =VLOOKUP(A64,Wages!$A$162:$A$172,1,FALSE) -> #N/A
A65: W0000008 | B65: Adams J | C65: POWDER COATING | D65: 72.85 | E65: =VLOOKUP(A65,Wages!$A$162:$A$172,1,FALSE) -> W0000008
A66: W0000037 | B66: Africa S | C66: POWDER COATING | D66: 81.61 | E66: =VLOOKUP(A66,Wages!$A$162:$A$172,1,FALSE) -> W0000037
A67: W0000068 | B67: Schrickker GS | C67: POWDER COATING | D67: 69.66 | E67: =VLOOKUP(A67,Wages!$A$162:$A$172,1,FALSE) -> W0000068
A68: W0000069 | B68: Bouwers RB | C68: POWDER COATING | D68: 69.66 | E68: =VLOOKUP(A68,Wages!$A$162:$A$172,1,FALSE) -> W0000069
A69: W0000070 | B69: Harris LJ | C69: POWDER COATING | D69: 66.93 | E69: =VLOOKUP(A69,Wages!$A$162:$A$172,1,FALSE) -> W0000070
A70: W0000071 | B70: Arendse Z | C70: POWDER COATING | D70: 66.93 | E70: =VLOOKUP(A70,Wages!$A$162:$A$172,1,FALSE) -> W0000071
A71: W0000072 | B71: Pelston VG | C71: POWDER COATING | D71: 69.66 | E71: =VLOOKUP(A71,Wages!$A$162:$A$172,1,FALSE) -> W0000072
A72: W0000086 | B72: Van Dyk A J | C72: POWDER COATING | D72: 69.66 | E72: =VLOOKUP(A72,Wages!$A$162:$A$172,1,FALSE) -> #N/A
A73: W0000087 | B73: Mc White N | C73: POWDER COATING | D73: 69.66 | E73: =VLOOKUP(A73,Wages!$A$162:$A$172,1,FALSE) -> W0000087
A74: W0000088 | B74: Booysen RD | C74: POWDER COATING | D74: 69.66 | E74: =VLOOKUP(A74,Wages!$A$162:$A$172,1,FALSE) -> W0000088
A76: C000154C | B76: Mosoane M | C76: PRETORIA | D76: 66.93
A77: CON531 | B77: Wevers N | C77: QUALITY | D77: 78.33
A78: W0000018 | B78: Lodewyk L | C78: QUALITY | D78: 81.61
A79: POW161 | B79: Nortje P | C79: Sales | D79: 99.76
A81: CON308A | B81: Duiker R | C81: STORES | D81: 109.2 | E81: =VLOOKUP(A81,'Other Overhead'!$A$13:$A$20,1,FALSE) -> CON308A
A82: W0000004 | B82: Sampson Y | C82: STORES | D82: 81.61 | E82: =VLOOKUP(A82,'Other Overhead'!$A$13:$A$20,1,FALSE) -> W0000004
A83: W0000025 | B83: Young S | C83: STORES | D83: 75.43 | E83: =VLOOKUP(A83,'Other Overhead'!$A$13:$A$20,1,FALSE) -> W0000025
A84: W0000054 | B84: Matthews A | C84: STORES | D84: 72.85 | E84: =VLOOKUP(A84,'Other Overhead'!$A$13:$A$20,1,FALSE) -> W0000054
A85: W0000057 | B85: Smith B | C85: STORES | D85: 66.93 | E85: =VLOOKUP(A85,'Other Overhead'!$A$13:$A$20,1,FALSE) -> W0000057
A86: W0000067 | B86: Saban MS | C86: STORES | D86: 66.93 | E86: =VLOOKUP(A86,'Other Overhead'!$A$13:$A$20,1,FALSE) -> W0000067
A87: W0000078 | B87: Du Plessis D | C87: STORES | D87: 66.93 | E87: =VLOOKUP(A87,'Other Overhead'!$A$13:$A$20,1,FALSE) -> W0000078
A88: W0000079 | B88: Links G | C88: STORES | D88: 66.93 | E88: =VLOOKUP(A88,'Other Overhead'!$A$13:$A$20,1,FALSE) -> W0000079
A90: W0000062 | B90: Mahlangu MS | C90: TEA LADY | D90: 66.93
A91: W0000002 | B91: Persens V | C91: Temporary Powder coating | D91: 78.33

Sheet Data with Optional
J1: Ottery | K1: Lansdowne | L1: Workcentres
A2: CON426B | B2: Louis | C2: Hendricks | D2: 8709265154086 | E2: M | F2: C | G2: Damper Assemble | H2: DAMPER | I2: 51.98 | J2: X | L2: Cutting | M2: 0.8
L3: Brushing | M3: 0.1
L4: Notching | M4: 0.1
A6: W0000022 | B6: Dale | C6: Fortune | D6: 9305175138084 | E6: M | F6: C | G6: Damper Assemble | H6: DAMPER | I6: 51.98 | J6: X | L6: Damper Assembly | M6: 1
A7: CON463A | B7: Samir | C7: Mentin | D7: 9001085025087 | E7: M | F7: C | G7: Damper Final El | H7: DAMPER | I7: 54.33 | J7: X | L7: Damper Assembly | M7: 1
A9: CON389 | B9: Petula | C9: Amos | D9: 8208050797084 | E9: F | F9: C | G9: Damper Tester | H9: DAMPER | I9: 54.33 | J9: X | L9: Testing | M9: 0.75
L10: Damper Assembly | M10: 0.25
A12: CON422B | B12: Chadwinn | C12: Carelse | D12: 8612075150080 | E12: M | F12: C | G12: DampReturn Air | H12: DAMPER | I12: 51.98 | J12: X | L12: Grille Assembly
A14: CON263 | B14: Justin | C14: Van Buuren | D14: 8308165250084 | E14: M | F14: C | G14: Leading Hand/We | H14: DAMPER | I14: 58.58 | J14: X | L14: Damper Assembly | M14: 0.75
L15: Welding | M15: 0.25
A17: CON160A | B17: Mogamat Cassiem | C17: Trout | D17: 8209115126087 | E17: M | F17: C | G17: Supervisor | H17: DAMPER | I17: 75.93 | J17: X | L17: Damper Assembly | M17: 0.5
L18: Welding | M18: 0.5
A20: CON403 | B20: Shannon | C20: Baatjies | D20: 9112155437084 | E20: M | F20: C | G20: Welder | H20: DAMPER | I20: 58.58 | J20: X | L20: Cutting | M20: 1
A22: CON469B | B22: Reuben | C22: Presence | D22: 8101035211083 | E22: M | F22: C | G22: Welder | H22: DAMPER | I22: 58.58 | J22: X | L22: Damper Assembly | M22: 0.5
L23: Welding | M23: 0.5
A25: CON184A | B25: Goodman | C25: Puza | D25: 7407205477086 | E25: M | F25: A | G25: Welder/Assemble | H25: DAMPER | I25: 54.33 | J25: X | L25: Welding | M25: 0.75
L26: Damper Assembly | M26: 0.25
A27: Optional
B28: NEW | I28: 51.98 | L28: Grille Assembly
A32: CON182 | B32: Ismiel | C32: Karlie | D32: 5608015152080 | E32: M | F32: C | G32: Driver | H32: DESPATCH | I32: 49.67 | L32: Despatch
A33: CON446 | B33: Eugene | C33: Ruiters | D33: 7408095059083 | E33: M | F33: C | G33: Driver- Code 10 | H33: DESPATCH | I33: 54.33 | L33: Dispatch Ottery
A34: CON132B | B34: Carswell | C34: Soggop | D34: 7311105207082 | E34: M | F34: C | G34: Leading Hand/De | H34: DESPATCH | I34: 62.05 | J34: X | L34: Dispatch Ottery
A35: SWL004 | B35: Ebriham | C35: Fredericks | D35: 6508055160085 | E35: M | F35: C | G35: Packer | H35: DESPATCH | I35: 50.1 | J35: x | L35: Dispatch Ottery
A36: W0000017 | B36: Brandon | C36: Jafta | D36: 9405095267086 | E36: M | F36: C | G36: Packer | H36: DESPATCH | I36: 43.59 | K36: x | L36: Despatch
G37: NEW | H37: DESPATCH | I37: 45.43 | J37: x | L37: Dispatch Ottery
G38: NEW | H38: DESPATCH | I38: 45.43 | K38: x | L38: Despatch
A39: W0000010 | B39: Clayton | C39: Sylevester | D39: 8601085269089 | E39: M | F39: C | G39: Senior Despatch | H39: DESPATCH | I39: 54.33 | K39: x | L39: Despatch
A40: CON049 | B40: Sean | C40: Ontong | D40: 6810125129086 | E40: M | F40: C | G40: Supervisor | H40: DESPATCH | I40: 75.93
A42: Optional
B43: NEW | I43: 45.43 | L43: Despatch
B44: NEW | I44: 45.43 | L44: Dispatch Ottery
A47: CON529 | B47: Graham | C47: Bailey | D47: 8508215242086 | E47: M | F47: C | G47: Polyurethane As | H47: PREPARATION | I47: 49.67 | L47: Induction Channel Assembly | M47: 1
A48: W0000005 | B48: Omar | C48: Karriem | D48: 9007215058088 | E48: M | F48: C | G48: Polyurethane As | H48: PREPARATION | I48: 45.43 | L48: Induction Channel Assembly | M48: 1
A49: W0000009 | B49: Chadley | C49: Sasman | D49: 9503125107080 | E49: M | F49: C | G49: Polyurethane As | H49: PREPARATION | I49: 45.43 | L49: Induction Channel Assembly | M49: 1
A50: W0000020 | B50: Carlo | C50: Gie | D50: 7601095256085 | E50: M | F50: C | G50: Polyurethane As | H50: PREPARATION | I50: 45.43 | L50: Induction Channel Assembly | M50: 1
A52: CON533 | B52: Rashied | C52: Isaacs | D52: 9309085163083 | E52: M | F52: C | G52: Diffuser Assemb | H52: DIFFUSER | I52: 49.67 | L52: Constant Volume Diffuser Ass | M52: 1
A53: W0000026 | B53: Eugene | C53: Smith | D53: 7808305032087 | E53: M | F53: C | G53: Diffuser Assemb | H53: DIFFUSER | I53: 49.67 | L53: Constant Volume Diffuser Ass | M53: 1
A54: W0000002 | B54: Valentino | C54: Persens | D54: 8911175149087 | E54: M | F54: C | G54: Diffuser Assemb | H54: DIFFUSER | I54: 51.98 | L54: Diffuser Sub-Assembly | M54: 0.5
A56: CON009J | B56: Erefaan | C56: Davids | D56: 8204255128084 | E56: M | F56: C | G56: Diffuser Assemb | H56: DIFFUSER | I56: 51.98 | L56: Diffuser Sub-Assembly | M56: 0.5
L57: Diffuser Final Assembly | M57: 0.5
A58: CON398B | B58: Fabian | C58: Davids | D58: 9104025228082 | E58: M | F58: C | G58: Diffuser Assemb | H58: DIFFUSER | I58: 51.98 | L58: Diffuser Sub-Assembly | M58: 0.5
L59: Diffuser Final Assembly | M59: 0.5
A60: CON466C | B60: Saliem | C60: Davids | D60: 7109225322082 | E60: M | F60: C | G60: Diffuser Assemb | H60: DIFFUSER | I60: 54.33 | L60: Diffuser Sub-Assembly | M60: 0.5
L61: Diffuser Final Assembly | M61: 0.5
A62: CON490B | B62: Ashwin | C62: Geduld | D62: 9006255130088 | E62: M | F62: C | G62: Diffuser Assemb | H62: DIFFUSER | I62: 51.98 | L62: Diffuser Sub-Assembly | M62: 0.5
L63: Diffuser Final Assembly | M63: 0.5
A64: CON531 | B64: Nigel | C64: Wevers | D64: 8812285206082 | E64: M | F64: C | G64: Diffuser Assemb | H64: DIFFUSER | I64: 47.59 | L64: Diffuser Sub-Assembly | M64: 0.5
L65: Diffuser Final Assembly | M65: 0.5
A66: NIT213 | B66: Marwaan | C66: Johnson | D66: 8004295219087 | E66: M | F66: C | G66: Diffuser Assemb | H66: DIFFUSER | I66: 58.58 | L66: Diffuser Sub-Assembly | M66: 0.5
L67: Diffuser Final Assembly | M67: 0.5
A68: W0000003 | B68: Brendon | C68: Mulder | D68: 9105175248085 | E68: M | F68: C | G68: Diffuser Assemb | H68: DIFFUSER | I68: 47.59 | L68: Diffuser Sub-Assembly | M68: 0.5
L69: Diffuser Final Assembly | M69: 0.5
A70: W0000007 | B70: Jason | C70: Overmeyer | D70: 8411155166086 | E70: M | F70: C | G70: Diffuser Assemb | H70: DIFFUSER | I70: 51.98 | L70: Diffuser Sub-Assembly | M70: 0.5
L71: Diffuser Final Assembly | M71: 0.5
A73: CON393A | B73: Richard | C73: Coakley | D73: 8305125304084 | E73: M | F73: C | G73: Diffuser Assemb | H73: DIFFUSER | I73: 54.33 | L73: Testing | M73: 1
A75: CON459B | B75: Gary | C75: Daniels | D75: 9402145252085 | E75: M | F75: C | G75: Leading Hand | H75: DIFFUSER | I75: 59.77 | L75: Diffuser Sub-Assembly | M75: 0.5
L76: Diffuser Final Assembly | M76: 0.5
A77: DIF032 | B77: Rudewaan | C77: Davids | D77: 7712135184086 | E77: M | F77: C | G77: Supervisor | H77: DIFFUSER | I77: 75.93
C79: NEW | I79: 47.59 | L79: Diffuser Sub-Assembly | M79: 0.5
L80: Diffuser Final Assembly | M80: 0.5
B82: OPTIONAL
I83: 47.59 | L83: Diffuser Final Assembly
L84: Diffuser Sub-Assembly
I85: 47.59 | L85: Diffuser Final Assembly
L86: Diffuser Sub-Assembly
I87: 47.59 | L87: Diffuser Final Assembly
L88: Diffuser Sub-Assembly
I89: 47.59 | L89: Diffuser Final Assembly
L90: Diffuser Sub-Assembly
I91: 47.59 | L91: Diffuser Final Assembly
L92: Diffuser Sub-Assembly
I93: 47.59 | L93: Diffuser Final Assembly
L94: Diffuser Sub-Assembly
I95: 47.59 | L95: Diffuser Final Assembly
L96: Diffuser Sub-Assembly
I97: 47.59 | L97: Diffuser Final Assembly
L98: Diffuser Sub-Assembly
I100: 54.33 | L100: Testing
A104: W0000036 | B104: Lucky | C104: Nombewu | D104: 8502185467088 | E104: M | F104: C | G104: Flex Duct Opera | H104: FLEX DUCTING DEPARTMENT | I104: 49.67 | L104: DUCTING
A105: W0000016 | B105: Dino | C105: Ray | D105: 9305055185080 | E105: M | F105: C | G105: Flex Duct Sette | H105: FLEX DUCTING DEPARTMENT | I105: 59.77 | L105: DUCTING
A106: W0000032 | B106: Richard | C106: Lubbe | D106: 7602165230083 | E106: M | F106: C | G106: Powder Coater | H106: FLEX DUCTING DEPARTMENT | I106: 45.43 | L106: DUCTING
A107: CON435B | B107: Revano | C107: Abrahams | D107: 9310305124087 | E107: M | F107: C | G107: Powder Coater/W | H107: POWDER COATING | I107: 47.59 | L107: DUCTING
A109: Optional
D110: NEW | I110: 47.59
A113: CON510 | B113: Petrus | C113: Francis | D113: 5912075118084 | E113: M | F113: C | G113: Assembly | H113: Maintenance | I113: 43.59 | L113: Overhead
A114: W0000027 | B114: Brendon | C114: Abrahams | D114: 7801205429081 | E114: M | F114: C | G114: Maintenance | H114: Maintenance | I114: 43.59 | L114: Overhead
A115: W0000028 | B115: Leticia | C115: Thomas | D115: 8403040102087 | E115: F | F115: C | G115: Maintenance | H115: Maintenance | I115: 42.8 | L115: Overhead
A116: DIF041 | B116: Shafiek | C116: Brown | D116: 7710125080082 | E116: M | F116: C | G116: Supervisor | H116: Maintenance | I116: 59.87 | L116: Overhead
B117: NEW | I117: 43.59 | L117: Overhead
A121: W0000030 | B121: Leon | C121: Du Preez | D121: 7904145192080 | E121: M | F121: C | G121: All Rounder - M | H121: MANUFACTURING | I121: 47.59 | L121: Spot Welding | M121: 0.25
L122: Bending Brakes | M122: 0.25
L123: Rolling | M123: 0.25
L124: Beading | M124: 0.25
A125: W0000041 | B125: Lyle | C125: Weber | D125: 9204205250086 | E125: M | F125: C | G125: All Rounder - M | H125: MANUFACTURING | I125: 47.59 | L125: Spot Welding | M125: 0.25
L126: Bending Brakes | M126: 0.25
L127: Rolling | M127: 0.25
L128: Beading | M128: 0.25
A129: CON509 | B129: Ashley | C129: Lewin | D129: 8806285263085 | E129: M | F129: C | G129: Packer | H129: MANUFACTURING | I129: 47.59 | L129: Spot Welding | M129: 0.25
L130: Bending Brakes | M130: 0.25
...

Sheet Syspro
A1: WorkCentre | B1: Description | C1: RunTimeRate1 | D1: FixOverRate1 | E1: VarOverRate1 | F1: Total | G1: Column1
A2: 01PASS | B2: Pretoria Assembly | C2: 0 | D2: 0 | E2: 0 | F2: =SUM(C2:E2) -> 0
A3: 01PTA | B3: Pretoria Assembly | C3: 1.62 | D3: 3.48 | E3: 0.66 | F3: =SUM(C3:E3) -> 5.76
A4: 02PWET | B4: Pretoria Wet Spray | C4: 1.56 | D4: 0 | E4: 0.07 | F4: =SUM(C4:E4) -> 1.63
A5: 03PQC | B5: Pretoria Quality Check | C5: 0 | D5: 0 | E5: 0 | F5: =SUM(C5:E5) -> 0
A6: 05 | B6: Trumpf | C6: 3.58 | D6: 8.17 | E6: 3.9 | F6: =SUM(C6:E6) -> 15.65
A7: 09 | B7: Press Shop | C7: 0 | D7: 0 | E7: 0 | F7: =SUM(C7:E7) -> 0
A8: 12 | B8: Engineering | C8: 0 | D8: 0 | E8: 0 | F8: =SUM(C8:E8) -> 0
A9: 20 | B9: Subcontract Operations Lansdowne | C9: 0 | D9: 0 | E9: 0 | F9: =SUM(C9:E9) -> 0
A10: 25 | B10: Subcontract Operations Ottery | C10: 0 | D10: 0 | E10: 0 | F10: =SUM(C10:E10) -> 0
A11: A00001 | B11: Induction Channel Assembly | C11: 3.51 | D11: 0.71 | E11: 0.12 | F11: =SUM(C11:E11) -> 4.34
A12: A00002 | B12: Constant Volume Diffuser Ass | C12: 3.5 | D12: 0.99 | E12: 0.13 | F12: =SUM(C12:E12) -> 4.62
A13: A00003 | B13: Diffuser Sub-Assembly | C13: 3.42 | D13: 1.04 | E13: 0.15 | F13: =SUM(C13:E13) -> 4.61
... A27: D00006 | B27: Damper Assembly | C27: 3.47 | D27: 1.12 | E27: 0.29 | F27: =SUM(C27:E27) -> 4.88
A28: D00007 | B28: Testing | C28: 4.15 | D28: 1.76 | E28: 0.27 | F28: =SUM(C28:E28) -> 6.18 | G28: x
A29: D00008 | B29: Damper QC | C29: 2.5 | D29: 0.68 | E29: 0.2 | F29: =SUM(C29:E29) -> 3.38 | G29: x
A30: DELIVERY | B30: Delivery Cost | C30: 0 | D30: 0 | E30: 0 | F30: =SUM(C30:E30) -> 0 | G30: x
A31: F00001 | B31: Despatch | C31: 3.59 | D31: 0.9 | E31: 0.27 | F31: =SUM(C31:E31) -> 4.76 | G31: x
A32: INJ00001 | B32: Arburg 70Ton | C32: 1.53 | D32: 1.23 | E32: 0.81 | F32: =SUM(C32:E32) -> 3.57 | G32: x
A33: INJ00002 | B33: Arburg 25Ton | C33: 1.53 | D33: 1.22 | E33: 0.78 | F33: =SUM(C33:E33) -> 3.53 | G33: x
A34: INJ00003 | B34: Victor 90 Ton | C34: 1.53 | D34: 1.17 | E34: 0.76 | F34: =SUM(C34:E34) -> 3.46
A35: INJ0004 | B35: Injection Final Operations | C35: 1.53 | D35: 1.13 | E35: 0.58 | F35: =SUM(C35:E35) -> 3.24
A36: L00001 | B36: Laser Cutter | C36: 2.72 | D36: 4.45 | E36: 1.83 | F36: =SUM(C36:E36) -> 9
A37: LASER | B37: Laser Cut VLN Cam | C37: 0 | D37: 0 | E37: 0 | F37: =SUM(C37:E37) -> 0
A38: LHA | B38: Outwork LHA | C38: 0 | D38: 0 | E38: 0 | F38: =SUM(C38:E38) -> 0
A39: M00001 | B39: Bending Brakes Landsdowne | C39: 4.08 | D39: 1.28 | E39: 0.78 | F39: =SUM(C39:E39) -> 6.14
A40: M00002 | B40: Spot Welding Lansdowne | C40: 3.14 | D40: 0.86 | E40: 0.4 | F40: =SUM(C40:E40) -> 4.4
A41: M00003 | B41: Grinding Stations Lansdowne | C41: 2.78 | D41: 2.41 | E41: 0.53 | F41: =SUM(C41:E41) -> 5.72
A42: M00004 | B42: Notching Lansdowne | C42: 2.78 | D42: 0.8 | E42: 0.35 | F42: =SUM(C42:E42) -> 3.93
A43: M00006 | B43: Rolling Lansdowne | C43: 2.29 | D43: 0.76 | E43: 0.34 | F43: =SUM(C43:E43) -> 3.39
A44: M00007 | B44: BeadingLansdowne | C44: 4.07 | D44: 1.94 | E44: 0.6 | F44: =SUM(C44:E44) -> 6.61
A45: M00008 | B45: Mig Welding Lansdowne | C45: 3.92 | D45: 0.95 | E45: 0.34 | F45: =SUM(C45:E45) -> 5.21
... A48: M00099 | B48: Miscellaneous Lansdowne | C48: 2.89 | D48: 0.83 | E48: 0.37 | F48: =SUM(C48:E48) -> 4.09
A49: MACHI2 | B49: Machining of induction caps | C49: 0 | D49: 0 | E49: 0 | F49: =SUM(C49:E49) -> 0 | G49: x
A50: MACHIN | B50: Machining of Power Pills | C50: 0 | D50: 0 | E50: 0 | F50: =SUM(C50:E50) -> 0 | G50: x
A51: OUTWM | B51: Miscellaneos Outwork | C51: 0 | D51: 0 | E51: 0 | F51: =SUM(C51:E51) -> 0 | G51: x
A52: P00001 | B52: Chemical Treatment | C52: 4.42 | D52: 0.39 | E52: 0.21 | F52: =SUM(C52:E52) -> 5.02
A53: P00002 | B53: Powder Coating | C53: 18.3 | D53: 7.45 | E53: 7.43 | F53: =SUM(C53:E53) -> 33.18
A54: P00003 | B54: Wetspray | C54: 1.56 | D54: 0.2 | E54: 0.11 | F54: =SUM(C54:E54) -> 1.87
A55: P00004 | B55: Do not Use | C55: 0 | D55: 0 | E55: 0 | F55: =SUM(C55:E55) -> 0
A56: PCB | B56: Electronic Controls on Order | C56: 0 | D56: 0 | E56: 0 | F56: =SUM(C56:E56) -> 0
A57: POWD | B57: Sub Contract Powder Coating | C57: 0 | D57: 0 | E57: 0 | F57: =SUM(C57:E57) -> 0
A58: PRES01 | B58: Punch and Form Cone | C58: 0 | D58: 0 | E58: 0 | F58: =SUM(C58:E58) -> 0
A59: PRES20 | B59: Press Bell Mouth | C59: 0 | D59: 0 | E59: 0 | F59: =SUM(C59:E59) -> 0
A60: PRES30 | B60: Notch Tile to size | C60: 0 | D60: 0 | E60: 0 | F60: =SUM(C60:E60) -> 0
A61: PRES40 | B61: Spin VCD/VSW CDISC Cap | C61: 0 | D61: 0 | E61: 0 | F61: =SUM(C61:E61) -> 0
A62: PRES50 | B62: Press VLN Track bracket | C62: 0 | D62: 0 | E62: 0 | F62: =SUM(C62:E62) -> 0
A63: PRINT | B63: Screen Print Plastic Parts | C63: 0 | D63: 0 | E63: 0 | F63: =SUM(C63:E63) -> 0
A64: PS00001 | B64: Hydraulic Press | C64: 1.89 | D64: 2.79 | E64: 1.13 | F64: =SUM(C64:E64) -> 5.81
A65: PS00002 | B65: HME Press | C65: 2.31 | D65: 2.64 | E65: 0.97 | F65: =SUM(C65:E65) -> 5.92 | G65: x
A66: PS00003 | B66: Toss Press | C66: 2.31 | D66: 3.16 | E66: 1.5 | F66: =SUM(C66:E66) -> 6.97
A67: PS00004 | B67: Erfurt Press | C67: 1.89 | D67: 2.7 | E67: 1.03 | F67: =SUM(C67:E67) -> 5.62
A68: PS00005 | B68: Bending Brake Press Shop | C68: 4.08 | D68: 1.28 | E68: 0.78 | F68: =SUM(C68:E68) -> 6.14
A69: PS00006 | B69: Spot Welding Press Shop | C69: 3.14 | D69: 0.86 | E69: 0.4 | F69: =SUM(C69:E69) -> 4.4
A70: PS00007 | B70: Press Shop Grinding | C70: 2.78 | D70: 2.41 | E70: 0.53 | F70: =SUM(C70:E70) -> 5.72
A71: PS00008 | B71: Press Shop Notching | C71: 2.78 | D71: 0.8 | E71: 0.53 | F71: =SUM(C71:E71) -> 4.11
A72: PS00009 | B72: Press Shop Rolling | C72: 2.29 | D72: 0.76 | E72: 0.34 | F72: =SUM(C72:E72) -> 3.39
A73: PS00010 | B73: Press Shop Mig Welding | C73: 3.92 | D73: 0.95 | E73: 0.34 | F73: =SUM(C73:E73) -> 5.21
A74: PS00011 | B74: Press Shop Misc | C74: 2.89 | D74: 0.83 | E74: 0.37 | F74: =SUM(C74:E74) -> 4.09
A75: PS00012 | B75: Press Shop Mech Tech 50Ton | C75: 0 | D75: 0 | E75: 0 | F75: =SUM(C75:E75) -> 0
A76: PS00013 | B76: Press Shop Stud Welding | C76: 0 | D76: 0 | E76: 0 | F76: =SUM(C76:E76) -> 0
A77: PS00014 | B77: Cugini Press | C77: 0 | D77: 0 | E77: 0 | F77: =SUM(C77:E77) -> 0
... A90: WETS | B90: Wet Spray | C90: 0 | D90: 0 | E90: 0 | F90: =SUM(C90:E90) -> 0
A91: X00001 | B91: Flex Ducting | C91: 2.38 | D91: 1.87 | E91: 0.61 | F91: =SUM(C91:E91) -> 4.86 | G91: x
